Workbook

Sheet Legenda
A1: Technieken-analyse ecdsa.fail (secp256k1 point add), 26-10-2026
A2: Score = gemiddeld uitgevoerde Toffoli x piek-qubits. Leader 9ef3139: 741,645 x 1,234 = 915.2M.
A4: Bladen
A5: Gebruikt: 45 technieken uit alle oplossingen (154 inzendingsnotities gelezen + leader-broncode).
A6: Ongebruikt: 36 quantum-computing technieken die de leader niet gebruikt, incl. recent werk (2024-2026).
A7: Tekstboek: 35 methoden van 2-qubit-poorten tot 256-bit bouwstenen; kolom Opmerking zegt of ze in het nieuwe ontwerp zitten.
A8: Weging: extra eigenschappen + gewichtenmodel (gele cellen aanpasbaar); score per kandidaat is een formule.
A9: Gelijkheid: Gower-gelijkenis van elke kandidaat met elke gebruikte techniek (14 numerieke kenmerken, formules).
A10: Ontwerp: het nieuwe ontwerp zonder leader-constructies, opgebouwd uit primitieven (formules; blauwe cellen = invoer).
A11: Vergelijking: leader, Google (README), gepubliceerd, nieuwe varianten.
A12: Mijlpalen: alle stappen die >=1% van de beste score afhaalden.
A14: Kleuren
... A22: Het ontwerp is een kostenmodel, geen gebouwd circuit: het is niet door eval_circuit gevalideerd.

Sheet Gebruikt
A1: Technieken in alle ingediende oplossingen (inclusief leader)
A3: ID | B3: Techniek | C3: Categorie | D3: Vakgebied | E3: Jaar | F3: Bron | G3: Primair doel | H3: Vast aantal qubits nodig | I3: Extra qubits @256 (schatting) | J3: Ancilla-type | K3: Coherentie-eis (1-5) | L3: Verstrengeling met data nodig | M3: Mid-circuit meting | N3: Klassieke feedforward | O3: Exact / benaderd | P3: Foutkans | Q3: Toffoli-schaal | R3: Qubit-schaal | S3: Diepte-schaal | T3: Challenge-gateset ok | U3: Rotaties nodig | V3: Data-afhankelijk pad | W3: Uncompute-methode | X3: Vooraf berekende tabellen | Y3: Fase-risico | Z3: Complexiteit (1-5) | AA3: Volwassenheid (1-5) | AB3: T-effect op leader (%) | AC3: Q-effect op leader (qubits) | AD3: In leader | AE3: Elders gebruikt | AF3: Opmerking | AH3: f:vast | AI3: f:ancilla | AJ3: f:coherentie | AK3: f:verstrengeling | AL3: f:meting | AM3: f:feedforward | AN3: f:exact | AO3: f:gateset | AP3: f:rotaties | AQ3: f:data-afh | AR3: f:uncompute | AS3: f:tabellen | AT3: f:complexiteit | AU3: f:volwassenheid
A4: G01 | B4: Kaliski binary-GCD inversion (Roetteler two-Kaliski affine point-add) | C4: inversion/GCD | D4: mathematics | E4: 2026 | F4: ecdsa.fail baseline (pre-30c8ded) (challenge baseline, 2026-05-30) | G4: T+Q | H4: ja | I4: - | J4: schoon | K4: 3 | L4: nee | M4: ja | N4: nee | O4: exact | P4: 0 | Q4: O(n^2) | R4: O(n) | S4: O(n^2) | T4: ja | U4: nee | V4: ja | W4: Bennett | X4: nee | Y4: laag | Z4: 4 | AA4: 4 | AB4: - | AC4: - | AD4: nee | AE4: ja | AF4: Baseline: affine point add with two reversible Kaliski binary-GCD modular inversions holding explicit Bezout (r,s) registers. | effect: baseline 10,758,874,395 (derived) = ~3.96M T x 2715 Q; inverse ~79% of Toffoli per f94f726 | Named in f94f726/42d936f notes. Kaliski/dialog code absent from leader (grep). anupsv 1b4e026 tested a single batched inversion (c = dx^3*e) and found it net-negative (+256 peak). | AH4: =IF(H4="ja",1,0) -> 1 | AI4: =IF(J4="schoon",1,IF(J4="vuil",0.5,0)) -> 1 | AJ4: =K4/5 -> 0.6 | AK4: =IF(L4="ja",1,0) -> 0 | AL4: =IF(M4="ja",1,0) -> 1 | AM4: =IF(N4="ja",1,0) -> 0 | AN4: =IF(O4="exact",1,0) -> 1 | AO4: =IF(T4="ja",1,0) -> 1 | AP4: =IF(U4="ja",1,0) -> 0 | AQ4: =IF(V4="ja",1,0) -> 1 | AR4: =IF(W4="Bennett",1,IF(W4="meting",0.5,0)) -> 1 | AS4: =IF(X4="ja",1,0) -> 0 | AT4: =Z4/5 -> 0.8 | AU4: =AA4/5 -> 0.8
A5: G02 | B5: (r,s) cswap boundary merge | C5: scheduling/fusion | D5: computer science | E5: 2026 | F5: ecdsa.fail d35d6e7 (Gajesh2007, 2026-05-31) | G5: T | H5: nee | I5: - | J5: geen | K5: 2 | L5: nee | M5: nee | N5: nee | O5: exact | P5: 0 | Q5: - | R5: - | S5: - | T5: ja | U5: nee | V5: nee | W5: geen | X5: nee | Y5: laag | Z5: 3 | AA5: 3 | AB5: - | AC5: - | AD5: nee | AE5: ja | AF5: Fuse step9(k) and step3(k+1) Bezout conditional swaps across Kaliski iterations via cswap(a)*cswap(b)=cswap(a xor b) with a frame-parity qubit. | effect: -274k Toffoli, peak-neutral; -6.92% vs running best | Kaliski-era only. | AH5: =IF(H5="ja",1,0) -> 0 | AI5: =IF(J5="schoon",1,IF(J5="vuil",0.5,0)) -> 0 | AJ5: =K5/5 -> 0.4 | AK5: =IF(L5="ja",1,0) -> 0 | AL5: =IF(M5="ja",1,0) -> 0 | AM5: =IF(N5="ja",1,0) -> 0 | AN5: =IF(O5="exact",1,0) -> 1 | AO5: =IF(T5="ja",1,0) -> 1 | AP5: =IF(U5="ja",1,0) -> 0 | AQ5: =IF(V5="ja",1,0) -> 0 | AR5: =IF(W5="Bennett",1,IF(W5="meting",0.5,0)) -> 0 | AS5: =IF(X5="ja",1,0) -> 0 | AT5: =Z5/5 -> 0.6 | AU5: =AA5/5 -> 0.6
A6: G03 | B6: (u,v_w) cswap boundary merge on equality-free prefix | C6: scheduling/fusion | D6: computer science | E6: 2026 | F6: ecdsa.fail 112d5a4 (Gajesh2007, 2026-06-01) | G6: T | H6: nee | I6: - | J6: geen | K6: 2 | L6: nee | M6: nee | N6: nee | O6: exact | P6: 0 | Q6: - | R6: - | S6: - | T6: ja | U6: nee | V6: nee | W6: geen | X6: nee | Y6: laag | Z6: 3 | AA6: 3 | AB6: - | AC6: - | AD6: nee | AE6: ja | AF6: Same cswap-fusion identity applied to the GCD operand pair for an early safe prefix of iterations where u != v_w (comparison correction gt ^= frame valid). | effect: -7.19% vs running best (T 3.64M->3.36M at 2310 Q) | Safe-prefix length later extended (0a0a631: 254->255; d1d29eb 329->331) with reroll co-tuning. | AH6: =IF(H6="ja",1,0) -> 0 | AI6: =IF(J6="schoon",1,IF(J6="vuil",0.5,0)) -> 0 | AJ6: =K6/5 -> 0.4 | AK6: =IF(L6="ja",1,0) -> 0 | AL6: =IF(M6="ja",1,0) -> 0 | AM6: =IF(N6="ja",1,0) -> 0 | AN6: =IF(O6="exact",1,0) -> 1 | AO6: =IF(T6="ja",1,0) -> 1 | AP6: =IF(U6="ja",1,0) -> 0 | AQ6: =IF(V6="ja",1,0) -> 0 | AR6: =IF(W6="Bennett",1,IF(W6="meting",0.5,0)) -> 0 | AS6: =IF(X6="ja",1,0) -> 0 | AT6: =Z6/5 -> 0.6 | AU6: =AA6/5 -> 0.6
A7: G04 | B7: Carry/scratch hosting on provably-|0> or idle wires | C7: width/qubit management | D7: computer science | E7: 2026 | F7: ecdsa.fail f94f726 (Gajesh2007, 2026-05-31) | G7: Q | H7: nee | I7: - | J7: vuil | K7: 2 | L7: nee | M7: ja | N7: nee | O7: benaderd | P7: per shot (lambda) | Q7: O(1) | R7: - | S7: - | T7: ja | U7: nee | V7: nee | W7: meting | X7: nee | Y7: midden | Z7: 3 | AA7: 3 | AB7: - | AC7: - | AD7: deels | AE7: ja | AF7: Borrow adder carry lanes and history bits from registers proven zero at that instant (future history bits, shrinking high bits of u/v/s/r, idle transcript/future-log slots) instead of dedicated ancilla. | effect: f94f726: -126k T (late carry recovery) and peak 2459->2333 (9n floor); 0620443 C*/dialog-fold: peak 2309->2025; 744b274 host-gated: 1698->1572 (with windowed apply); 53cab17/40e10ac: 1466->1446; 62c8115 composite scratch: ->1355 | Merged family: late-iteration carry recovery, 9n carry-borrow, dialog history-fold into v_w high bits, C* carry-pool relocation (0620443), HOST_GATED/compos | AH7: =IF(H7="ja",1,0) -> 0 | AI7: =IF(J7="schoon",1,IF(J7="vuil",0.5,0)) -> 0.5 | AJ7: =K7/5 -> 0.4 | AK7: =IF(L7="ja",1,0) -> 0 | AL7: =IF(M7="ja",1,0) -> 1 | AM7: =IF(N7="ja",1,0) -> 0 | AN7: =IF(O7="exact",1,0) -> 0 | AO7: =IF(T7="ja",1,0) -> 1 | AP7: =IF(U7="ja",1,0) -> 0 | AQ7: =IF(V7="ja",1,0) -> 0 | AR7: =IF(W7="Bennett",1,IF(W7="meting",0.5,0)) -> 0.5 | AS7: =IF(X7="ja",1,0) -> 0 | AT7: =Z7/5 -> 0.6 | AU7: =AA7/5 -> 0.6
A8: G05 | B8: Joint-pin peak analysis / peak-owner tracing and qubit-cap retuning | C8: width/qubit management | D8: computer science | E8: 2026 | F8: ecdsa.fail f94f726 (Gajesh2007, 2026-05-31) | G8: Q | H8: nee | I8: - | J8: vuil | K8: 2 | L8: nee | M8: nee | N8: nee | O8: exact | P8: 0 | Q8: O(1) | R8: - | S8: - | T8: ja | U8: nee | V8: nee | W8: geen | X8: nee | Y8: midden | Z8: 3 | AA8: 3 | AB8: 0 | AC8: 0 | AD8: ja | AE8: ja | AF8: Treat the peak as a tie of several co-resident clusters, trace binders per phase, attack all together; later pin an explicit walk cap and retune cap vs reorder for the Q x T optimum. | effect: f94f726 plateau break 2708->2565->2459; c8f6ff0 measured cap 1263->1260; 6e00c30 cap 1239->1244 (+5 Q, -3.5k T) net -0.03% | Methodology plus knobs; break-even quoted as ~640-723 Toffoli per qubit at ~1.24k Q (6e00c30, 21a0ba3). Majority packing / cap-1234 retiming by mochimodev (a362dca) credited in 076f110, not read. | AH8: =IF(H8="ja",1,0) -> 0 | AI8: =IF(J8="schoon",1,IF(J8="vuil",0.5,0)) -> 0.5 | AJ8: =K8/5 -> 0.4 | AK8: =IF(L8="ja",1,0) -> 0 | AL8: =IF(M8="ja",1,0) -> 0 | AM8: =IF(N8="ja",1,0) -> 0 | AN8: =IF(O8="exact",1,0) -> 1 | AO8: =IF(T8="ja",1,0) -> 1 | AP8: =IF(U8="ja",1,0) -> 0 | AQ8: =IF(V8="ja",1,0) -> 0 | AR8: =IF(W8="Bennett",1,IF(W8="meting",0.5,0)) -> 0 | AS8: =IF(X8="ja",1,0) -> 0 | AT8: =Z8/5 -> 0.6 | AU8: =AA8/5 -> 0.6
A9: G06 | B9: Iteration / round-count trimming | C9: approximation | D9: statistics | E9: 2026 | F9: ecdsa.fail c8f4367 (mmurrs, 2026-05-31) | G9: T | H9: nee | I9: - | J9: geen | K9: 1 | L9: nee | M9: nee | N9: nee | O9: benaderd | P9: per shot (lambda) | Q9: - | R9: - | S9: - | T9: ja | U9: nee | V9: ja | W9: geen | X9: nee | Y9: laag | Z9: 2 | AA9: 3 | AB9: - | AC9: - | AD9: deels | AE9: ja | AF9: Lower the fixed number of GCD iterations/rounds/ticks to the empirical convergence tail, co-tuned with the test island. | effect: per step: e.g. 42d936f -14k T (pair2 401->397); 40e10ac ACTIVE 399->397 -4.3k T; ~3k T per step in 1153Q route (b87bdf7) | PR 419/mochimodev limiting contract (8186402) forbids pure round reductions as error-for-score trades; 02146ca deliberately ADDED 3 divsteps (258->261) to buy lambda. | AH9: =IF(H9="ja",1,0) -> 0 | AI9: =IF(J9="schoon",1,IF(J9="vuil",0.5,0)) -> 0 | AJ9: =K9/5 -> 0.2 | AK9: =IF(L9="ja",1,0) -> 0 | AL9: =IF(M9="ja",1,0) -> 0 | AM9: =IF(N9="ja",1,0) -> 0 | AN9: =IF(O9="exact",1,0) -> 0 | AO9: =IF(T9="ja",1,0) -> 1 | AP9: =IF(U9="ja",1,0) -> 0 | AQ9: =IF(V9="ja",1,0) -> 1 | AR9: =IF(W9="Bennett",1,IF(W9="meting",0.5,0)) -> 0 | AS9: =IF(X9="ja",1,0) -> 0 | AT9: =Z9/5 -> 0.4 | AU9: =AA9/5 -> 0.6
A10: G07 | B10: W-TRUNC empirical width-envelope truncation | C10: approximation | D10: statistics | E10: 2026 | F10: ecdsa.fail 437e22a (Gajesh2007, 2026-06-01) | G10: T | H10: nee | I10: - | J10: geen | K10: 1 | L10: nee | M10: nee | N10: nee | O10: benaderd | P10: per shot (lambda) | Q10: - | R10: - | S10: - | T10: ja | U10: nee | V10: ja | W10: geen | X10: nee | Y10: laag | Z10: 2 | AA10: 3 | AB10: 0 | AC10: 0 | AD10: ja | AE10: ja | AF10: Size each GCD-step width loop (OR chain, comparator, add/sub) to a fitted empirical bit-length envelope + margin instead of the provable worst case. | effect: -8.73% vs running best (T 3.36M->3.06M); margin/K0 retunes 70699b7 -1.56%, 4a11f65 -1.38%, 03499c8 -1.46%; dialog-era width margin/slope 37816e7 -1.31%, 730949a -1.14%, 64f75ba -1.80% | Family includes Kaliski W-TRUNC, dialog-GCD active-width margin/slope (08573bd), ping-pong SLOPE_2 (9dcbdb8), leapfrog joint 'peeling' envelope fit on 1.92M walks (53986ea). Failures surface as classical mismatches. | AH10: =IF(H10="ja",1,0) -> 0 | AI10: =IF(J10="schoon",1,IF(J10="vuil",0.5,0)) -> 0 | AJ10: =K10/5 -> 0.2 | AK10: =IF(L10="ja",1,0) -> 0 | AL10: =IF(M10="ja",1,0) -> 0 | AM10: =IF(N10="ja",1,0) -> 0 | AN10: =IF(O10="exact",1,0) -> 0 | AO10: =IF(T10="ja",1,0) -> 1 | AP10: =IF(U10="ja",1,0) -> 0 | AQ10: =IF(V10="ja",1,0) -> 1 | AR10: =IF(W10="Bennett",1,IF(W10="meting",0.5,0)) -> 0 | AS10: =IF(X10="ja",1,0) -> 0 | AT10: =Z10/5 -> 0.4 | AU10: =AA10/5 -> 0.6
A11: G08 | B11: Realizable-width truncation of conditional swaps | C11: approximation | D11: statistics | E11: 2026 | F11: ecdsa.fail 2ca410f (Gajesh2007, 2026-06-01) | G11: T | H11: nee | I11: - | J11: geen | K11: 1 | L11: nee | M11: nee | N11: nee | O11: benaderd | P11: per shot (lambda) | Q11: - | R11: - | S11: - | T11: ja | U11: nee | V11: ja | W11: geen | X11: nee | Y11: laag | Z11: 2 | AA11: 3 | AB11: - | AC11: - | AD11: nee | AE11: ja | AF11: Truncate the Kaliski STEP-3/9 (u,v_w) conditional swaps to the W-TRUNC width + margin instead of the invariant 2n-iter. | effect: -212,688 emitted CCX (-7.5%); -6.41% vs running best | cswaps were ~27% of Toffoli. Leapfrog's fixed alternating roles remove data-dependent swaps entirely. | AH11: =IF(H11="ja",1,0) -> 0 | AI11: =IF(J11="schoon",1,IF(J11="vuil",0.5,0)) -> 0 | AJ11: =K11/5 -> 0.2 | AK11: =IF(L11="ja",1,0) -> 0 | AL11: =IF(M11="ja",1,0) -> 0 | AM11: =IF(N11="ja",1,0) -> 0 | AN11: =IF(O11="exact",1,0) -> 0 | AO11: =IF(T11="ja",1,0) -> 1 | AP11: =IF(U11="ja",1,0) -> 0 | AQ11: =IF(V11="ja",1,0) -> 1 | AR11: =IF(W11="Bennett",1,IF(W11="meting",0.5,0)) -> 0 | AS11: =IF(X11="ja",1,0) -> 0 | AT11: =Z11/5 -> 0.4 | AU11: =AA11/5 -> 0.6
A12: G09 | B12: Carry-tail / fold-window truncation for the sparse constant f=2^32+977 | C12: approximation | D12: statistics | E12: 2026 | F12: ecdsa.fail 037fd71 (Gajesh2007, 2026-06-01) | G12: T | H12: nee | I12: - | J12: geen | K12: 1 | L12: nee | M12: ja | N12: nee | O12: benaderd | P12: per shot (lambda) | Q12: - | R12: - | S12: - | T12: ja | U12: nee | V12: ja | W12: meting | X12: nee | Y12: laag | Z12: 2 | AA12: 3 | AB12: 0 | AC12: 0 | AD12: ja | AE12: ja | AF12: In +-c constant adders and pseudo-Mersenne folds, cut the carry/borrow ripple a window W above bit 32; propagation beyond has probability ~2^-W. | effect: -2.04% vs running best (037fd71); W 96->59 f751e0b -0.49%; DIRECT_CONST_DOUBLE routing 375fdff -3.32%; apply-phase double/halve trunc 66ad478 (-152,520 T) | solimander 22bae60 found it unsound for the dense constant p+1 and added a constant-aware window. 375fdff routed mod_double through the register-free direct const-add so truncation applies. 21a0ba3 argues ENDPOINT_FOLD_WINDOW 54->40 is 'provably lambda-free' (~2^-40). | AH12: =IF(H12="ja",1,0) -> 0 | AI12: =IF(J12="schoon",1,IF(J12="vuil",0.5,0)) -> 0 | AJ12: =K12/5 -> 0.2 | AK12: =IF(L12="ja",1,0) -> 0 | AL12: =IF(M12="ja",1,0) -> 1 | AM12: =IF(N12="ja",1,0) -> 0 | AN12: =IF(O12="exact",1,0) -> 0 | AO12: =IF(T12="ja",1,0) -> 1 | AP12: =IF(U12="ja",1,0) -> 0 | AQ12: =IF(V12="ja",1,0) -> 1 | AR12: =IF(W12="Bennett",1,IF(W12="meting",0.5,0)) -> 0.5 | AS12: =IF(X12="ja",1,0) -> 0 | AT12: =Z12/5 -> 0.4 | AU12: =AA12/5 -> 0.6
A13: G10 | B13: Correction-free doubling for small r (R_SMALL threshold) | C13: reduction | D13: mathematics | E13: 2026 | F13: ecdsa.fail 42d936f (bxue-l2, 2026-06-01) | G13: T | H13: ja | I13: - | J13: schoon | K13: 2 | L13: nee | M13: nee | N13: nee | O13: benaderd | P13: per shot (lambda) | Q13: O(n) | R13: O(n) | S13: O(n) | T13: ja | U13: nee | V13: nee | W13: Bennett | X13: ja | Y13: laag | Z13: 3 | AA13: 4 | AB13: - | AC13: - | AD13: nee | AE13: ja | AF13: In early Kaliski iterations where r is provably/empirically small, replace mod_double(r) by a plain shift (no reduction). | effect: ~255 CCX per affected iteration (ea4f6e0); mostly used as a re-roll knob | Pre-existing in the tree when first mentioned (R_SMALL_THRESHOLD=326); origin not read. Kaliski-era only. | AH13: =IF(H13="ja",1,0) -> 1 | AI13: =IF(J13="schoon",1,IF(J13="vuil",0.5,0)) -> 1 | AJ13: =K13/5 -> 0.4 | AK13: =IF(L13="ja",1,0) -> 0 | AL13: =IF(M13="ja",1,0) -> 0 | AM13: =IF(N13="ja",1,0) -> 0 | AN13: =IF(O13="exact",1,0) -> 0 | AO13: =IF(T13="ja",1,0) -> 1 | AP13: =IF(U13="ja",1,0) -> 0 | AQ13: =IF(V13="ja",1,0) -> 0 | AR13: =IF(W13="Bennett",1,IF(W13="meting",0.5,0)) -> 1 | AS13: =IF(X13="ja",1,0) -> 1 | AT13: =Z13/5 -> 0.6 | AU13: =AA13/5 -> 0.8
A14: G11 | B14: Fiat-Shamir reroll / identity-tail nonce island selection | C14: validation/nonce | D14: cryptography | E14: 2026 | F14: ecdsa.fail 0ae959c (Epistetechnician, 2026-06-02) | G14: geen | H14: nee | I14: - | J14: geen | K14: 1 | L14: nee | M14: nee | N14: nee | O14: benaderd | P14: per shot (lambda) | Q14: - | R14: - | S14: - | T14: ja | U14: nee | V14: nee | W14: geen | X14: nee | Y14: laag | Z14: 2 | AA14: 3 | AB14: 0 | AC14: 0 | AD14: ja | AE14: ja | AF14: Append identity X;X pairs whose targets encode a nonce; this changes the SHAKE256 hash of the op stream and so re-draws the 9,024 test inputs without changing the circuit. Pick a nonce on which every shot passes. | effect: no direct T/Q change; enables every truncation. Nonce also moves avg executed T by ~10-15k band (b5fa90f, 7bb8713) | First seen as KAL_REROLL (0ae959c; Gajesh 2a05eae and 08573bd describe the 'island lottery'). Fixed-length 96-op tail with prefix-hash reuse introduced by stevenhao f026481 (2026-06-04); compact base-1024 tail by swadhin 6f8aba7. jtrose24 f1acd7f flags the int | AH14: =IF(H14="ja",1,0) -> 0 | AI14: =IF(J14="schoon",1,IF(J14="vuil",0.5,0)) -> 0 | AJ14: =K14/5 -> 0.2 | AK14: =IF(L14="ja",1,0) -> 0 | AL14: =IF(M14="ja",1,0) -> 0 | AM14: =IF(N14="ja",1,0) -> 0 | AN14: =IF(O14="exact",1,0) -> 0 | AO14: =IF(T14="ja",1,0) -> 1 | AP14: =IF(U14="ja",1,0) -> 0 | AQ14: =IF(V14="ja",1,0) -> 0 | AR14: =IF(W14="Bennett",1,IF(W14="meting",0.5,0)) -> 0 | AS14: =IF(X14="ja",1,0) -> 0 | AT14: =Z14/5 -> 0.4 | AU14: =AA14/5 -> 0.6
A15: G12 | B15: Classical prefilter + GPU nonce search pipeline | C15: validation/nonce | D15: cryptography | E15: 2026 | F15: ecdsa.fail 823b7cf (zuiris, 2026-06-05) | G15: geen | H15: nee | I15: - | J15: geen | K15: 1 | L15: nee | M15: nee | N15: nee | O15: exact | P15: 0 | Q15: - | R15: - | S15: - | T15: ja | U15: nee | V15: nee | W15: geen | X15: nee | Y15: laag | Z15: 2 | AA15: 3 | AB15: - | AC15: - | AD15: nee | AE15: ja | AF15: Bit-exact classical replay of the GCD/walk (and later phase-repair sites) on candidate nonces, GPU-parallel, with survivors confirmed by the trusted 9,024-shot evaluator. | effect: search cost only; e.g. 9e1ab6a scanned 2.3e10 seeds on ~28 RTX 4090s; 6e00c30 expects ~1.2e8 nonces at lambda 18.6 | External tooling, not in src/point_add. Jieyi Long's public ecdsafail_gpu_toolkit credited from ca5f0c3 onward. Input derivation reimplemented with Jacobian + comb + Montgomery batch inversion. | AH15: =IF(H15="ja",1,0) -> 0 | AI15: =IF(J15="schoon",1,IF(J15="vuil",0.5,0)) -> 0 | AJ15: =K15/5 -> 0.2 | AK15: =IF(L15="ja",1,0) -> 0 | AL15: =IF(M15="ja",1,0) -> 0 | AM15: =IF(N15="ja",1,0) -> 0 | AN15: =IF(O15="exact",1,0) -> 1 | AO15: =IF(T15="ja",1,0) -> 1 | AP15: =IF(U15="ja",1,0) -> 0 | AQ15: =IF(V15="ja",1,0) -> 0 | AR15: =IF(W15="Bennett",1,IF(W15="meting",0.5,0)) -> 0 | AS15: =IF(X15="ja",1,0) -> 0 | AT15: =Z15/5 -> 0.4 | AU15: =AA15/5 -> 0.6
A16: G13 | B16: Lambda budget economics and limiting contract | C16: validation/nonce | D16: cryptography | E16: 2026 | F16: ecdsa.fail 02146ca (Gajesh2007, 2026-07-26) | G16: geen | H16: nee | I16: - | J16: geen | K16: 1 | L16: nee | M16: nee | N16: nee | O16: exact | P16: 0 | Q16: - | R16: - | S16: - | T16: ja | U16: nee | V16: nee | W16: geen | X16: nee | Y16: laag | Z16: 2 | AA16: 3 | AB16: - | AC16: - | AD16: deels | AE16: ja | AF16: Model failing shots per 9,024 as Poisson lambda (classical + phase); minimise score subject to lambda being grindable; buy lambda back with exact cuts and spend it where Toffoli-per-lambda is highest. | effect: 02146ca measured head lambda_total=23.29, P(clean)=7.7e-11; 9dcbdb8 trade table (ROUNDS_MUL -6 vs -2: 10.6x hunt cost); contract caps lambda at 18, later 19.5 | Methodology, not a gate-level technique. Social rule introduced with PR 419 (8186402, mochimodev, 2026-09-25): lambda<=18 on 9,024 shots, no direct error-for-score trades; later raised to 19.5 after Telegram discussion. | AH16: =IF(H16="ja",1,0) -> 0 | AI16: =IF(J16="schoon",1,IF(J16="vuil",0.5,0)) -> 0 | AJ16: =K16/5 -> 0.2 | AK16: =IF(L16="ja",1,0) -> 0 | AL16: =IF(M16="ja",1,0) -> 0 | AM16: =IF(N16="ja",1,0) -> 0 | AN16: =IF(O16="exact",1,0) -> 1 | AO16: =IF(T16="ja",1,0) -> 1 | AP16: =IF(U16="ja",1,0) -> 0 | AQ16: =IF(V16="ja",1,0) -> 0 | AR16: =IF(W16="Bennett",1,IF(W16="meting",0.5,0)) -> 0 | AS16: =IF(X16="ja",1,0) -> 0 | AT16: =Z16/5 -> 0.4 | AU16: =AA16/5 -> 0.6
A17: G14 | B17: Measurement-based uncomputation (Gidney HMR + classically-controlled CZ) | C17: uncomputation | D17: physics | E17: 2026 | F17: ecdsa.fail c8f4367 (mmurrs, 2026-05-31) | G17: T | H17: nee | I17: - | J17: geen | K17: 1 | L17: nee | M17: ja | N17: ja | O17: exact | P17: 0 | Q17: O(n) | R17: O(1) | S17: O(n) | T17: ja | U17: nee | V17: nee | W17: meting | X17: nee | Y17: hoog | Z17: 3 | AA17: 4 | AB17: 0 | AC17: 0 | AD17: ja | AE17: ja | AF17: Uncompute AND ancillas and adder carry lanes by X-basis measurement plus a measurement-conditioned phase fix (0 Toffoli) instead of a mirrored Toffoli sweep. | effect: 75927ba comparator -209,520 T (-7.21%); df59687 sub-clear + comparator fast-eval (-6.27%); 1f7aabe apply sub -102k T (-4.90%); 690bdb9/8ee9ad8 -23.9k T each | c8f4367 already uses a 'measurement-uncomputed fast Cuccaro' path; origin earlier than read notes. Value-exact; failures only if phase fix is wrong. | AH17: =IF(H17="ja",1,0) -> 0 | AI17: =IF(J17="schoon",1,IF(J17="vuil",0.5,0)) -> 0 | AJ17: =K17/5 -> 0.2 | AK17: =IF(L17="ja",1,0) -> 0 | AL17: =IF(M17="ja",1,0) -> 1 | AM17: =IF(N17="ja",1,0) -> 1 | AN17: =IF(O17="exact",1,0) -> 1 | AO17: =IF(T17="ja",1,0) -> 1 | AP17: =IF(U17="ja",1,0) -> 0 | AQ17: =IF(V17="ja",1,0) -> 0 | AR17: =IF(W17="Bennett",1,IF(W17="meting",0.5,0)) -> 0.5 | AS17: =IF(X17="ja",1,0) -> 0 | AT17: =Z17/5 -> 0.6 | AU17: =AA17/5 -> 0.8
A18: G15 | B18: Dialog-GCD: record-and-replay transcript instead of Bezout registers | C18: inversion/GCD | D18: mathematics | E18: 2026 | F18: ecdsa.fail 0c1d4d9 (pldallairedemers, 2026-06-02) | G18: T+Q | H18: ja | I18: - | J18: schoon | K18: 3 | L18: nee | M18: ja | N18: nee | O18: exact | P18: 0 | Q18: O(n^2) | R18: O(n) | S18: O(n^2) | T18: ja | U18: nee | V18: ja | W18: Bennett | X18: nee | Y18: laag | Z18: 4 | AA18: 4 | AB18: - | AC18: - | AD18: deels | AE18: ja | AF18: Run the binary GCD forward recording per-step branch decisions in a sidecar log, replay the log to apply the quotient to the payload, then reverse; no explicit (r,s) cofactor registers. | effect: -18.83% vs running best; peak 2006->1698, T 2.55M->2.45M | Ported 'TensorFurnace' framework (note is short). Lineage: dialog-GCD -> K=2 jump -> trailmix -> ping-pong -> Skywalk -> Leapfrog all record a transcript and replay it on the payload. | AH18: =IF(H18="ja",1,0) -> 1 | AI18: =IF(J18="schoon",1,IF(J18="vuil",0.5,0)) -> 1 | AJ18: =K18/5 -> 0.6 | AK18: =IF(L18="ja",1,0) -> 0 | AL18: =IF(M18="ja",1,0) -> 1 | AM18: =IF(N18="ja",1,0) -> 0 | AN18: =IF(O18="exact",1,0) -> 1 | AO18: =IF(T18="ja",1,0) -> 1 | AP18: =IF(U18="ja",1,0) -> 0 | AQ18: =IF(V18="ja",1,0) -> 1 | AR18: =IF(W18="Bennett",1,IF(W18="meting",0.5,0)) -> 1 | AS18: =IF(X18="ja",1,0) -> 0 | AT18: =Z18/5 -> 0.8 | AU18: =AA18/5 -> 0.8
A19: G16 | B19: Transcript compression codecs | C19: encoding/transcript | D19: information theory | E19: 2026 | F19: ecdsa.fail 0c1d4d9 (pldallairedemers, 2026-06-02) | G19: Q | H19: ja | I19: - | J19: schoon | K19: 2 | L19: nee | M19: nee | N19: nee | O19: exact | P19: 0 | Q19: O(n) | R19: O(n) | S19: O(n) | T19: ja | U19: nee | V19: ja | W19: Bennett | X19: nee | Y19: laag | Z19: 3 | AA19: 3 | AB19: - | AC19: - | AD19: deels | AE19: ja | AF19: Pack the GCD decision transcript below 1 qubit per raw bit using reachability constraints (compressed sidecar blocks, K2 pair 6->5 bits, base-5 triples 9->7 bits, Skywalk ternary 5 steps in 8 qubits, SAT-synthesized in-place pairs core). | effect: 351373f K2 pair compressor: drops to 1313 Q tier; af5abb1 tob-joe: resident tape 603q vs ~775 raw | Inline/streamed compression so the raw tape never exists (af5abb1). | AH19: =IF(H19="ja",1,0) -> 1 | AI19: =IF(J19="schoon",1,IF(J19="vuil",0.5,0)) -> 1 | AJ19: =K19/5 -> 0.4 | AK19: =IF(L19="ja",1,0) -> 0 | AL19: =IF(M19="ja",1,0) -> 0 | AM19: =IF(N19="ja",1,0) -> 0 | AN19: =IF(O19="exact",1,0) -> 1 | AO19: =IF(T19="ja",1,0) -> 1 | AP19: =IF(U19="ja",1,0) -> 0 | AQ19: =IF(V19="ja",1,0) -> 1 | AR19: =IF(W19="Bennett",1,IF(W19="meting",0.5,0)) -> 1 | AS19: =IF(X19="ja",1,0) -> 0 | AT19: =Z19/5 -> 0.6 | AU19: =AA19/5 -> 0.6
A20: G17 | B20: Truncated top-window comparators | C20: approximation | D20: statistics | E20: 2026 | F20: ecdsa.fail 0c1d4d9 (pldallairedemers, 2026-06-02) | G20: T | H20: nee | I20: - | J20: geen | K20: 1 | L20: nee | M20: nee | N20: nee | O20: benaderd | P20: per shot (lambda) | Q20: - | R20: - | S20: - | T20: ja | U20: nee | V20: ja | W20: geen | X20: nee | Y20: laag | Z20: 2 | AA20: 3 | AB20: 0 | AC20: 0 | AD20: ja | AE20: ja | AF20: Decide branch (u>v), flag and chunk-boundary predicates using only the top k bits of the active window, with per-step schedules. | effect: 4ac4a16 72->68 (~20k T); f1acd7f 75->63 (-1.48%); 66ad478 per-step schedule (-5,384 T); leapfrog W1 24->18 bits (a02c716) | Many single-bit retunes (COMPARE_BITS 59..44, APPLY_CLEAN 22..18, REPLAY_CHUNK_COMPARE 26->21) are the same family. | AH20: =IF(H20="ja",1,0) -> 0 | AI20: =IF(J20="schoon",1,IF(J20="vuil",0.5,0)) -> 0 | AJ20: =K20/5 -> 0.2 | AK20: =IF(L20="ja",1,0) -> 0 | AL20: =IF(M20="ja",1,0) -> 0 | AM20: =IF(N20="ja",1,0) -> 0 | AN20: =IF(O20="exact",1,0) -> 0 | AO20: =IF(T20="ja",1,0) -> 1 | AP20: =IF(U20="ja",1,0) -> 0 | AQ20: =IF(V20="ja",1,0) -> 1 | AR20: =IF(W20="Bennett",1,IF(W20="meting",0.5,0)) -> 0 | AS20: =IF(X20="ja",1,0) -> 0 | AT20: =Z20/5 -> 0.4 | AU20: =AA20/5 -> 0.6
A21: G18 | B21: Fused branch-bit comparator | C21: scheduling/fusion | D21: computer science | E21: 2026 | F21: ecdsa.fail fd70a60 (Epistetechnician, 2026-06-02) | G21: T | H21: nee | I21: - | J21: geen | K21: 2 | L21: nee | M21: nee | N21: nee | O21: exact | P21: 0 | Q21: - | R21: - | S21: - | T21: ja | U21: nee | V21: nee | W21: geen | X21: nee | Y21: laag | Z21: 3 | AA21: 3 | AB21: - | AC21: - | AD21: nee | AE21: ja | AF21: Emit b0 AND b1 directly under the control from the in-flight comparator carry, avoiding an intermediate compare qubit and its uncompute. | effect: -3.32% vs running best (T 1.93M->1.86M) | f2cd713 later hosted this comparator's carry lane on future-log slots (peak 1500->1466). | AH21: =IF(H21="ja",1,0) -> 0 | AI21: =IF(J21="schoon",1,IF(J21="vuil",0.5,0)) -> 0 | AJ21: =K21/5 -> 0.4 | AK21: =IF(L21="ja",1,0) -> 0 | AL21: =IF(M21="ja",1,0) -> 0 | AM21: =IF(N21="ja",1,0) -> 0 | AN21: =IF(O21="exact",1,0) -> 1 | AO21: =IF(T21="ja",1,0) -> 1 | AP21: =IF(U21="ja",1,0) -> 0 | AQ21: =IF(V21="ja",1,0) -> 0 | AR21: =IF(W21="Bennett",1,IF(W21="meting",0.5,0)) -> 0 | AS21: =IF(X21="ja",1,0) -> 0 | AT21: =Z21/5 -> 0.6 | AU21: =AA21/5 -> 0.6
A22: G19 | B22: Chunked/windowed adders with measured boundary-carry erasure | C22: adder | D22: computer science | E22: 2026 | F22: ecdsa.fail 744b274 (saucegodbased, 2026-06-02) | G22: T | H22: ja | I22: - | J22: schoon | K22: 2 | L22: nee | M22: ja | N22: nee | O22: benaderd | P22: per shot (lambda) | Q22: O(n) | R22: O(n) | S22: O(n) | T22: ja | U22: nee | V22: nee | W22: meting | X22: nee | Y22: laag | Z22: 2 | AA22: 5 | AB22: 0 | AC22: 0 | AD22: ja | AE22: ja | AF22: Split a wide ripple add into blocks so the full carry lane never coexists with other wide registers; clear each block-boundary carry by HMR plus a (truncated) comparator repair. | effect: 744b274: peak 1698->1572 (+102k T); 3bd3aa5 chunked f-materialization -3.09%; 67be862 apply teardown 1382->1320 Q | Boundary repair compares are a truncation (2^-k per boundary, k~21-25). Later refinements: lazy carry-out allocation and eager boundary erasure (21a0ba3), budgeted chunk count per round (bc7a792). | AH22: =IF(H22="ja",1,0) -> 1 | AI22: =IF(J22="schoon",1,IF(J22="vuil",0.5,0)) -> 1 | AJ22: =K22/5 -> 0.4 | AK22: =IF(L22="ja",1,0) -> 0 | AL22: =IF(M22="ja",1,0) -> 1 | AM22: =IF(N22="ja",1,0) -> 0 | AN22: =IF(O22="exact",1,0) -> 0 | AO22: =IF(T22="ja",1,0) -> 1 | AP22: =IF(U22="ja",1,0) -> 0 | AQ22: =IF(V22="ja",1,0) -> 0 | AR22: =IF(W22="Bennett",1,IF(W22="meting",0.5,0)) -> 0.5 | AS22: =IF(X22="ja",1,0) -> 0 | AT22: =Z22/5 -> 0.4 | AU22: =AA22/5 -> 1
A23: G20 | B23: Odd low-bit / parked constant bit 0 | C23: width/qubit management | D23: computer science | E23: 2026 | F23: ecdsa.fail 73f81cc (Epistetechnician, 2026-06-02) | G23: Q | H23: nee | I23: - | J23: vuil | K23: 2 | L23: nee | M23: nee | N23: nee | O23: exact | P23: 0 | Q23: O(1) | R23: - | S23: - | T23: ja | U23: nee | V23: nee | W23: geen | X23: nee | Y23: midden | Z23: 3 | AA23: 3 | AB23: 0 | AC23: 0 | AD23: ja | AE23: ja | AF23: Odd operands have bit 0 = 1 on the reachable path: replace CCX by CX on lane 0, skip lane-0 swaps, and later park bit 0 off-register for the whole walk. | effect: ~-3,192 T (b54d856); c8f6ff0 parked bit 0: -274 executed T; frees 2 walk wires | Exact on the reachable support. | AH23: =IF(H23="ja",1,0) -> 0 | AI23: =IF(J23="schoon",1,IF(J23="vuil",0.5,0)) -> 0.5 | AJ23: =K23/5 -> 0.4 | AK23: =IF(L23="ja",1,0) -> 0 | AL23: =IF(M23="ja",1,0) -> 0 | AM23: =IF(N23="ja",1,0) -> 0 | AN23: =IF(O23="exact",1,0) -> 1 | AO23: =IF(T23="ja",1,0) -> 1 | AP23: =IF(U23="ja",1,0) -> 0 | AQ23: =IF(V23="ja",1,0) -> 0 | AR23: =IF(W23="Bennett",1,IF(W23="meting",0.5,0)) -> 0 | AS23: =IF(X23="ja",1,0) -> 0 | AT23: =Z23/5 -> 0.6 | AU23: =AA23/5 -> 0.6
A24: G21 | B24: Affine square-recompute and lambda^2 lifetime shortening | C24: width/qubit management | D24: computer science | E24: 2026 | F24: ecdsa.fail f94f726 (Gajesh2007, 2026-05-31) | G24: Q | H24: nee | I24: - | J24: vuil | K24: 2 | L24: nee | M24: nee | N24: nee | O24: exact | P24: 0 | Q24: O(1) | R24: - | S24: - | T24: ja | U24: nee | V24: nee | W24: geen | X24: nee | Y24: midden | Z24: 3 | AA24: 3 | AB24: - | AC24: - | AD24: nee | AE24: ja | AF24: Early-uncompute the 512-bit lambda^2 product, run the y-multiply without it, recompute once to clear; and free the dead square temp at the fused affine instant. | effect: f94f726 affine low-scratch 2565->2459; 0620443 AFFINE_SQUARE_RECOMPUTE part of 2309->2025 | Pays one extra symmetric-square pair for the qubit saving. | AH24: =IF(H24="ja",1,0) -> 0 | AI24: =IF(J24="schoon",1,IF(J24="vuil",0.5,0)) -> 0.5 | AJ24: =K24/5 -> 0.4 | AK24: =IF(L24="ja",1,0) -> 0 | AL24: =IF(M24="ja",1,0) -> 0 | AM24: =IF(N24="ja",1,0) -> 0 | AN24: =IF(O24="exact",1,0) -> 1 | AO24: =IF(T24="ja",1,0) -> 1 | AP24: =IF(U24="ja",1,0) -> 0 | AQ24: =IF(V24="ja",1,0) -> 0 | AR24: =IF(W24="Bennett",1,IF(W24="meting",0.5,0)) -> 0 | AS24: =IF(X24="ja",1,0) -> 0 | AT24: =Z24/5 -> 0.6 | AU24: =AA24/5 -> 0.6
A25: G22 | B25: Karatsuba squaring (recursive, in place) | C25: multiplication | D25: mathematics | E25: 2026 | F25: ecdsa.fail 0399ebe (prasiddhnaik, 2026-06-02) | G25: T | H25: ja | I25: - | J25: schoon | K25: 3 | L25: nee | M25: nee | N25: nee | O25: exact | P25: 0 | Q25: O(n^1.58) | R25: O(n) | S25: O(n) | T25: ja | U25: nee | V25: nee | W25: Bennett | X25: nee | Y25: laag | Z25: 3 | AA25: 5 | AB25: 0 | AC25: 0 | AD25: ja | AE25: ja | AF25: Square via Karatsuba split x^2 = a^2 + 2ab<<k + b^2 with 2ab = t^2-a^2-b^2, t formed in place; recursion depth chosen by break-even (~60 bits); sequential half-square recombination to keep one product live. | effect: 717b405 sequential recombination -1.36% vs running best; 9e1ab6a second split level -1,211 T; schoolbook-vs-Karatsuba swaps used for peak (f94f726, 62c8115) | First read mention is 0399ebe ('Karatsuba x-tail' already present); origin not read (inferred earlier, ROUND84 lineage). b87bdf7 reports a 2-level recursion regressed on the 1153Q route. | AH25: =IF(H25="ja",1,0) -> 1 | AI25: =IF(J25="schoon",1,IF(J25="vuil",0.5,0)) -> 1 | AJ25: =K25/5 -> 0.6 | AK25: =IF(L25="ja",1,0) -> 0 | AL25: =IF(M25="ja",1,0) -> 0 | AM25: =IF(N25="ja",1,0) -> 0 | AN25: =IF(O25="exact",1,0) -> 1 | AO25: =IF(T25="ja",1,0) -> 1 | AP25: =IF(U25="ja",1,0) -> 0 | AQ25: =IF(V25="ja",1,0) -> 0 | AR25: =IF(W25="Bennett",1,IF(W25="meting",0.5,0)) -> 1 | AS25: =IF(X25="ja",1,0) -> 0 | AT25: =Z25/5 -> 0.6 | AU25: =AA25/5 -> 1
A26: G23 | B26: Chained-row square with held carries and split first reduction | C26: multiplication | D26: mathematics | E26: 2026 | F26: ecdsa.fail e3b5c51 (zuiris, 2026-10-20) | G26: T | H26: ja | I26: - | J26: schoon | K26: 3 | L26: nee | M26: ja | N26: nee | O26: benaderd | P26: per shot (lambda) | Q26: O(n^1.58) | R26: O(n) | S26: O(n) | T26: ja | U26: nee | V26: nee | W26: Bennett | X26: nee | Y26: laag | Z26: 3 | AA26: 5 | AB26: 0 | AC26: 0 | AD26: ja | AE26: ja | AF26: Add C = s^2 directly into the output with chained rows, holding carries and erasing them together, REDC-style one-digit frame travel, witness erase by measurement, and the square's first reduction split into digits. | effect: e3b5c51 G1M square -1,950 T (part of -0.601%); e4075d6 split first reduction -399 T | G1M uses a 21-bit overflow check (approximate); other parts exact per note. | AH26: =IF(H26="ja",1,0) -> 1 | AI26: =IF(J26="schoon",1,IF(J26="vuil",0.5,0)) -> 1 | AJ26: =K26/5 -> 0.6 | AK26: =IF(L26="ja",1,0) -> 0 | AL26: =IF(M26="ja",1,0) -> 1 | AM26: =IF(N26="ja",1,0) -> 0 | AN26: =IF(O26="exact",1,0) -> 0 | AO26: =IF(T26="ja",1,0) -> 1 | AP26: =IF(U26="ja",1,0) -> 0 | AQ26: =IF(V26="ja",1,0) -> 0 | AR26: =IF(W26="Bennett",1,IF(W26="meting",0.5,0)) -> 1 | AS26: =IF(X26="ja",1,0) -> 0 | AT26: =Z26/5 -> 0.6 | AU26: =AA26/5 -> 1
A27: G24 | B27: Pseudo-Mersenne (Solinas) fold reduction | C27: reduction | D27: mathematics | E27: 2026 | F27: ecdsa.fail f94f726 (Gajesh2007, 2026-05-31) | G27: T | H27: ja | I27: - | J27: schoon | K27: 2 | L27: nee | M27: nee | N27: nee | O27: exact | P27: 0 | Q27: O(n) | R27: O(n) | S27: O(n) | T27: ja | U27: nee | V27: nee | W27: Bennett | X27: ja | Y27: laag | Z27: 3 | AA27: 4 | AB27: 0 | AC27: 0 | AD27: ja | AE27: ja | AF27: Reduce mod p = 2^256 - (2^32+977) by folding high words times f into the low word; lazy/in-place variants, shift-by-22 forms, mask-free folds. | effect: f94f726 Solinas low-scratch 2333->2310 Q; 835298d in-place Solinas fold -13,360 T | Present from the baseline in some form (inferred). Shift-by-22 later replaced by a value-identical 22x double / sub / 22x halve walk to save peak (cbc35ea, 83e3b66). | AH27: =IF(H27="ja",1,0) -> 1 | AI27: =IF(J27="schoon",1,IF(J27="vuil",0.5,0)) -> 1 | AJ27: =K27/5 -> 0.4 | AK27: =IF(L27="ja",1,0) -> 0 | AL27: =IF(M27="ja",1,0) -> 0 | AM27: =IF(N27="ja",1,0) -> 0 | AN27: =IF(O27="exact",1,0) -> 1 | AO27: =IF(T27="ja",1,0) -> 1 | AP27: =IF(U27="ja",1,0) -> 0 | AQ27: =IF(V27="ja",1,0) -> 0 | AR27: =IF(W27="Bennett",1,IF(W27="meting",0.5,0)) -> 1 | AS27: =IF(X27="ja",1,0) -> 1 | AT27: =Z27/5 -> 0.6 | AU27: =AA27/5 -> 0.8
A28: G25 | B28: One fold per payload tick (deferred reduction) | C28: reduction | D28: mathematics | E28: 2026 | F28: ecdsa.fail e9cacd1 (krishparadox, 2026-10-09) | G28: T | H28: ja | I28: - | J28: schoon | K28: 2 | L28: nee | M28: nee | N28: nee | O28: benaderd | P28: per shot (lambda) | Q28: O(n) | R28: O(n) | S28: O(n) | T28: ja | U28: nee | V28: nee | W28: Bennett | X28: ja | Y28: laag | Z28: 3 | AA28: 4 | AB28: 0 | AC28: 0 | AD28: ja | AE28: ja | AF28: Do the three signed adds of a payload tick on a 259-bit integer with no folds in between, then fold once; later an in-place fold with a reduction digit of up to 10 bits. | effect: -1.45% vs running best (-11,416 T builder count); 4cb9cf0 in-place 10-bit fold within lever A | Fold window 56->57 bought back failing shots (+268 T). | AH28: =IF(H28="ja",1,0) -> 1 | AI28: =IF(J28="schoon",1,IF(J28="vuil",0.5,0)) -> 1 | AJ28: =K28/5 -> 0.4 | AK28: =IF(L28="ja",1,0) -> 0 | AL28: =IF(M28="ja",1,0) -> 0 | AM28: =IF(N28="ja",1,0) -> 0 | AN28: =IF(O28="exact",1,0) -> 0 | AO28: =IF(T28="ja",1,0) -> 1 | AP28: =IF(U28="ja",1,0) -> 0 | AQ28: =IF(V28="ja",1,0) -> 0 | AR28: =IF(W28="Bennett",1,IF(W28="meting",0.5,0)) -> 1 | AS28: =IF(X28="ja",1,0) -> 1 | AT28: =Z28/5 -> 0.6 | AU28: =AA28/5 -> 0.8
A29: G26 | B29: Conditional replay exploiting average-executed Toffoli | C29: scheduling/fusion | D29: computer science | E29: 2026 | F29: ecdsa.fail 4b7d727 (BitWonka, 2026-06-08) | G29: T | H29: nee | I29: - | J29: geen | K29: 2 | L29: nee | M29: ja | N29: ja | O29: exact | P29: 0 | Q29: - | R29: - | S29: - | T29: ja | U29: nee | V29: nee | W29: meting | X29: nee | Y29: laag | Z29: 3 | AA29: 3 | AB29: - | AC29: - | AD29: deels | AE29: ja | AF29: Put boundary steps under classical (measurement-outcome) conditions so their Toffolis execute on only a fraction of shots; the score counts average executed, not emitted, Toffoli. | effect: -3.49% vs running best (emitted 1,452,820 vs avg executed 1,404,058); 52c6b6b extension -1.20% | The author flags in the note that physical hardware would execute every emitted gate, so emitted count is the meaningful cost. b5fa90f notes that the nonce flips some Toffolis between depth 0 and depth 1, so cost is nonce-dependent. | AH29: =IF(H29="ja",1,0) -> 0 | AI29: =IF(J29="schoon",1,IF(J29="vuil",0.5,0)) -> 0 | AJ29: =K29/5 -> 0.4 | AK29: =IF(L29="ja",1,0) -> 0 | AL29: =IF(M29="ja",1,0) -> 1 | AM29: =IF(N29="ja",1,0) -> 1 | AN29: =IF(O29="exact",1,0) -> 1 | AO29: =IF(T29="ja",1,0) -> 1 | AP29: =IF(U29="ja",1,0) -> 0 | AQ29: =IF(V29="ja",1,0) -> 0 | AR29: =IF(W29="Bennett",1,IF(W29="meting",0.5,0)) -> 0.5 | AS29: =IF(X29="ja",1,0) -> 0 | AT29: =Z29/5 -> 0.6 | AU29: =AA29/5 -> 0.6
A30: G27 | B30: Classical offset point held in classical bit registers | C30: classical/precompute | D30: computer science | E30: 2026 | F30: ecdsa.fail af5abb1 (tob-joe, 2026-06-19) | G30: T | H30: nee | I30: - | J30: geen | K30: 1 | L30: nee | M30: ja | N30: ja | O30: exact | P30: 0 | Q30: - | R30: - | S30: - | T30: ja | U30: nee | V30: nee | W30: meting | X30: ja | Y30: laag | Z30: 2 | AA30: 4 | AB30: 0 | AC30: 0 | AD30: ja | AE30: ja | AF30: Keep the classical point Q as 2x256 classical bits, loading only transient quantum temps off-peak, so Q never occupies qubits at the GCD peak. | effect: stated as the decisive -512q product-min lever of trailmix-ludicrous (af5abb1) | Inferred: the challenge ABI already supplies Q classically (3616dbf), so the lever is not materialising it in qubits. Earlier routes may have done so (not verified). | AH30: =IF(H30="ja",1,0) -> 0 | AI30: =IF(J30="schoon",1,IF(J30="vuil",0.5,0)) -> 0 | AJ30: =K30/5 -> 0.2 | AK30: =IF(L30="ja",1,0) -> 0 | AL30: =IF(M30="ja",1,0) -> 1 | AM30: =IF(N30="ja",1,0) -> 1 | AN30: =IF(O30="exact",1,0) -> 1 | AO30: =IF(T30="ja",1,0) -> 1 | AP30: =IF(U30="ja",1,0) -> 0 | AQ30: =IF(V30="ja",1,0) -> 0 | AR30: =IF(W30="Bennett",1,IF(W30="meting",0.5,0)) -> 0.5 | AS30: =IF(X30="ja",1,0) -> 1 | AT30: =Z30/5 -> 0.4 | AU30: =AA30/5 -> 0.8
A31: G28 | B31: Multi-bit shift per GCD step (jump-GCD K=2 to 8-way barrel e<=7) | C31: inversion/GCD | D31: mathematics | E31: 2026 | F31: ecdsa.fail ca1cd1f (johnbxx, 2026-06-05) | G31: T+Q | H31: ja | I31: - | J31: schoon | K31: 3 | L31: nee | M31: nee | N31: nee | O31: exact | P31: 0 | Q31: O(n^2) | R31: O(n) | S31: O(n^2) | T31: ja | U31: nee | V31: ja | W31: Bennett | X31: nee | Y31: laag | Z31: 4 | AA31: 4 | AB31: 0 | AC31: 0 | AD31: ja | AE31: ja | AF31: Strip several trailing zeros per step (K=2 bounded shift / Schrottenloher jump-2; leapfrog 2-stage barrel e in [0,3]; lever A e<=7 with a per-rail (3,1) record) to cut step count. | effect: ca1cd1f iterations ~393->~259, -4.53% vs running best; 4cb9cf0 lever A 138->122 ticks, -16,281 T for +8 Q (-0.75%) | Barrel = 4-way (later 8-way) rotation from controlled reflections (1.5n-2 CSWAPs) plus a merged constant fold. Zero-fill rail barrel (e4075d6, -731.5 T) is a later refinement (RAIL_ZERO_FILL in mod.rs). | AH31: =IF(H31="ja",1,0) -> 1 | AI31: =IF(J31="schoon",1,IF(J31="vuil",0.5,0)) -> 1 | AJ31: =K31/5 -> 0.6 | AK31: =IF(L31="ja",1,0) -> 0 | AL31: =IF(M31="ja",1,0) -> 0 | AM31: =IF(N31="ja",1,0) -> 0 | AN31: =IF(O31="exact",1,0) -> 1 | AO31: =IF(T31="ja",1,0) -> 1 | AP31: =IF(U31="ja",1,0) -> 0 | AQ31: =IF(V31="ja",1,0) -> 1 | AR31: =IF(W31="Bennett",1,IF(W31="meting",0.5,0)) -> 1 | AS31: =IF(X31="ja",1,0) -> 0 | AT31: =Z31/5 -> 0.8 | AU31: =AA31/5 -> 0.8
A32: G29 | B32: Ping-pong fixed-schedule signed binary division | C32: inversion/GCD | D32: mathematics | E32: 2026 | F32: ecdsa.fail 3616dbf (teddyjfpender, 2026-08-21) | G32: T+Q | H32: ja | I32: - | J32: schoon | K32: 3 | L32: nee | M32: ja | N32: nee | O32: exact | P32: 0 | Q32: O(n^2) | R32: O(n) | S32: O(n^2) | T32: ja | U32: nee | V32: ja | W32: Bennett | X32: nee | Y32: laag | Z32: 4 | AA32: 4 | AB32: - | AC32: - | AD32: deels | AE32: ja | AF32: Two signed odd rails; the target alternates by round number; the low-bit predicate picks add/sub so (t+-s)/2 stays odd; one sign bit per round on a tape; multiply via the algebraic inverse recurrence T = 2T' + gS. | effect: -14.82% vs running best; Q 1150->1321 (up), T 1,284,776->952,707 | No data-dependent routing swaps. lambda ~1.2 at first (7bb8713), far below the trailmix route's 23.29. | AH32: =IF(H32="ja",1,0) -> 1 | AI32: =IF(J32="schoon",1,IF(J32="vuil",0.5,0)) -> 1 | AJ32: =K32/5 -> 0.6 | AK32: =IF(L32="ja",1,0) -> 0 | AL32: =IF(M32="ja",1,0) -> 1 | AM32: =IF(N32="ja",1,0) -> 0 | AN32: =IF(O32="exact",1,0) -> 1 | AO32: =IF(T32="ja",1,0) -> 1 | AP32: =IF(U32="ja",1,0) -> 0 | AQ32: =IF(V32="ja",1,0) -> 1 | AR32: =IF(W32="Bennett",1,IF(W32="meting",0.5,0)) -> 1 | AS32: =IF(X32="ja",1,0) -> 0 | AT32: =Z32/5 -> 0.8 | AU32: =AA32/5 -> 0.8
A33: G30 | B33: Interleaved walk/replay schedule | C33: scheduling/fusion | D33: computer science | E33: 2026 | F33: ecdsa.fail aac98e9 (0xrlawrence, 2026-08-21) | G33: T | H33: nee | I33: - | J33: geen | K33: 2 | L33: nee | M33: ja | N33: nee | O33: benaderd | P33: per shot (lambda) | Q33: - | R33: - | S33: - | T33: ja | U33: nee | V33: nee | W33: meting | X33: nee | Y33: laag | Z33: 3 | AA33: 3 | AB33: - | AC33: - | AD33: deels | AE33: ja | AF33: Replay coefficient round r while the walk is at round r (tape and payload only meet near the end), turning a flat peak into a ramp; budgeted chunk counts and segmented folds per round. | effect: aac98e9 1300->1279 Q (-1.18%); bc7a792 fused schedule 1316->1281 Q (-1.55% stated) | Two near-simultaneous independent versions (bc7a792 Akashneelesh 18:23, aac98e9 0xrlawrence 18:42 on 2026-08-21). | AH33: =IF(H33="ja",1,0) -> 0 | AI33: =IF(J33="schoon",1,IF(J33="vuil",0.5,0)) -> 0 | AJ33: =K33/5 -> 0.4 | AK33: =IF(L33="ja",1,0) -> 0 | AL33: =IF(M33="ja",1,0) -> 1 | AM33: =IF(N33="ja",1,0) -> 0 | AN33: =IF(O33="exact",1,0) -> 0 | AO33: =IF(T33="ja",1,0) -> 1 | AP33: =IF(U33="ja",1,0) -> 0 | AQ33: =IF(V33="ja",1,0) -> 0 | AR33: =IF(W33="Bennett",1,IF(W33="meting",0.5,0)) -> 0.5 | AS33: =IF(X33="ja",1,0) -> 0 | AT33: =Z33/5 -> 0.6 | AU33: =AA33/5 -> 0.6
A34: G31 | B34: Rails-only / payload-only early-tick reorder | C34: scheduling/fusion | D34: computer science | E34: 2026 | F34: ecdsa.fail 53986ea (BitWonka, 2026-10-07) | G34: T | H34: nee | I34: - | J34: geen | K34: 2 | L34: nee | M34: nee | N34: nee | O34: exact | P34: 0 | Q34: - | R34: - | S34: - | T34: ja | U34: nee | V34: nee | W34: geen | X34: nee | Y34: laag | Z34: 3 | AA34: 3 | AB34: 0 | AC34: 0 | AD34: ja | AE34: ja | AF34: For early ticks run the rails alone (one payload register live, no split adders), then replay the payload over the taped letters while the rails stay parked. | effect: -5.9k T (leapfrog.rs recipe comment); boundary retuned 73-77 | | AH34: =IF(H34="ja",1,0) -> 0 | AI34: =IF(J34="schoon",1,IF(J34="vuil",0.5,0)) -> 0 | AJ34: =K34/5 -> 0.4 | AK34: =IF(L34="ja",1,0) -> 0 | AL34: =IF(M34="ja",1,0) -> 0 | AM34: =IF(N34="ja",1,0) -> 0 | AN34: =IF(O34="exact",1,0) -> 1 | AO34: =IF(T34="ja",1,0) -> 1 | AP34: =IF(U34="ja",1,0) -> 0 | AQ34: =IF(V34="ja",1,0) -> 0 | AR34: =IF(W34="Bennett",1,IF(W34="meting",0.5,0)) -> 0 | AS34: =IF(X34="ja",1,0) -> 0 | AT34: =Z34/5 -> 0.6 | AU34: =AA34/5 -> 0.6
A35: G32 | B35: Terminal passenger loan / known-copy wire lending | C35: width/qubit management | D35: computer science | E35: 2026 | F35: ecdsa.fail 21a0ba3 (0xrlawrence, 2026-08-21) | G35: Q | H35: nee | I35: - | J35: vuil | K35: 2 | L35: nee | M35: nee | N35: nee | O35: exact | P35: 0 | Q35: O(1) | R35: - | S35: - | T35: ja | U35: nee | V35: nee | W35: geen | X35: nee | Y35: midden | Z35: 3 | AA35: 3 | AB35: 0 | AC35: 0 | AD35: ja | AE35: ja | AF35: At walk termination u,v in {+1,-1}, so non-sign wires are copies of the sign or constants; clear them with CX, free them across the replay, and restore them afterwards. | effect: -15 qubits (1317->1302), part of -1.15% vs running best | One-bit passenger loan by welttowelt preceded it (credited, not read). | AH35: =IF(H35="ja",1,0) -> 0 | AI35: =IF(J35="schoon",1,IF(J35="vuil",0.5,0)) -> 0.5 | AJ35: =K35/5 -> 0.4 | AK35: =IF(L35="ja",1,0) -> 0 | AL35: =IF(M35="ja",1,0) -> 0 | AM35: =IF(N35="ja",1,0) -> 0 | AN35: =IF(O35="exact",1,0) -> 1 | AO35: =IF(T35="ja",1,0) -> 1 | AP35: =IF(U35="ja",1,0) -> 0 | AQ35: =IF(V35="ja",1,0) -> 0 | AR35: =IF(W35="Bennett",1,IF(W35="meting",0.5,0)) -> 0 | AS35: =IF(X35="ja",1,0) -> 0 | AT35: =Z35/5 -> 0.6 | AU35: =AA35/5 -> 0.6
A36: G33 | B36: Skywalk min-source GCD in sum/difference frame | C36: inversion/GCD | D36: mathematics | E36: 2026 | F36: ecdsa.fail 4f0d213 (mochimodev, 2026-09-29) | G36: T+Q | H36: ja | I36: - | J36: schoon | K36: 3 | L36: nee | M36: nee | N36: nee | O36: exact | P36: 0 | Q36: O(n^2) | R36: O(n) | S36: O(n^2) | T36: ja | U36: nee | V36: ja | W36: Bennett | X36: nee | Y36: laag | Z36: 4 | AA36: 4 | AB36: - | AC36: - | AD36: deels | AE36: ja | AF36: Represent the pair as {u+v,u}; route the even rail to halving, replace the other by |O-H| with signed add/sub; orientation + sign-flip bits form a 3-symbol history (5 steps in 8 qubits). | effect: Q 1250->1174 at T 888,879->946,250; score -0.02% | ~390 steps vs ping-pong ~700. By Matt Zweil / MAI-A.A.E. | AH36: =IF(H36="ja",1,0) -> 1 | AI36: =IF(J36="schoon",1,IF(J36="vuil",0.5,0)) -> 1 | AJ36: =K36/5 -> 0.6 | AK36: =IF(L36="ja",1,0) -> 0 | AL36: =IF(M36="ja",1,0) -> 0 | AM36: =IF(N36="ja",1,0) -> 0 | AN36: =IF(O36="exact",1,0) -> 1 | AO36: =IF(T36="ja",1,0) -> 1 | AP36: =IF(U36="ja",1,0) -> 0 | AQ36: =IF(V36="ja",1,0) -> 1 | AR36: =IF(W36="Bennett",1,IF(W36="meting",0.5,0)) -> 1 | AS36: =IF(X36="ja",1,0) -> 0 | AT36: =Z36/5 -> 0.8 | AU36: =AA36/5 -> 0.8
A37: G34 | B37: Leapfrog route-free multi-step 2-adic walk | C37: inversion/GCD | D37: mathematics | E37: 2026 | F37: ecdsa.fail 53986ea (BitWonka, 2026-10-07) | G37: T+Q | H37: ja | I37: - | J37: schoon | K37: 3 | L37: nee | M37: ja | N37: nee | O37: benaderd | P37: per shot (lambda) | Q37: O(n^2) | R37: O(n) | S37: O(n^2) | T37: ja | U37: nee | V37: ja | W37: Bennett | X37: nee | Y37: laag | Z37: 4 | AA37: 4 | AB37: 0 | AC37: 0 | AD37: ja | AE37: ja | AF37: Odd rails alternate target roles on a fixed schedule; each tick does two forced add-halves, one deep/flat choice add-halve (top-window compare), and a barrel strip; 5-qubit letter per tick; 4 payload updates per leap. | effect: -9.74% vs running best (1,107,467,010 -> 999,570,880; Q 1170->1243, T 946,553->804,160) | lambda 14.4 at introduction. Later refinements: size-test choice rule, 138 ticks (c2fb64c), lever A 122 ticks (4cb9cf0). | AH37: =IF(H37="ja",1,0) -> 1 | AI37: =IF(J37="schoon",1,IF(J37="vuil",0.5,0)) -> 1 | AJ37: =K37/5 -> 0.6 | AK37: =IF(L37="ja",1,0) -> 0 | AL37: =IF(M37="ja",1,0) -> 1 | AM37: =IF(N37="ja",1,0) -> 0 | AN37: =IF(O37="exact",1,0) -> 0 | AO37: =IF(T37="ja",1,0) -> 1 | AP37: =IF(U37="ja",1,0) -> 0 | AQ37: =IF(V37="ja",1,0) -> 1 | AR37: =IF(W37="Bennett",1,IF(W37="meting",0.5,0)) -> 1 | AS37: =IF(X37="ja",1,0) -> 0 | AT37: =Z37/5 -> 0.8 | AU37: =AA37/5 -> 0.8
A38: G35 | B38: Merged last cell + barrel Montgomery-style op and minimal-AND (rank-bound) rewrites | C38: scheduling/fusion | D38: computer science | E38: 2026 | F38: ecdsa.fail 53986ea (BitWonka, 2026-10-07) | G38: T | H38: nee | I38: - | J38: geen | K38: 2 | L38: nee | M38: ja | N38: ja | O38: exact | P38: 0 | Q38: - | R38: - | S38: - | T38: ja | U38: nee | V38: nee | W38: meting | X38: nee | Y38: laag | Z38: 3 | AA38: 3 | AB38: 0 | AC38: 0 | AD38: ja | AE38: ja | AF38: Fuse the third add-halve and the 2^-e rotation into one op; rewrite small corrections to their AND rank lower bound (U4: u=x+ov+15sg -> (x+ov-sg)+16sg with 4 ANDs instead of 8; 10-AND table; XOR-of-existing-ANDs letters). | effect: U4 (0393770, mochimodev): -968 expected T; 242c0de nine exact rewrites: -3,872 T | Exact rewrites, verified on common inputs (242c0de) or all 64 helper inputs (U4). | AH38: =IF(H38="ja",1,0) -> 0 | AI38: =IF(J38="schoon",1,IF(J38="vuil",0.5,0)) -> 0 | AJ38: =K38/5 -> 0.4 | AK38: =IF(L38="ja",1,0) -> 0 | AL38: =IF(M38="ja",1,0) -> 1 | AM38: =IF(N38="ja",1,0) -> 1 | AN38: =IF(O38="exact",1,0) -> 1 | AO38: =IF(T38="ja",1,0) -> 1 | AP38: =IF(U38="ja",1,0) -> 0 | AQ38: =IF(V38="ja",1,0) -> 0 | AR38: =IF(W38="Bennett",1,IF(W38="meting",0.5,0)) -> 0.5 | AS38: =IF(X38="ja",1,0) -> 0 | AT38: =Z38/5 -> 0.6 | AU38: =AA38/5 -> 0.6
A39: G36 | B39: Tick-0 letter off the tape, short last tick, and size-test choice rule | C39: encoding/transcript | D39: information theory | E39: 2026 | F39: ecdsa.fail c2fb64c (krishparadox, 2026-10-08) | G39: Q | H39: ja | I39: - | J39: schoon | K39: 2 | L39: nee | M39: ja | N39: nee | O39: benaderd | P39: per shot (lambda) | Q39: O(n) | R39: O(n) | S39: O(n) | T39: ja | U39: nee | V39: ja | W39: Bennett | X39: nee | Y39: laag | Z39: 3 | AA39: 3 | AB39: 0 | AC39: 0 | AD39: ja | AE39: ja | AF39: Measure tick 0's letter away after its last read and re-derive it from the source rail at the walk end; make the last tick a choice-only 3-bit letter; use a one-chain size test in the deep/flat rule so slow walks finish one tick sooner. | effect: -1.04% vs running best (139->138 ticks, cap 1240->1237) | | AH39: =IF(H39="ja",1,0) -> 1 | AI39: =IF(J39="schoon",1,IF(J39="vuil",0.5,0)) -> 1 | AJ39: =K39/5 -> 0.4 | AK39: =IF(L39="ja",1,0) -> 0 | AL39: =IF(M39="ja",1,0) -> 1 | AM39: =IF(N39="ja",1,0) -> 0 | AN39: =IF(O39="exact",1,0) -> 0 | AO39: =IF(T39="ja",1,0) -> 1 | AP39: =IF(U39="ja",1,0) -> 0 | AQ39: =IF(V39="ja",1,0) -> 1 | AR39: =IF(W39="Bennett",1,IF(W39="meting",0.5,0)) -> 1 | AS39: =IF(X39="ja",1,0) -> 0 | AT39: =Z39/5 -> 0.6 | AU39: =AA39/5 -> 0.6
A40: G37 | B40: Census-mined dead-gate strip and CCX->CX/CZ downgrades | C40: approximation | D40: statistics | E40: 2026 | F40: ecdsa.fail dcbafc5 (mochimodev, 2026-07-11) | G40: T | H40: nee | I40: - | J40: geen | K40: 1 | L40: nee | M40: nee | N40: nee | O40: benaderd | P40: per shot (lambda) | Q40: - | R40: - | S40: - | T40: ja | U40: nee | V40: ja | W40: geen | X40: nee | Y40: laag | Z40: 2 | AA40: 3 | AB40: 0 | AC40: 0 | AD40: ja | AE40: ja | AF40: Simulate the exact stream on many random valid inputs, record per Toffoli whether its AND ever fired or always equalled one control, then delete or downgrade by op-index table bound to the stream hash. | effect: dcbafc5 2,101 CCX (-0.15%); 3493c83 action mask 16,850 actions; 02146ca 1e9-input census 9,268 dead + 2,050 downgrades; 076f110 156 cuts on 24.2M shots (-148.5 T); 46ae05c failure-priced k<=7 (-317.5 T) | Sampled-exact, not proved: 076f110 shows 86 of 242 candidates clean at 8M shots fire by 24M. b5fa90f: true greedy re-evaluation of marginal coverage under a risk budget. dcbafc5 itsel | AH40: =IF(H40="ja",1,0) -> 0 | AI40: =IF(J40="schoon",1,IF(J40="vuil",0.5,0)) -> 0 | AJ40: =K40/5 -> 0.2 | AK40: =IF(L40="ja",1,0) -> 0 | AL40: =IF(M40="ja",1,0) -> 0 | AM40: =IF(N40="ja",1,0) -> 0 | AN40: =IF(O40="exact",1,0) -> 0 | AO40: =IF(T40="ja",1,0) -> 1 | AP40: =IF(U40="ja",1,0) -> 0 | AQ40: =IF(V40="ja",1,0) -> 1 | AR40: =IF(W40="Bennett",1,IF(W40="meting",0.5,0)) -> 0 | AS40: =IF(X40="ja",1,0) -> 0 | AT40: =Z40/5 -> 0.4 | AU40: =AA40/5 -> 0.6
A41: G38 | B41: Proved exact op-stream simplification passes | C41: classical/precompute | D41: computer science | E41: 2026 | F41: ecdsa.fail 66d8c54 (gopikannappan, 2026-06-19) | G41: T | H41: nee | I41: - | J41: geen | K41: 1 | L41: nee | M41: ja | N41: nee | O41: exact | P41: 0 | Q41: - | R41: - | S41: - | T41: ja | U41: nee | V41: nee | W41: meting | X41: ja | Y41: laag | Z41: 2 | AA41: 4 | AB41: 0 | AC41: 0 | AD41: ja | AE41: ja | AF41: Generic post-passes that prove CCX controls constant or support-redundant (classical constant propagation, affine/quadratic/truth-table support identities, consumed-only-by-phase cond pass, constant-Hmr zero_force, clear-before-reset y33) and drop or weaken them. | effect: 66d8c54 -1,254 executed T (679 dropped + 575 to CX); 427ac4c 70 proved cuts + 2 classical passes (part of -1,243 T) | Exact by construction. Includes swadhin 6f8aba7 exact affine 'bridges' (exhaustive window checks) as a hand-made instance. | AH41: =IF(H41="ja",1,0) -> 0 | AI41: =IF(J41="schoon",1,IF(J41="vuil",0.5,0)) -> 0 | AJ41: =K41/5 -> 0.2 | AK41: =IF(L41="ja",1,0) -> 0 | AL41: =IF(M41="ja",1,0) -> 1 | AM41: =IF(N41="ja",1,0) -> 0 | AN41: =IF(O41="exact",1,0) -> 1 | AO41: =IF(T41="ja",1,0) -> 1 | AP41: =IF(U41="ja",1,0) -> 0 | AQ41: =IF(V41="ja",1,0) -> 0 | AR41: =IF(W41="Bennett",1,IF(W41="meting",0.5,0)) -> 0.5 | AS41: =IF(X41="ja",1,0) -> 1 | AT41: =Z41/5 -> 0.4 | AU41: =AA41/5 -> 0.8
A42: G39 | B42: Cascade-root inverse-pair cancellation | C42: approximation | D42: statistics | E42: 2026 | F42: ecdsa.fail 92809b4 (odinfree, 2026-08-16) | G42: T | H42: nee | I42: - | J42: geen | K42: 1 | L42: nee | M42: nee | N42: nee | O42: benaderd | P42: per shot (lambda) | Q42: - | R42: - | S42: - | T42: ja | U42: nee | V42: ja | W42: geen | X42: nee | Y42: laag | Z42: 2 | AA42: 3 | AB42: - | AC42: - | AD42: nee | AE42: ja | AF42: Accept blocked self-inverse CCX pairs whose single intervening write is one unconditional CCX (residual t ^= s*c*d), unblocking many further exact inverse pairs. | effect: -308 CCX static, 11 roots unblock 144 pairs (-0.02%) | Mechanism credited to Echo-Merlini note cd0a483 (not a submission id in the table; not read). Explicit lambda trade. No 'cascade'/'inverse_pair' in leader grep. | AH42: =IF(H42="ja",1,0) -> 0 | AI42: =IF(J42="schoon",1,IF(J42="vuil",0.5,0)) -> 0 | AJ42: =K42/5 -> 0.2 | AK42: =IF(L42="ja",1,0) -> 0 | AL42: =IF(M42="ja",1,0) -> 0 | AM42: =IF(N42="ja",1,0) -> 0 | AN42: =IF(O42="exact",1,0) -> 0 | AO42: =IF(T42="ja",1,0) -> 1 | AP42: =IF(U42="ja",1,0) -> 0 | AQ42: =IF(V42="ja",1,0) -> 1 | AR42: =IF(W42="Bennett",1,IF(W42="meting",0.5,0)) -> 0 | AS42: =IF(X42="ja",1,0) -> 0 | AT42: =Z42/5 -> 0.4 | AU42: =AA42/5 -> 0.6
A43: G40 | B43: AND holds: park erased AND values instead of recomputing | C43: uncomputation | D43: physics | E43: 2026 | F43: ecdsa.fail fe0ced8 (Meganpark980320, 2026-10-22) | G43: T | H43: nee | I43: - | J43: geen | K43: 1 | L43: nee | M43: ja | N43: nee | O43: benaderd | P43: per shot (lambda) | Q43: O(n) | R43: O(1) | S43: O(n) | T43: ja | U43: nee | V43: nee | W43: meting | X43: nee | Y43: hoog | Z43: 3 | AA43: 4 | AB43: 0 | AC43: 0 | AD43: ja | AE43: ja | AF43: Where a Toffoli recomputes a value an earlier Hmr erased, swap the value into an idle provably-zero wire at the erase (BitStore0 instead of Hmr) and swap it back at the recompute. | effect: 405 holds ~-405 T (fe0ced8 total -784.7 T with C/Z cuts); 362-363 holds in 92e793e/e52002d | Qualified by sampling (>=1M shots, zero violations), so approximate. Generated by a sigscan->holds->countg pipeline. 7d81445 later proves 7 functional holds exactly (BDD). | AH43: =IF(H43="ja",1,0) -> 0 | AI43: =IF(J43="schoon",1,IF(J43="vuil",0.5,0)) -> 0 | AJ43: =K43/5 -> 0.2 | AK43: =IF(L43="ja",1,0) -> 0 | AL43: =IF(M43="ja",1,0) -> 1 | AM43: =IF(N43="ja",1,0) -> 0 | AN43: =IF(O43="exact",1,0) -> 0 | AO43: =IF(T43="ja",1,0) -> 1 | AP43: =IF(U43="ja",1,0) -> 0 | AQ43: =IF(V43="ja",1,0) -> 0 | AR43: =IF(W43="Bennett",1,IF(W43="meting",0.5,0)) -> 0.5 | AS43: =IF(X43="ja",1,0) -> 0 | AT43: =Z43/5 -> 0.6 | AU43: =AA43/5 -> 0.8
A44: G41 | B44: Exact AND cache in idle wires | C44: uncomputation | D44: physics | E44: 2026 | F44: ecdsa.fail d7f6938 (MonitSharma, 2026-10-17) | G44: T | H44: nee | I44: - | J44: geen | K44: 1 | L44: nee | M44: nee | N44: nee | O44: exact | P44: 0 | Q44: O(n) | R44: O(1) | S44: O(n) | T44: ja | U44: nee | V44: nee | W44: meting | X44: nee | Y44: hoog | Z44: 3 | AA44: 4 | AB44: - | AC44: - | AD44: deels | AE44: ja | AF44: Reuse repeated Boolean AND computations by caching them on idle wires (67-stage frozen cache), certified equivalent for every input. | effect: -102.14 executed T per shot, peak unchanged | Universal certificate claimed (245,820 leases). Admission rule included a McNemar test against the parent. | AH44: =IF(H44="ja",1,0) -> 0 | AI44: =IF(J44="schoon",1,IF(J44="vuil",0.5,0)) -> 0 | AJ44: =K44/5 -> 0.2 | AK44: =IF(L44="ja",1,0) -> 0 | AL44: =IF(M44="ja",1,0) -> 0 | AM44: =IF(N44="ja",1,0) -> 0 | AN44: =IF(O44="exact",1,0) -> 1 | AO44: =IF(T44="ja",1,0) -> 1 | AP44: =IF(U44="ja",1,0) -> 0 | AQ44: =IF(V44="ja",1,0) -> 0 | AR44: =IF(W44="Bennett",1,IF(W44="meting",0.5,0)) -> 0.5 | AS44: =IF(X44="ja",1,0) -> 0 | AT44: =Z44/5 -> 0.6 | AU44: =AA44/5 -> 0.8
A45: G42 | B45: Measured rail tops / rail output erase | C45: uncomputation | D45: physics | E45: 2026 | F45: ecdsa.fail 9da9a45 (jackylee0424, 2026-10-23) | G45: T | H45: nee | I45: - | J45: geen | K45: 1 | L45: nee | M45: ja | N45: nee | O45: benaderd | P45: per shot (lambda) | Q45: O(n) | R45: O(1) | S45: O(n) | T45: ja | U45: nee | V45: nee | W45: meting | X45: nee | Y45: hoog | Z45: 3 | AA45: 4 | AB45: 0 | AC45: 0 | AD45: ja | AE45: ja | AF45: Erase rail top bits on the multiply's rails-only forward ticks by measurement where their value is consumed only as phase. | effect: 127 sites in spookyfrog 18 (credited in 46ae05c); more in be1f667/da097c3 | Origin note not read; described in 46ae05c and be1f667. Partly non-exact per be1f667 ('balanced portfolio'). | AH45: =IF(H45="ja",1,0) -> 0 | AI45: =IF(J45="schoon",1,IF(J45="vuil",0.5,0)) -> 0 | AJ45: =K45/5 -> 0.2 | AK45: =IF(L45="ja",1,0) -> 0 | AL45: =IF(M45="ja",1,0) -> 1 | AM45: =IF(N45="ja",1,0) -> 0 | AN45: =IF(O45="exact",1,0) -> 0 | AO45: =IF(T45="ja",1,0) -> 1 | AP45: =IF(U45="ja",1,0) -> 0 | AQ45: =IF(V45="ja",1,0) -> 0 | AR45: =IF(W45="Bennett",1,IF(W45="meting",0.5,0)) -> 0.5 | AS45: =IF(X45="ja",1,0) -> 0 | AT45: =Z45/5 -> 0.6 | AU45: =AA45/5 -> 0.8
A46: G43 | B46: Dead-low carry/borrow elimination in constant adders | C46: adder | D46: computer science | E46: 2026 | F46: ecdsa.fail e8f71df (moscowchill, 2026-08-21) | G46: T | H46: ja | I46: - | J46: schoon | K46: 2 | L46: nee | M46: nee | N46: nee | O46: exact | P46: 0 | Q46: O(n) | R46: O(n) | S46: O(n) | T46: ja | U46: nee | V46: nee | W46: meting | X46: nee | Y46: laag | Z46: 2 | AA46: 5 | AB46: 0 | AC46: 0 | AD46: ja | AE46: ja | AF46: When the low constant bits and/or operand relations force the first carries to zero, skip allocating those ripple ancillas and gates; also delete provably unread last-chunk carries. | effect: -6 T at 1279Q (small); b5fa90f unread last-chunk carry: part of -0.116% | Credited origin Kimi-assisted 8910bd1 in the R700 line (commit id, not read). Exact static dataflow proof. | AH46: =IF(H46="ja",1,0) -> 1 | AI46: =IF(J46="schoon",1,IF(J46="vuil",0.5,0)) -> 1 | AJ46: =K46/5 -> 0.4 | AK46: =IF(L46="ja",1,0) -> 0 | AL46: =IF(M46="ja",1,0) -> 0 | AM46: =IF(N46="ja",1,0) -> 0 | AN46: =IF(O46="exact",1,0) -> 1 | AO46: =IF(T46="ja",1,0) -> 1 | AP46: =IF(U46="ja",1,0) -> 0 | AQ46: =IF(V46="ja",1,0) -> 0 | AR46: =IF(W46="Bennett",1,IF(W46="meting",0.5,0)) -> 0.5 | AS46: =IF(X46="ja",1,0) -> 0 | AT46: =Z46/5 -> 0.4 | AU46: =AA46/5 -> 1
A47: G44 | B47: Per-band truncation-window shapes with equal-marginal pricing | C47: approximation | D47: statistics | E47: 2026 | F47: ecdsa.fail c8f6ff0 (nipzu, 2026-09-05) | G47: T | H47: nee | I47: - | J47: geen | K47: 1 | L47: nee | M47: nee | N47: nee | O47: benaderd | P47: per shot (lambda) | Q47: - | R47: - | S47: - | T47: ja | U47: nee | V47: ja | W47: geen | X47: nee | Y47: laag | Z47: 2 | AA47: 3 | AB47: 0 | AC47: 0 | AD47: ja | AE47: ja | AF47: Replace flat truncation windows (fold, chunk compare, flag compare, walk width) with tables keyed on walk width/round, balancing d(lambda)/dToffoli across sites. | effect: chunk shape -994 T, flag shape -246 T; fold profile frees 3 Q (1263->1260); 9dcbdb8 GUARD 44->24 + SLOPE_2 33->34 ~+9.3M score for +0.46 lambda | Phase-channel errors cannot be seen by a classical model, so these were tuned on failing-shot counts. | AH47: =IF(H47="ja",1,0) -> 0 | AI47: =IF(J47="schoon",1,IF(J47="vuil",0.5,0)) -> 0 | AJ47: =K47/5 -> 0.2 | AK47: =IF(L47="ja",1,0) -> 0 | AL47: =IF(M47="ja",1,0) -> 0 | AM47: =IF(N47="ja",1,0) -> 0 | AN47: =IF(O47="exact",1,0) -> 0 | AO47: =IF(T47="ja",1,0) -> 1 | AP47: =IF(U47="ja",1,0) -> 0 | AQ47: =IF(V47="ja",1,0) -> 1 | AR47: =IF(W47="Bennett",1,IF(W47="meting",0.5,0)) -> 0 | AS47: =IF(X47="ja",1,0) -> 0 | AT47: =Z47/5 -> 0.4 | AU47: =AA47/5 -> 0.6
A48: G45 | B48: Phase-fix deferral and phase-only fixes | C48: uncomputation | D48: physics | E48: 2026 | F48: ecdsa.fail 8186402 (mochimodev, 2026-09-25) | G48: T | H48: nee | I48: - | J48: geen | K48: 1 | L48: nee | M48: ja | N48: ja | O48: exact | P48: 0 | Q48: O(n) | R48: O(1) | S48: O(n) | T48: ja | U48: nee | V48: nee | W48: meting | X48: nee | Y48: hoog | Z48: 3 | AA48: 4 | AB48: 0 | AC48: 0 | AD48: ja | AE48: ja | AF48: Defer carry/boundary phase repairs to a matching inverse or walkback, replace AND-then-Z with CZ-plus-Pauli identities, and drop payload rotations from phase fixes. | effect: part of PR 419 -1.27% vs running best; 242c0de phase-only compares -124 T; leader G7 phase tricks -1,199 T (recipe comment) | PR 419 bundled 62 levers (square preload/diagonals, deferred boundary phases, retained-fold corrections). Only part of that note was read (sections listed). | AH48: =IF(H48="ja",1,0) -> 0 | AI48: =IF(J48="schoon",1,IF(J48="vuil",0.5,0)) -> 0 | AJ48: =K48/5 -> 0.2 | AK48: =IF(L48="ja",1,0) -> 0 | AL48: =IF(M48="ja",1,0) -> 1 | AM48: =IF(N48="ja",1,0) -> 1 | AN48: =IF(O48="exact",1,0) -> 1 | AO48: =IF(T48="ja",1,0) -> 1 | AP48: =IF(U48="ja",1,0) -> 0 | AQ48: =IF(V48="ja",1,0) -> 0 | AR48: =IF(W48="Bennett",1,IF(W48="meting",0.5,0)) -> 0.5 | AS48: =IF(X48="ja",1,0) -> 0 | AT48: =Z48/5 -> 0.6 | AU48: =AA48/5 -> 0.8

Sheet Ongebruikt
A1: Technieken die de leader niet gebruikt (incl. recent academisch werk)
A3: ID | B3: Techniek | C3: Categorie | D3: Vakgebied | E3: Jaar | F3: Bron | G3: Primair doel | H3: Vast aantal qubits nodig | I3: Extra qubits @256 (schatting) | J3: Ancilla-type | K3: Coherentie-eis (1-5) | L3: Verstrengeling met data nodig | M3: Mid-circuit meting | N3: Klassieke feedforward | O3: Exact / benaderd | P3: Foutkans | Q3: Toffoli-schaal | R3: Qubit-schaal | S3: Diepte-schaal | T3: Challenge-gateset ok | U3: Rotaties nodig | V3: Data-afhankelijk pad | W3: Uncompute-methode | X3: Vooraf berekende tabellen | Y3: Fase-risico | Z3: Complexiteit (1-5) | AA3: Volwassenheid (1-5) | AB3: T-effect op leader (%) | AC3: Q-effect op leader (qubits) | AD3: In leader | AE3: Elders gebruikt | AF3: Opmerking | AH3: f:vast | AI3: f:ancilla | AJ3: f:coherentie | AK3: f:verstrengeling | AL3: f:meting | AM3: f:feedforward | AN3: f:exact | AO3: f:gateset | AP3: f:rotaties | AQ3: f:data-afh | AR3: f:uncompute | AS3: f:tabellen | AT3: f:complexiteit | AU3: f:volwassenheid
A4: U01 | B4: Half-delta divsteps (Bernstein-Yang hddivsteps) | C4: inversion | D4: mathematics | E4: 2021 | F4: Bernstein-Yang 2019; sipa safegcd bounds | G4: exactness | H4: ja | I4: 500 | J4: schoon | K4: 3 | L4: nee | M4: nee | N4: nee | O4: exact | P4: 0 | Q4: O(n^2) | R4: O(n) | S4: O(n^2) | T4: ja | U4: nee | V4: ja | W4: Bennett | X4: nee | Y4: laag | Z4: 3 | AA4: 4 | AB4: 40 | AC4: 500 | AD4: nee | AE4: ja | AF4: measured: 591 fixed steps, 3000/3000 inverses correct, rail envelope median+7 bits; transcript ~2 bits/step | AH4: =IF(H4="ja",1,0) -> 1 | AI4: =IF(J4="schoon",1,IF(J4="vuil",0.5,0)) -> 1 | AJ4: =K4/5 -> 0.6 | AK4: =IF(L4="ja",1,0) -> 0 | AL4: =IF(M4="ja",1,0) -> 0 | AM4: =IF(N4="ja",1,0) -> 0 | AN4: =IF(O4="exact",1,0) -> 1 | AO4: =IF(T4="ja",1,0) -> 1 | AP4: =IF(U4="ja",1,0) -> 0 | AQ4: =IF(V4="ja",1,0) -> 1 | AR4: =IF(W4="Bennett",1,IF(W4="meting",0.5,0)) -> 1 | AS4: =IF(X4="ja",1,0) -> 0 | AT4: =Z4/5 -> 0.6 | AU4: =AA4/5 -> 0.8
A5: U02 | B5: safegcd jump matrices (62-step batches from low bits) | C5: inversion | D5: mathematics | E5: 2019 | F5: Bernstein-Yang 2019 | G5: T | H5: ja | I5: 250 | J5: schoon | K5: 3 | L5: nee | M5: nee | N5: nee | O5: exact | P5: 0 | Q5: O(n^2) | R5: O(n) | S5: O(n^2/w) | T5: ja | U5: nee | V5: ja | W5: Bennett | X5: nee | Y5: laag | Z5: 4 | AA5: 3 | AB5: 60 | AC5: 250 | AD5: nee | AE5: nee | AF5: matrix application costs ~4 n-bit products per batch, ~3x the stepwise adds per bit (crossfield doc) | AH5: =IF(H5="ja",1,0) -> 1 | AI5: =IF(J5="schoon",1,IF(J5="vuil",0.5,0)) -> 1 | AJ5: =K5/5 -> 0.6 | AK5: =IF(L5="ja",1,0) -> 0 | AL5: =IF(M5="ja",1,0) -> 0 | AM5: =IF(N5="ja",1,0) -> 0 | AN5: =IF(O5="exact",1,0) -> 1 | AO5: =IF(T5="ja",1,0) -> 1 | AP5: =IF(U5="ja",1,0) -> 0 | AQ5: =IF(V5="ja",1,0) -> 1 | AR5: =IF(W5="Bennett",1,IF(W5="meting",0.5,0)) -> 1 | AS5: =IF(X5="ja",1,0) -> 0 | AT5: =Z5/5 -> 0.8 | AU5: =AA5/5 -> 0.6
A6: U03 | B6: k-ary GCD with small-multiplier table (Sorenson/Weber) | C6: inversion | D6: mathematics | E6: 1994 | F6: Sorenson 1994; Weber 1995; Sedjelmaci-Lavault 2014 | G6: T | H6: ja | I6: 300 | J6: schoon | K6: 3 | L6: nee | M6: nee | N6: nee | O6: exact | P6: 0 | Q6: O(n^2) | R6: O(n) | S6: O(n^2) | T6: ja | U6: nee | V6: ja | W6: Bennett | X6: ja | Y6: midden | Z6: 4 | AA6: 2 | AB6: 150 | AC6: 300 | AD6: nee | AE6: nee | AF6: a*u+b*v with quantum a,b ~ 2 adds per bit vs leader ~0.66; spurious factors need a second inverse | AH6: =IF(H6="ja",1,0) -> 1 | AI6: =IF(J6="schoon",1,IF(J6="vuil",0.5,0)) -> 1 | AJ6: =K6/5 -> 0.6 | AK6: =IF(L6="ja",1,0) -> 0 | AL6: =IF(M6="ja",1,0) -> 0 | AM6: =IF(N6="ja",1,0) -> 0 | AN6: =IF(O6="exact",1,0) -> 1 | AO6: =IF(T6="ja",1,0) -> 1 | AP6: =IF(U6="ja",1,0) -> 0 | AQ6: =IF(V6="ja",1,0) -> 1 | AR6: =IF(W6="Bennett",1,IF(W6="meting",0.5,0)) -> 1 | AS6: =IF(X6="ja",1,0) -> 1 | AT6: =Z6/5 -> 0.8 | AU6: =AA6/5 -> 0.4
A7: U04 | B7: Lehmer / half-GCD (Schonhage, Stehle-Zimmermann) | C7: inversion | D7: mathematics | E7: 1971 | F7: Schonhage 1971; Stehle-Zimmermann 2004 | G7: T | H7: ja | I7: 512 | J7: schoon | K7: 4 | L7: nee | M7: nee | N7: nee | O7: exact | P7: 0 | Q7: O(M(n) log n) | R7: O(n) | S7: O(n log n) | T7: ja | U7: nee | V7: ja | W7: Bennett | X7: nee | Y7: laag | Z7: 5 | AA7: 2 | AB7: 200 | AC7: 512 | AD7: nee | AE7: nee | AF7: asymptotic only; at n=256 matrix products dominate | AH7: =IF(H7="ja",1,0) -> 1 | AI7: =IF(J7="schoon",1,IF(J7="vuil",0.5,0)) -> 1 | AJ7: =K7/5 -> 0.8 | AK7: =IF(L7="ja",1,0) -> 0 | AL7: =IF(M7="ja",1,0) -> 0 | AM7: =IF(N7="ja",1,0) -> 0 | AN7: =IF(O7="exact",1,0) -> 1 | AO7: =IF(T7="ja",1,0) -> 1 | AP7: =IF(U7="ja",1,0) -> 0 | AQ7: =IF(V7="ja",1,0) -> 1 | AR7: =IF(W7="Bennett",1,IF(W7="meting",0.5,0)) -> 1 | AS7: =IF(X7="ja",1,0) -> 0 | AT7: =Z7/5 -> 1 | AU7: =AA7/5 -> 0.4
A8: U05 | B8: Extended Euclid with quotients + register sharing (Proos-Zalka) | C8: inversion | D8: mathematics | E8: 2003 | F8: Proos-Zalka 2003; arXiv 2604.02311 (2026) | G8: Q | H8: ja | I8: -200 | J8: schoon | K8: 5 | L8: nee | M8: nee | N8: nee | O8: exact | P8: 0 | Q8: O(n^2 log n) | R8: O(n) | S8: O(n^2 log n) | T8: ja | U8: nee | V8: ja | W8: Bennett | X8: nee | Y8: laag | Z8: 5 | AA8: 3 | AB8: 3000 | AC8: -200 | AD8: nee | AE8: ja | AF8: 2604.02311: ~204 n^2 log2 n T per inversion (~107M at n=256) | AH8: =IF(H8="ja",1,0) -> 1 | AI8: =IF(J8="schoon",1,IF(J8="vuil",0.5,0)) -> 1 | AJ8: =K8/5 -> 1 | AK8: =IF(L8="ja",1,0) -> 0 | AL8: =IF(M8="ja",1,0) -> 0 | AM8: =IF(N8="ja",1,0) -> 0 | AN8: =IF(O8="exact",1,0) -> 1 | AO8: =IF(T8="ja",1,0) -> 1 | AP8: =IF(U8="ja",1,0) -> 0 | AQ8: =IF(V8="ja",1,0) -> 1 | AR8: =IF(W8="Bennett",1,IF(W8="meting",0.5,0)) -> 1 | AS8: =IF(X8="ja",1,0) -> 0 | AT8: =Z8/5 -> 1 | AU8: =AA8/5 -> 0.6
A9: U06 | B9: Kaliski Montgomery inverse with comparisons | C9: inversion | D9: mathematics | E9: 1995 | F9: Kaliski 1995; Roetteler et al. 2017 | G9: T | H9: ja | I9: 300 | J9: schoon | K9: 3 | L9: nee | M9: nee | N9: nee | O9: exact | P9: 0 | Q9: O(n^2) | R9: O(n) | S9: O(n^2) | T9: ja | U9: nee | V9: ja | W9: Bennett | X9: nee | Y9: laag | Z9: 3 | AA9: 5 | AB9: 150 | AC9: 300 | AD9: nee | AE9: ja | AF9: full-width compare + swap per step; Roetteler: 4 inversion calls per point add | AH9: =IF(H9="ja",1,0) -> 1 | AI9: =IF(J9="schoon",1,IF(J9="vuil",0.5,0)) -> 1 | AJ9: =K9/5 -> 0.6 | AK9: =IF(L9="ja",1,0) -> 0 | AL9: =IF(M9="ja",1,0) -> 0 | AM9: =IF(N9="ja",1,0) -> 0 | AN9: =IF(O9="exact",1,0) -> 1 | AO9: =IF(T9="ja",1,0) -> 1 | AP9: =IF(U9="ja",1,0) -> 0 | AQ9: =IF(V9="ja",1,0) -> 1 | AR9: =IF(W9="Bennett",1,IF(W9="meting",0.5,0)) -> 1 | AS9: =IF(X9="ja",1,0) -> 0 | AT9: =Z9/5 -> 0.6 | AU9: =AA9/5 -> 1
A10: U07 | B10: Fermat inversion a^(p-2) via addition chain | C10: inversion | D10: mathematics | E10: 1640 | F10: classical; binary-field use: arXiv 2503.02984 | G10: exactness | H10: ja | I10: 2560 | J10: schoon | K10: 5 | L10: nee | M10: nee | N10: nee | O10: exact | P10: 0 | Q10: O(n^3) | R10: O(n k) | S10: O(n^3) | T10: ja | U10: nee | V10: nee | W10: Bennett | X10: nee | Y10: laag | Z10: 2 | AA10: 5 | AB10: 30000 | AC10: 2400 | AD10: nee | AE10: nee | AF10: measured with optimal pebbling: best 961B score (k=11), 1050x the leader | AH10: =IF(H10="ja",1,0) -> 1 | AI10: =IF(J10="schoon",1,IF(J10="vuil",0.5,0)) -> 1 | AJ10: =K10/5 -> 1 | AK10: =IF(L10="ja",1,0) -> 0 | AL10: =IF(M10="ja",1,0) -> 0 | AM10: =IF(N10="ja",1,0) -> 0 | AN10: =IF(O10="exact",1,0) -> 1 | AO10: =IF(T10="ja",1,0) -> 1 | AP10: =IF(U10="ja",1,0) -> 0 | AQ10: =IF(V10="ja",1,0) -> 0 | AR10: =IF(W10="Bennett",1,IF(W10="meting",0.5,0)) -> 1 | AS10: =IF(X10="ja",1,0) -> 0 | AT10: =Z10/5 -> 0.4 | AU10: =AA10/5 -> 1
A11: U08 | B11: Spooky pebbling (measurement-based pebble game) | C11: uncomputation | D11: physics | E11: 2019 | F11: Gidney 2019; Kornerup-Sadun-Soloveichik, Quantum 2025 | G11: Q | H11: nee | I11: -150 | J11: geen | K11: 4 | L11: nee | M11: ja | N11: ja | O11: exact | P11: 0 | Q11: O(L^(1+e)) | R11: O(log L) | S11: O(L^(1+e)) | T11: ja | U11: nee | V11: ja | W11: meting | X11: nee | Y11: hoog | Z11: 4 | AA11: 3 | AB11: 15 | AC11: -150 | AD11: nee | AE11: nee | AF11: trades qubits for recomputation and phase fix-ups; same flat T/Q trade as Bennett at this size (estimate) | AH11: =IF(H11="ja",1,0) -> 0 | AI11: =IF(J11="schoon",1,IF(J11="vuil",0.5,0)) -> 0 | AJ11: =K11/5 -> 0.8 | AK11: =IF(L11="ja",1,0) -> 0 | AL11: =IF(M11="ja",1,0) -> 1 | AM11: =IF(N11="ja",1,0) -> 1 | AN11: =IF(O11="exact",1,0) -> 1 | AO11: =IF(T11="ja",1,0) -> 1 | AP11: =IF(U11="ja",1,0) -> 0 | AQ11: =IF(V11="ja",1,0) -> 1 | AR11: =IF(W11="Bennett",1,IF(W11="meting",0.5,0)) -> 0.5 | AS11: =IF(X11="ja",1,0) -> 0 | AT11: =Z11/5 -> 0.8 | AU11: =AA11/5 -> 0.6
A12: U09 | B12: Knill optimal reversible pebbling | C12: uncomputation | D12: computer science | E12: 1995 | F12: Knill 1995 | G12: Q | H12: nee | I12: -100 | J12: geen | K12: 4 | L12: nee | M12: nee | N12: nee | O12: exact | P12: 0 | Q12: O(L^(1+e)) | R12: O(k) | S12: O(L^(1+e)) | T12: ja | U12: nee | V12: ja | W12: Bennett | X12: nee | Y12: laag | Z12: 2 | AA12: 5 | AB12: 20 | AC12: -100 | AD12: nee | AE12: nee | AF12: measured for the Fermat chain; flat for the walk (7,100 T per qubit) | AH12: =IF(H12="ja",1,0) -> 0 | AI12: =IF(J12="schoon",1,IF(J12="vuil",0.5,0)) -> 0 | AJ12: =K12/5 -> 0.8 | AK12: =IF(L12="ja",1,0) -> 0 | AL12: =IF(M12="ja",1,0) -> 0 | AM12: =IF(N12="ja",1,0) -> 0 | AN12: =IF(O12="exact",1,0) -> 1 | AO12: =IF(T12="ja",1,0) -> 1 | AP12: =IF(U12="ja",1,0) -> 0 | AQ12: =IF(V12="ja",1,0) -> 1 | AR12: =IF(W12="Bennett",1,IF(W12="meting",0.5,0)) -> 1 | AS12: =IF(X12="ja",1,0) -> 0 | AT12: =Z12/5 -> 0.4 | AU12: =AA12/5 -> 1
A13: U10 | B13: SAT-based reversible pebbling (Meuli et al.) | C13: uncomputation | D13: computer science | E13: 2019 | F13: Meuli, Soeken, Roetteler, Bjorner, De Micheli 2019 | G13: Q | H13: nee | I13: -80 | J13: geen | K13: 4 | L13: nee | M13: nee | N13: nee | O13: exact | P13: 0 | Q13: instance | R13: instance | S13: instance | T13: ja | U13: nee | V13: ja | W13: Bennett | X13: nee | Y13: laag | Z13: 3 | AA13: 3 | AB13: 10 | AC13: -80 | AD13: nee | AE13: nee | AF13: optimal schedules for small DAGs; the walk DAG is a line | AH13: =IF(H13="ja",1,0) -> 0 | AI13: =IF(J13="schoon",1,IF(J13="vuil",0.5,0)) -> 0 | AJ13: =K13/5 -> 0.8 | AK13: =IF(L13="ja",1,0) -> 0 | AL13: =IF(M13="ja",1,0) -> 0 | AM13: =IF(N13="ja",1,0) -> 0 | AN13: =IF(O13="exact",1,0) -> 1 | AO13: =IF(T13="ja",1,0) -> 1 | AP13: =IF(U13="ja",1,0) -> 0 | AQ13: =IF(V13="ja",1,0) -> 1 | AR13: =IF(W13="Bennett",1,IF(W13="meting",0.5,0)) -> 1 | AS13: =IF(X13="ja",1,0) -> 0 | AT13: =Z13/5 -> 0.6 | AU13: =AA13/5 -> 0.6
A14: U11 | B14: Coset representation of modular integers | C14: reduction | D14: physics | E14: 2006 | F14: Zalka 2006; Gidney arXiv 1905.08488 | G14: T | H14: ja | I14: 24 | J14: schoon | K14: 2 | L14: nee | M14: nee | N14: nee | O14: benaderd | P14: 2^-pad per add | Q14: O(n) | R14: O(n+pad) | S14: O(n) | T14: ja | U14: nee | V14: nee | W14: geen | X14: nee | Y14: laag | Z14: 3 | AA14: 4 | AB14: -3 | AC14: 48 | AD14: nee | AE14: nee | AF14: removes modular compares; leader already folds lazily (IPK), so the gain is small (estimate) | AH14: =IF(H14="ja",1,0) -> 1 | AI14: =IF(J14="schoon",1,IF(J14="vuil",0.5,0)) -> 1 | AJ14: =K14/5 -> 0.4 | AK14: =IF(L14="ja",1,0) -> 0 | AL14: =IF(M14="ja",1,0) -> 0 | AM14: =IF(N14="ja",1,0) -> 0 | AN14: =IF(O14="exact",1,0) -> 0 | AO14: =IF(T14="ja",1,0) -> 1 | AP14: =IF(U14="ja",1,0) -> 0 | AQ14: =IF(V14="ja",1,0) -> 0 | AR14: =IF(W14="Bennett",1,IF(W14="meting",0.5,0)) -> 0 | AS14: =IF(X14="ja",1,0) -> 0 | AT14: =Z14/5 -> 0.6 | AU14: =AA14/5 -> 0.8
A15: U12 | B15: Oblivious carry runways (piecewise adders) | C15: adder | D15: physics | E15: 2019 | F15: Gidney arXiv 1905.08488; US11710063 | G15: depth | H15: ja | I15: 40 | J15: schoon | K15: 1 | L15: nee | M15: nee | N15: nee | O15: benaderd | P15: 2^-runway | Q15: O(n) | R15: O(n) | S15: O(lg lg n) | T15: ja | U15: nee | V15: nee | W15: geen | X15: nee | Y15: laag | Z15: 3 | AA15: 4 | AB15: 2 | AC15: 40 | AD15: nee | AE15: nee | AF15: reduces depth, not Toffoli count; score ignores depth | AH15: =IF(H15="ja",1,0) -> 1 | AI15: =IF(J15="schoon",1,IF(J15="vuil",0.5,0)) -> 1 | AJ15: =K15/5 -> 0.2 | AK15: =IF(L15="ja",1,0) -> 0 | AL15: =IF(M15="ja",1,0) -> 0 | AM15: =IF(N15="ja",1,0) -> 0 | AN15: =IF(O15="exact",1,0) -> 0 | AO15: =IF(T15="ja",1,0) -> 1 | AP15: =IF(U15="ja",1,0) -> 0 | AQ15: =IF(V15="ja",1,0) -> 0 | AR15: =IF(W15="Bennett",1,IF(W15="meting",0.5,0)) -> 0 | AS15: =IF(X15="ja",1,0) -> 0 | AT15: =Z15/5 -> 0.6 | AU15: =AA15/5 -> 0.8
A16: U13 | B16: Residue number system arithmetic | C16: multiplication | D16: mathematics | E16: 2024 | F16: Chevignard-Fouque-Schrottenloher ePrint 2024/222, 2026/280 | G16: Q | H16: ja | I16: -300 | J16: schoon | K16: 4 | L16: nee | M16: ja | N16: ja | O16: benaderd | P16: parametrised | Q16: O(n^2 log n) | R16: O(n/2) | S16: O(n^2) | T16: ja | U16: nee | V16: nee | W16: meting | X16: ja | Y16: midden | Z16: 5 | AA16: 2 | AB16: 500 | AC16: -300 | AD16: nee | AE16: nee | AF16: built for modexp output bits; GCD inversion in RNS needs base extension, costly | AH16: =IF(H16="ja",1,0) -> 1 | AI16: =IF(J16="schoon",1,IF(J16="vuil",0.5,0)) -> 1 | AJ16: =K16/5 -> 0.8 | AK16: =IF(L16="ja",1,0) -> 0 | AL16: =IF(M16="ja",1,0) -> 1 | AM16: =IF(N16="ja",1,0) -> 1 | AN16: =IF(O16="exact",1,0) -> 0 | AO16: =IF(T16="ja",1,0) -> 1 | AP16: =IF(U16="ja",1,0) -> 0 | AQ16: =IF(V16="ja",1,0) -> 0 | AR16: =IF(W16="Bennett",1,IF(W16="meting",0.5,0)) -> 0.5 | AS16: =IF(X16="ja",1,0) -> 1 | AT16: =Z16/5 -> 1 | AU16: =AA16/5 -> 0.4
A17: U14 | B17: Approximate residue arithmetic (truncated outputs) | C17: approximation | D17: mathematics | E17: 2025 | F17: Gidney arXiv 2505.15917; CFS 2024 | G17: T | H17: nee | I17: 0 | J17: geen | K17: 2 | L17: nee | M17: ja | N17: ja | O17: benaderd | P17: parametrised | Q17: O(n^2) | R17: O(n) | S17: O(n^2) | T17: ja | U17: nee | V17: nee | W17: meting | X17: ja | Y17: midden | Z17: 5 | AA17: 3 | AB17: n.a. | AC17: n.a. | AD17: nee | AE17: nee | AF17: needs only top output bits; the point add must output exact coordinates | AH17: =IF(H17="ja",1,0) -> 0 | AI17: =IF(J17="schoon",1,IF(J17="vuil",0.5,0)) -> 0 | AJ17: =K17/5 -> 0.4 | AK17: =IF(L17="ja",1,0) -> 0 | AL17: =IF(M17="ja",1,0) -> 1 | AM17: =IF(N17="ja",1,0) -> 1 | AN17: =IF(O17="exact",1,0) -> 0 | AO17: =IF(T17="ja",1,0) -> 1 | AP17: =IF(U17="ja",1,0) -> 0 | AQ17: =IF(V17="ja",1,0) -> 0 | AR17: =IF(W17="Bennett",1,IF(W17="meting",0.5,0)) -> 0.5 | AS17: =IF(X17="ja",1,0) -> 1 | AT17: =Z17/5 -> 1 | AU17: =AA17/5 -> 0.6
A18: U15 | B18: Ekera-Hastad short discrete-log runs | C18: algorithm | D18: mathematics | E18: 2017 | F18: Ekera-Hastad 2017 | G18: Q | H18: nee | I18: 0 | J18: geen | K18: 1 | L18: nee | M18: nee | N18: nee | O18: exact | P18: 0 | Q18: - | R18: - | S18: - | T18: ja | U18: ja | V18: nee | W18: geen | X18: nee | Y18: laag | Z18: 2 | AA18: 5 | AB18: n.a. | AC18: n.a. | AD18: nee | AE18: nee | AF18: changes the outer algorithm, not one point add | AH18: =IF(H18="ja",1,0) -> 0 | AI18: =IF(J18="schoon",1,IF(J18="vuil",0.5,0)) -> 0 | AJ18: =K18/5 -> 0.2 | AK18: =IF(L18="ja",1,0) -> 0 | AL18: =IF(M18="ja",1,0) -> 0 | AM18: =IF(N18="ja",1,0) -> 0 | AN18: =IF(O18="exact",1,0) -> 1 | AO18: =IF(T18="ja",1,0) -> 1 | AP18: =IF(U18="ja",1,0) -> 1 | AQ18: =IF(V18="ja",1,0) -> 0 | AR18: =IF(W18="Bennett",1,IF(W18="meting",0.5,0)) -> 0 | AS18: =IF(X18="ja",1,0) -> 0 | AT18: =Z18/5 -> 0.4 | AU18: =AA18/5 -> 1
A19: U16 | B19: Regev multidimensional algorithm | C19: algorithm | D19: mathematics | E19: 2023 | F19: Regev 2023; Ekera-Gartner 2024 | G19: T | H19: nee | I19: 0 | J19: geen | K19: 1 | L19: nee | M19: nee | N19: nee | O19: exact | P19: 0 | Q19: - | R19: - | S19: - | T19: ja | U19: ja | V19: nee | W19: geen | X19: nee | Y19: laag | Z19: 4 | AA19: 3 | AB19: n.a. | AC19: n.a. | AD19: nee | AE19: nee | AF19: outer-algorithm level; not applicable to the benchmark | AH19: =IF(H19="ja",1,0) -> 0 | AI19: =IF(J19="schoon",1,IF(J19="vuil",0.5,0)) -> 0 | AJ19: =K19/5 -> 0.2 | AK19: =IF(L19="ja",1,0) -> 0 | AL19: =IF(M19="ja",1,0) -> 0 | AM19: =IF(N19="ja",1,0) -> 0 | AN19: =IF(O19="exact",1,0) -> 1 | AO19: =IF(T19="ja",1,0) -> 1 | AP19: =IF(U19="ja",1,0) -> 1 | AQ19: =IF(V19="ja",1,0) -> 0 | AR19: =IF(W19="Bennett",1,IF(W19="meting",0.5,0)) -> 0 | AS19: =IF(X19="ja",1,0) -> 0 | AT19: =Z19/5 -> 0.8 | AU19: =AA19/5 -> 0.6
A20: U17 | B20: x-only / Montgomery-ladder differential addition | C20: curve model | D20: mathematics | E20: 1987 | F20: Montgomery 1987; ECC floor article 2026 | G20: Q | H20: ja | I20: -256 | J20: geen | K20: 2 | L20: nee | M20: nee | N20: nee | O20: exact | P20: 0 | Q20: - | R20: O(n) | S20: - | T20: ja | U20: nee | V20: nee | W20: geen | X20: nee | Y20: laag | Z20: 4 | AA20: 2 | AB20: n.a. | AC20: n.a. | AD20: nee | AE20: nee | AF20: benchmark demands (x, y) affine in place | AH20: =IF(H20="ja",1,0) -> 1 | AI20: =IF(J20="schoon",1,IF(J20="vuil",0.5,0)) -> 0 | AJ20: =K20/5 -> 0.4 | AK20: =IF(L20="ja",1,0) -> 0 | AL20: =IF(M20="ja",1,0) -> 0 | AM20: =IF(N20="ja",1,0) -> 0 | AN20: =IF(O20="exact",1,0) -> 1 | AO20: =IF(T20="ja",1,0) -> 1 | AP20: =IF(U20="ja",1,0) -> 0 | AQ20: =IF(V20="ja",1,0) -> 0 | AR20: =IF(W20="Bennett",1,IF(W20="meting",0.5,0)) -> 0 | AS20: =IF(X20="ja",1,0) -> 0 | AT20: =Z20/5 -> 0.8 | AU20: =AA20/5 -> 0.4
A21: U18 | B21: Projective / Jacobian coordinates | C21: curve model | D21: mathematics | E21: 1986 | F21: Chudnovsky-Chudnovsky 1986 | G21: T | H21: ja | I21: 512 | J21: geen | K21: 2 | L21: nee | M21: nee | N21: nee | O21: exact | P21: 0 | Q21: O(n^2) | R21: O(n) | S21: O(n^2) | T21: ja | U21: nee | V21: nee | W21: geen | X21: nee | Y21: laag | Z21: 3 | AA21: 5 | AB21: n.a. | AC21: n.a. | AD21: nee | AE21: nee | AF21: affine output still needs an inversion; extra registers | AH21: =IF(H21="ja",1,0) -> 1 | AI21: =IF(J21="schoon",1,IF(J21="vuil",0.5,0)) -> 0 | AJ21: =K21/5 -> 0.4 | AK21: =IF(L21="ja",1,0) -> 0 | AL21: =IF(M21="ja",1,0) -> 0 | AM21: =IF(N21="ja",1,0) -> 0 | AN21: =IF(O21="exact",1,0) -> 1 | AO21: =IF(T21="ja",1,0) -> 1 | AP21: =IF(U21="ja",1,0) -> 0 | AQ21: =IF(V21="ja",1,0) -> 0 | AR21: =IF(W21="Bennett",1,IF(W21="meting",0.5,0)) -> 0 | AS21: =IF(X21="ja",1,0) -> 0 | AT21: =Z21/5 -> 0.6 | AU21: =AA21/5 -> 1
A22: U19 | B22: Legendre-symbol hash (inversion-free ECDLP) | C22: algorithm | D22: mathematics | E22: 2026 | F22: Chevignard et al. 2026 (via postquantum.com) | G22: T | H22: nee | I22: 0 | J22: geen | K22: 2 | L22: nee | M22: ja | N22: ja | O22: benaderd | P22: hash | Q22: - | R22: - | S22: - | T22: ja | U22: nee | V22: nee | W22: meting | X22: nee | Y22: midden | Z22: 4 | AA22: 2 | AB22: n.a. | AC22: n.a. | AD22: nee | AE22: nee | AF22: skips affine normalisation; the benchmark requires it | AH22: =IF(H22="ja",1,0) -> 0 | AI22: =IF(J22="schoon",1,IF(J22="vuil",0.5,0)) -> 0 | AJ22: =K22/5 -> 0.4 | AK22: =IF(L22="ja",1,0) -> 0 | AL22: =IF(M22="ja",1,0) -> 1 | AM22: =IF(N22="ja",1,0) -> 1 | AN22: =IF(O22="exact",1,0) -> 0 | AO22: =IF(T22="ja",1,0) -> 1 | AP22: =IF(U22="ja",1,0) -> 0 | AQ22: =IF(V22="ja",1,0) -> 0 | AR22: =IF(W22="Bennett",1,IF(W22="meting",0.5,0)) -> 0.5 | AS22: =IF(X22="ja",1,0) -> 0 | AT22: =Z22/5 -> 0.8 | AU22: =AA22/5 -> 0.4
A23: U20 | B23: GLV endomorphism | C23: curve model | D23: mathematics | E23: 2001 | F23: Gallant-Lambert-Vanstone 2001 | G23: T | H23: nee | I23: 0 | J23: geen | K23: 1 | L23: nee | M23: nee | N23: nee | O23: exact | P23: 0 | Q23: O(n) | R23: 0 | S23: O(1) | T23: ja | U23: nee | V23: nee | W23: geen | X23: ja | Y23: laag | Z23: 2 | AA23: 5 | AB23: n.a. | AC23: n.a. | AD23: nee | AE23: nee | AF23: halves scalar multiplication, not one addition | AH23: =IF(H23="ja",1,0) -> 0 | AI23: =IF(J23="schoon",1,IF(J23="vuil",0.5,0)) -> 0 | AJ23: =K23/5 -> 0.2 | AK23: =IF(L23="ja",1,0) -> 0 | AL23: =IF(M23="ja",1,0) -> 0 | AM23: =IF(N23="ja",1,0) -> 0 | AN23: =IF(O23="exact",1,0) -> 1 | AO23: =IF(T23="ja",1,0) -> 1 | AP23: =IF(U23="ja",1,0) -> 0 | AQ23: =IF(V23="ja",1,0) -> 0 | AR23: =IF(W23="Bennett",1,IF(W23="meting",0.5,0)) -> 0 | AS23: =IF(X23="ja",1,0) -> 1 | AT23: =Z23/5 -> 0.4 | AU23: =AA23/5 -> 1
A24: U21 | B24: Draper QFT adder | C24: adder | D24: physics | E24: 2000 | F24: Draper 2000 | G24: Q | H24: nee | I24: -50 | J24: geen | K24: 4 | L24: ja | M24: nee | N24: nee | O24: exact | P24: 0 | Q24: O(n^2) rot | R24: O(n) | S24: O(n) | T24: nee | U24: ja | V24: nee | W24: geen | X24: nee | Y24: hoog | Z24: 3 | AA24: 5 | AB24: n.a. | AC24: n.a. | AD24: nee | AE24: nee | AF24: needs rotations: not in the challenge gate set | AH24: =IF(H24="ja",1,0) -> 0 | AI24: =IF(J24="schoon",1,IF(J24="vuil",0.5,0)) -> 0 | AJ24: =K24/5 -> 0.8 | AK24: =IF(L24="ja",1,0) -> 1 | AL24: =IF(M24="ja",1,0) -> 0 | AM24: =IF(N24="ja",1,0) -> 0 | AN24: =IF(O24="exact",1,0) -> 1 | AO24: =IF(T24="ja",1,0) -> 0 | AP24: =IF(U24="ja",1,0) -> 1 | AQ24: =IF(V24="ja",1,0) -> 0 | AR24: =IF(W24="Bennett",1,IF(W24="meting",0.5,0)) -> 0 | AS24: =IF(X24="ja",1,0) -> 0 | AT24: =Z24/5 -> 0.6 | AU24: =AA24/5 -> 1
A25: U22 | B25: Phase-gradient arithmetic | C25: adder | D25: physics | E25: 2018 | F25: Gidney 2018 (Halving the cost of quantum addition) | G25: T | H25: ja | I25: 30 | J25: schoon | K25: 3 | L25: ja | M25: nee | N25: nee | O25: benaderd | P25: rotation precision | Q25: O(n) | R25: O(n) | S25: O(n) | T25: nee | U25: ja | V25: nee | W25: geen | X25: nee | Y25: hoog | Z25: 3 | AA25: 4 | AB25: n.a. | AC25: n.a. | AD25: nee | AE25: nee | AF25: phase-gradient state + rotations: gate set excludes | AH25: =IF(H25="ja",1,0) -> 1 | AI25: =IF(J25="schoon",1,IF(J25="vuil",0.5,0)) -> 1 | AJ25: =K25/5 -> 0.6 | AK25: =IF(L25="ja",1,0) -> 1 | AL25: =IF(M25="ja",1,0) -> 0 | AM25: =IF(N25="ja",1,0) -> 0 | AN25: =IF(O25="exact",1,0) -> 0 | AO25: =IF(T25="ja",1,0) -> 0 | AP25: =IF(U25="ja",1,0) -> 1 | AQ25: =IF(V25="ja",1,0) -> 0 | AR25: =IF(W25="Bennett",1,IF(W25="meting",0.5,0)) -> 0 | AS25: =IF(X25="ja",1,0) -> 0 | AT25: =Z25/5 -> 0.6 | AU25: =AA25/5 -> 0.8
A26: U23 | B26: Carry-lookahead adder (Draper-Kutin-Rains-Svore) | C26: adder | D26: computer science | E26: 2004 | F26: DKRS 2004 | G26: depth | H26: ja | I26: 256 | J26: schoon | K26: 1 | L26: nee | M26: nee | N26: nee | O26: exact | P26: 0 | Q26: O(n) | R26: O(n) | S26: O(log n) | T26: ja | U26: nee | V26: nee | W26: Bennett | X26: nee | Y26: laag | Z26: 3 | AA26: 5 | AB26: 8 | AC26: 256 | AD26: nee | AE26: nee | AF26: ~2-4x Toffolis of a ripple adder for log depth | AH26: =IF(H26="ja",1,0) -> 1 | AI26: =IF(J26="schoon",1,IF(J26="vuil",0.5,0)) -> 1 | AJ26: =K26/5 -> 0.2 | AK26: =IF(L26="ja",1,0) -> 0 | AL26: =IF(M26="ja",1,0) -> 0 | AM26: =IF(N26="ja",1,0) -> 0 | AN26: =IF(O26="exact",1,0) -> 1 | AO26: =IF(T26="ja",1,0) -> 1 | AP26: =IF(U26="ja",1,0) -> 0 | AQ26: =IF(V26="ja",1,0) -> 0 | AR26: =IF(W26="Bennett",1,IF(W26="meting",0.5,0)) -> 1 | AS26: =IF(X26="ja",1,0) -> 0 | AT26: =Z26/5 -> 0.6 | AU26: =AA26/5 -> 1
A27: U24 | B27: CDKM / Cuccaro ripple adder (1 ancilla) | C27: adder | D27: computer science | E27: 2004 | F27: Cuccaro et al. 2004 | G27: Q | H27: ja | I27: -250 | J27: schoon | K27: 2 | L27: nee | M27: nee | N27: nee | O27: exact | P27: 0 | Q27: O(2n) | R27: O(1) | S27: O(n) | T27: ja | U27: nee | V27: nee | W27: Bennett | X27: nee | Y27: laag | Z27: 1 | AA27: 5 | AB27: 25 | AC27: -60 | AD27: nee | AE27: ja | AF27: 2n T vs Gidney n T with n ancillas; used in arXiv 2606.02235 hybrid; at the leader's peak only a few adders are live | AH27: =IF(H27="ja",1,0) -> 1 | AI27: =IF(J27="schoon",1,IF(J27="vuil",0.5,0)) -> 1 | AJ27: =K27/5 -> 0.4 | AK27: =IF(L27="ja",1,0) -> 0 | AL27: =IF(M27="ja",1,0) -> 0 | AM27: =IF(N27="ja",1,0) -> 0 | AN27: =IF(O27="exact",1,0) -> 1 | AO27: =IF(T27="ja",1,0) -> 1 | AP27: =IF(U27="ja",1,0) -> 0 | AQ27: =IF(V27="ja",1,0) -> 0 | AR27: =IF(W27="Bennett",1,IF(W27="meting",0.5,0)) -> 1 | AS27: =IF(X27="ja",1,0) -> 0 | AT27: =Z27/5 -> 0.2 | AU27: =AA27/5 -> 1
A28: U25 | B28: Dirty-ancilla arithmetic (Haner 2n+2) | C28: width | D28: computer science | E28: 2016 | F28: Haner-Roetteler-Svore 2016 | G28: Q | H28: nee | I28: -100 | J28: vuil | K28: 3 | L28: nee | M28: nee | N28: nee | O28: exact | P28: 0 | Q28: O(n^2 log n) | R28: O(1) | S28: O(n^2) | T28: ja | U28: nee | V28: nee | W28: Bennett | X28: nee | Y28: laag | Z28: 4 | AA28: 4 | AB28: 40 | AC28: -100 | AD28: nee | AE28: nee | AF28: 2-4x Toffolis for borrowed qubits | AH28: =IF(H28="ja",1,0) -> 0 | AI28: =IF(J28="schoon",1,IF(J28="vuil",0.5,0)) -> 0.5 | AJ28: =K28/5 -> 0.6 | AK28: =IF(L28="ja",1,0) -> 0 | AL28: =IF(M28="ja",1,0) -> 0 | AM28: =IF(N28="ja",1,0) -> 0 | AN28: =IF(O28="exact",1,0) -> 1 | AO28: =IF(T28="ja",1,0) -> 1 | AP28: =IF(U28="ja",1,0) -> 0 | AQ28: =IF(V28="ja",1,0) -> 0 | AR28: =IF(W28="Bennett",1,IF(W28="meting",0.5,0)) -> 1 | AS28: =IF(X28="ja",1,0) -> 0 | AT28: =Z28/5 -> 0.8 | AU28: =AA28/5 -> 0.8
A29: U26 | B29: Conditionally clean ancillae | C29: width | D29: computer science | E29: 2024 | F29: Khattar-Gidney, Quantum 2025 (arXiv 2407.17966) | G29: Q | H29: nee | I29: -20 | J29: vuil | K29: 2 | L29: nee | M29: nee | N29: nee | O29: exact | P29: 0 | Q29: O(n) | R29: O(log* n) | S29: O(log n) | T29: ja | U29: nee | V29: nee | W29: geen | X29: nee | Y29: laag | Z29: 3 | AA29: 4 | AB29: 1 | AC29: -20 | AD29: nee | AE29: nee | AF29: comparators ~3n T; helps multi-controls, little for window compares | AH29: =IF(H29="ja",1,0) -> 0 | AI29: =IF(J29="schoon",1,IF(J29="vuil",0.5,0)) -> 0.5 | AJ29: =K29/5 -> 0.4 | AK29: =IF(L29="ja",1,0) -> 0 | AL29: =IF(M29="ja",1,0) -> 0 | AM29: =IF(N29="ja",1,0) -> 0 | AN29: =IF(O29="exact",1,0) -> 1 | AO29: =IF(T29="ja",1,0) -> 1 | AP29: =IF(U29="ja",1,0) -> 0 | AQ29: =IF(V29="ja",1,0) -> 0 | AR29: =IF(W29="Bennett",1,IF(W29="meting",0.5,0)) -> 0 | AS29: =IF(X29="ja",1,0) -> 0 | AT29: =Z29/5 -> 0.6 | AU29: =AA29/5 -> 0.8
A30: U27 | B30: QROAM select-swap lookup | C30: lookup | D30: computer science | E30: 2018 | F30: Low-Kliuchnikov-Schaeffer 2018; Berry et al. 2019 | G30: T | H30: ja | I30: 64 | J30: schoon | K30: 2 | L30: nee | M30: ja | N30: ja | O30: exact | P30: 0 | Q30: O(L/k + k w) | R30: O(k w) | S30: O(L/k) | T30: ja | U30: nee | V30: nee | W30: meting | X30: ja | Y30: midden | Z30: 3 | AA30: 5 | AB30: 0 | AC30: 64 | AD30: nee | AE30: ja | AF30: only pays when indexed function costs > table size; per-tick logic is ~5-30 T | AH30: =IF(H30="ja",1,0) -> 1 | AI30: =IF(J30="schoon",1,IF(J30="vuil",0.5,0)) -> 1 | AJ30: =K30/5 -> 0.4 | AK30: =IF(L30="ja",1,0) -> 0 | AL30: =IF(M30="ja",1,0) -> 1 | AM30: =IF(N30="ja",1,0) -> 1 | AN30: =IF(O30="exact",1,0) -> 1 | AO30: =IF(T30="ja",1,0) -> 1 | AP30: =IF(U30="ja",1,0) -> 0 | AQ30: =IF(V30="ja",1,0) -> 0 | AR30: =IF(W30="Bennett",1,IF(W30="meting",0.5,0)) -> 0.5 | AS30: =IF(X30="ja",1,0) -> 1 | AT30: =Z30/5 -> 0.6 | AU30: =AA30/5 -> 1
A31: U28 | B31: Measurement-based lookup cleanup | C31: lookup | D31: physics | E31: 2019 | F31: Berry et al. 2019; Long et al. 2026 | G31: T | H31: nee | I31: 0 | J31: geen | K31: 1 | L31: nee | M31: ja | N31: ja | O31: exact | P31: 0 | Q31: O(sqrt L) | R31: O(1) | S31: O(sqrt L) | T31: ja | U31: nee | V31: nee | W31: meting | X31: ja | Y31: midden | Z31: 2 | AA31: 5 | AB31: 0 | AC31: 0 | AD31: nee | AE31: ja | AF31: only relevant once lookups exist | AH31: =IF(H31="ja",1,0) -> 0 | AI31: =IF(J31="schoon",1,IF(J31="vuil",0.5,0)) -> 0 | AJ31: =K31/5 -> 0.2 | AK31: =IF(L31="ja",1,0) -> 0 | AL31: =IF(M31="ja",1,0) -> 1 | AM31: =IF(N31="ja",1,0) -> 1 | AN31: =IF(O31="exact",1,0) -> 1 | AO31: =IF(T31="ja",1,0) -> 1 | AP31: =IF(U31="ja",1,0) -> 0 | AQ31: =IF(V31="ja",1,0) -> 0 | AR31: =IF(W31="Bennett",1,IF(W31="meting",0.5,0)) -> 0.5 | AS31: =IF(X31="ja",1,0) -> 1 | AT31: =Z31/5 -> 0.4 | AU31: =AA31/5 -> 1
A32: U29 | B32: Toom-Cook multiplication | C32: multiplication | D32: mathematics | E32: 1963 | F32: Toom 1963; Dutta et al. PRA 98, 012311 (2018) | G32: T | H32: ja | I32: 300 | J32: schoon | K32: 3 | L32: nee | M32: nee | N32: nee | O32: exact | P32: 0 | Q32: O(n^1.46) | R32: O(n) | S32: O(n) | T32: ja | U32: nee | V32: nee | W32: Bennett | X32: nee | Y32: laag | Z32: 4 | AA32: 3 | AB32: 1 | AC32: 300 | AD32: nee | AE32: nee | AF32: square phase is 4.6% of T; crossover far above 256 bits | AH32: =IF(H32="ja",1,0) -> 1 | AI32: =IF(J32="schoon",1,IF(J32="vuil",0.5,0)) -> 1 | AJ32: =K32/5 -> 0.6 | AK32: =IF(L32="ja",1,0) -> 0 | AL32: =IF(M32="ja",1,0) -> 0 | AM32: =IF(N32="ja",1,0) -> 0 | AN32: =IF(O32="exact",1,0) -> 1 | AO32: =IF(T32="ja",1,0) -> 1 | AP32: =IF(U32="ja",1,0) -> 0 | AQ32: =IF(V32="ja",1,0) -> 0 | AR32: =IF(W32="Bennett",1,IF(W32="meting",0.5,0)) -> 1 | AS32: =IF(X32="ja",1,0) -> 0 | AT32: =Z32/5 -> 0.8 | AU32: =AA32/5 -> 0.6
A33: U30 | B33: Barrett reduction | C33: reduction | D33: mathematics | E33: 1986 | F33: Barrett 1986 | G33: T | H33: ja | I33: 256 | J33: schoon | K33: 2 | L33: nee | M33: nee | N33: nee | O33: exact | P33: 0 | Q33: O(n^2) | R33: O(n) | S33: O(n^2) | T33: ja | U33: nee | V33: nee | W33: Bennett | X33: nee | Y33: laag | Z33: 2 | AA33: 5 | AB33: 0 | AC33: 256 | AD33: nee | AE33: nee | AF33: pseudo-Mersenne p makes Solinas folding cheaper | AH33: =IF(H33="ja",1,0) -> 1 | AI33: =IF(J33="schoon",1,IF(J33="vuil",0.5,0)) -> 1 | AJ33: =K33/5 -> 0.4 | AK33: =IF(L33="ja",1,0) -> 0 | AL33: =IF(M33="ja",1,0) -> 0 | AM33: =IF(N33="ja",1,0) -> 0 | AN33: =IF(O33="exact",1,0) -> 1 | AO33: =IF(T33="ja",1,0) -> 1 | AP33: =IF(U33="ja",1,0) -> 0 | AQ33: =IF(V33="ja",1,0) -> 0 | AR33: =IF(W33="Bennett",1,IF(W33="meting",0.5,0)) -> 1 | AS33: =IF(X33="ja",1,0) -> 0 | AT33: =Z33/5 -> 0.4 | AU33: =AA33/5 -> 1
A34: U31 | B34: Integer cofactor tracking (growing cofactors, register sharing) | C34: inversion | D34: mathematics | E34: 2003 | F34: Proos-Zalka 2003; Bernstein-Yang 2019 | G34: T | H34: ja | I34: 512 | J34: schoon | K34: 3 | L34: nee | M34: nee | N34: nee | O34: exact | P34: 0 | Q34: O(n^2) | R34: O(n) | S34: O(n^2) | T34: ja | U34: nee | V34: ja | W34: Bennett | X34: nee | Y34: laag | Z34: 4 | AA34: 3 | AB34: 5 | AC34: 512 | AD34: nee | AE34: nee | AF34: payload adds roughly halve but two modular multiplications and end-of-walk width cancel it (design.py variant D) | AH34: =IF(H34="ja",1,0) -> 1 | AI34: =IF(J34="schoon",1,IF(J34="vuil",0.5,0)) -> 1 | AJ34: =K34/5 -> 0.6 | AK34: =IF(L34="ja",1,0) -> 0 | AL34: =IF(M34="ja",1,0) -> 0 | AM34: =IF(N34="ja",1,0) -> 0 | AN34: =IF(O34="exact",1,0) -> 1 | AO34: =IF(T34="ja",1,0) -> 1 | AP34: =IF(U34="ja",1,0) -> 0 | AQ34: =IF(V34="ja",1,0) -> 1 | AR34: =IF(W34="Bennett",1,IF(W34="meting",0.5,0)) -> 1 | AS34: =IF(X34="ja",1,0) -> 0 | AT34: =Z34/5 -> 0.8 | AU34: =AA34/5 -> 0.6
A35: U32 | B35: Base-k transcript packing (Jump-2 base-5) | C35: encoding | D35: information theory | E35: 2026 | F35: Long et al. arXiv 2609.28882 | G35: Q | H35: ja | I35: -60 | J35: schoon | K35: 2 | L35: nee | M35: nee | N35: nee | O35: exact | P35: 0 | Q35: O(n) | R35: - | S35: O(n) | T35: ja | U35: nee | V35: ja | W35: Bennett | X35: nee | Y35: laag | Z35: 3 | AA35: 3 | AB35: 1 | AC35: -20 | AD35: nee | AE35: ja | AF35: leader transcript measured at its local floor (694 vs 690 bits) | AH35: =IF(H35="ja",1,0) -> 1 | AI35: =IF(J35="schoon",1,IF(J35="vuil",0.5,0)) -> 1 | AJ35: =K35/5 -> 0.4 | AK35: =IF(L35="ja",1,0) -> 0 | AL35: =IF(M35="ja",1,0) -> 0 | AM35: =IF(N35="ja",1,0) -> 0 | AN35: =IF(O35="exact",1,0) -> 1 | AO35: =IF(T35="ja",1,0) -> 1 | AP35: =IF(U35="ja",1,0) -> 0 | AQ35: =IF(V35="ja",1,0) -> 1 | AR35: =IF(W35="Bennett",1,IF(W35="meting",0.5,0)) -> 1 | AS35: =IF(X35="ja",1,0) -> 0 | AT35: =Z35/5 -> 0.6 | AU35: =AA35/5 -> 0.6
A36: U33 | B36: Batch inversion (Montgomery trick) | C36: inversion | D36: mathematics | E36: 1987 | F36: Montgomery 1987 | G36: T | H36: ja | I36: 256 | J36: schoon | K36: 3 | L36: nee | M36: nee | N36: nee | O36: exact | P36: 0 | Q36: O(n^2) | R36: O(n) | S36: O(n^2) | T36: ja | U36: nee | V36: nee | W36: Bennett | X36: nee | Y36: laag | Z36: 3 | AA36: 5 | AB36: 0 | AC36: 256 | AD36: nee | AE36: nee | AF36: one inversion for both 1/dx and 1/d' (checked 50/50) but in place still needs a second walk | AH36: =IF(H36="ja",1,0) -> 1 | AI36: =IF(J36="schoon",1,IF(J36="vuil",0.5,0)) -> 1 | AJ36: =K36/5 -> 0.6 | AK36: =IF(L36="ja",1,0) -> 0 | AL36: =IF(M36="ja",1,0) -> 0 | AM36: =IF(N36="ja",1,0) -> 0 | AN36: =IF(O36="exact",1,0) -> 1 | AO36: =IF(T36="ja",1,0) -> 1 | AP36: =IF(U36="ja",1,0) -> 0 | AQ36: =IF(V36="ja",1,0) -> 0 | AR36: =IF(W36="Bennett",1,IF(W36="meting",0.5,0)) -> 1 | AS36: =IF(X36="ja",1,0) -> 0 | AT36: =Z36/5 -> 0.6 | AU36: =AA36/5 -> 1
A37: U34 | B37: 2-adic Hensel/Newton inversion | C37: inversion | D37: mathematics | E37: 1960 | F37: Hensel; Jebelean exact division 1993 | G37: T | H37: ja | I37: 512 | J37: schoon | K37: 3 | L37: nee | M37: nee | N37: nee | O37: exact | P37: 0 | Q37: O(n^2) | R37: O(n) | S37: O(n^2 log n) | T37: ja | U37: nee | V37: nee | W37: Bennett | X37: nee | Y37: laag | Z37: 3 | AA37: 4 | AB37: n.a. | AC37: n.a. | AD37: nee | AE37: nee | AF37: cheap mod 2^k; a mod-p inverse needs p^-1 mod d (GCD-equivalent) | AH37: =IF(H37="ja",1,0) -> 1 | AI37: =IF(J37="schoon",1,IF(J37="vuil",0.5,0)) -> 1 | AJ37: =K37/5 -> 0.6 | AK37: =IF(L37="ja",1,0) -> 0 | AL37: =IF(M37="ja",1,0) -> 0 | AM37: =IF(N37="ja",1,0) -> 0 | AN37: =IF(O37="exact",1,0) -> 1 | AO37: =IF(T37="ja",1,0) -> 1 | AP37: =IF(U37="ja",1,0) -> 0 | AQ37: =IF(V37="ja",1,0) -> 0 | AR37: =IF(W37="Bennett",1,IF(W37="meting",0.5,0)) -> 1 | AS37: =IF(X37="ja",1,0) -> 0 | AT37: =Z37/5 -> 0.6 | AU37: =AA37/5 -> 0.8
A38: U35 | B38: Square-only multiplication (quarter squares) | C38: multiplication | D38: mathematics | E38: 1817 | F38: quarter-square tables; this session | G38: T | H38: ja | I38: 256 | J38: schoon | K38: 2 | L38: nee | M38: nee | N38: nee | O38: exact | P38: 0 | Q38: O(n^2) | R38: O(n) | S38: O(n^2) | T38: ja | U38: nee | V38: nee | W38: Bennett | X38: nee | Y38: laag | Z38: 2 | AA38: 5 | AB38: 0 | AC38: 256 | AD38: nee | AE38: nee | AF38: the point add has one product outside the walks and it is already a square | AH38: =IF(H38="ja",1,0) -> 1 | AI38: =IF(J38="schoon",1,IF(J38="vuil",0.5,0)) -> 1 | AJ38: =K38/5 -> 0.4 | AK38: =IF(L38="ja",1,0) -> 0 | AL38: =IF(M38="ja",1,0) -> 0 | AM38: =IF(N38="ja",1,0) -> 0 | AN38: =IF(O38="exact",1,0) -> 1 | AO38: =IF(T38="ja",1,0) -> 1 | AP38: =IF(U38="ja",1,0) -> 0 | AQ38: =IF(V38="ja",1,0) -> 0 | AR38: =IF(W38="Bennett",1,IF(W38="meting",0.5,0)) -> 1 | AS38: =IF(X38="ja",1,0) -> 0 | AT38: =Z38/5 -> 0.4 | AU38: =AA38/5 -> 1
A39: U36 | B39: ZK-proof validation of withheld circuits | C39: validation | D39: computer science | E39: 2026 | F39: Babbush et al. 2026 | G39: none | H39: nee | I39: 0 | J39: geen | K39: 1 | L39: nee | M39: nee | N39: nee | O39: exact | P39: 0 | Q39: - | R39: - | S39: - | T39: ja | U39: nee | V39: nee | W39: geen | X39: nee | Y39: laag | Z39: 5 | AA39: 3 | AB39: n.a. | AC39: n.a. | AD39: nee | AE39: ja | AF39: evidence method, not a circuit technique | AH39: =IF(H39="ja",1,0) -> 0 | AI39: =IF(J39="schoon",1,IF(J39="vuil",0.5,0)) -> 0 | AJ39: =K39/5 -> 0.2 | AK39: =IF(L39="ja",1,0) -> 0 | AL39: =IF(M39="ja",1,0) -> 0 | AM39: =IF(N39="ja",1,0) -> 0 | AN39: =IF(O39="exact",1,0) -> 1 | AO39: =IF(T39="ja",1,0) -> 1 | AP39: =IF(U39="ja",1,0) -> 0 | AQ39: =IF(V39="ja",1,0) -> 0 | AR39: =IF(W39="Bennett",1,IF(W39="meting",0.5,0)) -> 0 | AS39: =IF(X39="ja",1,0) -> 0 | AT39: =Z39/5 -> 1 | AU39: =AA39/5 -> 0.6

Sheet Tekstboek
A1: Tekstboekmethoden van 2 qubits tot 256-bit bouwstenen
A3: ID | B3: Techniek | C3: Categorie | D3: Vakgebied | E3: Jaar | F3: Bron | G3: Primair doel | H3: Vast aantal qubits nodig | I3: Extra qubits @256 (schatting) | J3: Ancilla-type | K3: Coherentie-eis (1-5) | L3: Verstrengeling met data nodig | M3: Mid-circuit meting | N3: Klassieke feedforward | O3: Exact / benaderd | P3: Foutkans | Q3: Toffoli-schaal | R3: Qubit-schaal | S3: Diepte-schaal | T3: Challenge-gateset ok | U3: Rotaties nodig | V3: Data-afhankelijk pad | W3: Uncompute-methode | X3: Vooraf berekende tabellen | Y3: Fase-risico | Z3: Complexiteit (1-5) | AA3: Volwassenheid (1-5) | AB3: T-effect op leader (%) | AC3: Q-effect op leader (qubits) | AD3: In leader | AE3: Elders gebruikt | AF3: Opmerking | AH3: f:vast | AI3: f:ancilla | AJ3: f:coherentie | AK3: f:verstrengeling | AL3: f:meting | AM3: f:feedforward | AN3: f:exact | AO3: f:gateset | AP3: f:rotaties | AQ3: f:data-afh | AR3: f:uncompute | AS3: f:tabellen | AT3: f:complexiteit | AU3: f:volwassenheid
A4: B01 | B4: [2 qubits] CNOT / CZ | C4: gate | D4: physics | E4: 1995 | F4: Barenco et al. 1995; Nielsen-Chuang ch.4 | G4: basis | H4: nee | I4: 0 | J4: geen | K4: 1 | L4: ja | M4: nee | N4: nee | O4: exact | P4: 0 | Q4: 0 T | R4: - | S4: O(1) | T4: ja | U4: nee | V4: nee | W4: geen | X4: nee | Y4: laag | Z4: 1 | AA4: 5 | AB4: 0 | AC4: 0 | AD4: ja | AE4: ja | AF4: Clifford, free in the score | in nieuw ontwerp: T6,S | AH4: =IF(H4="ja",1,0) -> 0 | AI4: =IF(J4="schoon",1,IF(J4="vuil",0.5,0)) -> 0 | AJ4: =K4/5 -> 0.2 | AK4: =IF(L4="ja",1,0) -> 1 | AL4: =IF(M4="ja",1,0) -> 0 | AM4: =IF(N4="ja",1,0) -> 0 | AN4: =IF(O4="exact",1,0) -> 1 | AO4: =IF(T4="ja",1,0) -> 1 | AP4: =IF(U4="ja",1,0) -> 0 | AQ4: =IF(V4="ja",1,0) -> 0 | AR4: =IF(W4="Bennett",1,IF(W4="meting",0.5,0)) -> 0 | AS4: =IF(X4="ja",1,0) -> 0 | AT4: =Z4/5 -> 0.2 | AU4: =AA4/5 -> 1
A5: B02 | B5: [2 qubits] SWAP (3 CNOT) / wire relabel | C5: gate | D5: physics | E5: 1995 | F5: Nielsen-Chuang ch.4 | G5: basis | H5: nee | I5: 0 | J5: geen | K5: 1 | L5: nee | M5: nee | N5: nee | O5: exact | P5: 0 | Q5: 0 T | R5: - | S5: O(1) | T5: ja | U5: nee | V5: nee | W5: geen | X5: nee | Y5: laag | Z5: 1 | AA5: 5 | AB5: 0 | AC5: 0 | AD5: ja | AE5: ja | AF5: shifts by a constant are relabels | in nieuw ontwerp: T6,S | AH5: =IF(H5="ja",1,0) -> 0 | AI5: =IF(J5="schoon",1,IF(J5="vuil",0.5,0)) -> 0 | AJ5: =K5/5 -> 0.2 | AK5: =IF(L5="ja",1,0) -> 0 | AL5: =IF(M5="ja",1,0) -> 0 | AM5: =IF(N5="ja",1,0) -> 0 | AN5: =IF(O5="exact",1,0) -> 1 | AO5: =IF(T5="ja",1,0) -> 1 | AP5: =IF(U5="ja",1,0) -> 0 | AQ5: =IF(V5="ja",1,0) -> 0 | AR5: =IF(W5="Bennett",1,IF(W5="meting",0.5,0)) -> 0 | AS5: =IF(X5="ja",1,0) -> 0 | AT5: =Z5/5 -> 0.2 | AU5: =AA5/5 -> 1
A6: B03 | B6: [2 qubits] Z-basis measurement + reset | C6: measurement | D6: physics | E6: 1995 | F6: Nielsen-Chuang ch.2 | G6: Q | H6: nee | I6: 0 | J6: geen | K6: 1 | L6: nee | M6: ja | N6: nee | O6: exact | P6: 0 | Q6: 0 T | R6: - | S6: O(1) | T6: ja | U6: nee | V6: nee | W6: meting | X6: nee | Y6: midden | Z6: 1 | AA6: 5 | AB6: 0 | AC6: 0 | AD6: ja | AE6: ja | AF6: allowed only on clean or determined wires | in nieuw ontwerp: T6 | AH6: =IF(H6="ja",1,0) -> 0 | AI6: =IF(J6="schoon",1,IF(J6="vuil",0.5,0)) -> 0 | AJ6: =K6/5 -> 0.2 | AK6: =IF(L6="ja",1,0) -> 0 | AL6: =IF(M6="ja",1,0) -> 1 | AM6: =IF(N6="ja",1,0) -> 0 | AN6: =IF(O6="exact",1,0) -> 1 | AO6: =IF(T6="ja",1,0) -> 1 | AP6: =IF(U6="ja",1,0) -> 0 | AQ6: =IF(V6="ja",1,0) -> 0 | AR6: =IF(W6="Bennett",1,IF(W6="meting",0.5,0)) -> 0.5 | AS6: =IF(X6="ja",1,0) -> 0 | AT6: =Z6/5 -> 0.2 | AU6: =AA6/5 -> 1
A7: B04 | B7: [2 qubits] X-basis measurement (HMR) + classically controlled CZ | C7: measurement | D7: physics | E7: 2018 | F7: Gidney 2018; Jones 2013 | G7: T | H7: nee | I7: 0 | J7: geen | K7: 1 | L7: nee | M7: ja | N7: ja | O7: exact | P7: 0 | Q7: 0 T | R7: - | S7: O(1) | T7: ja | U7: nee | V7: nee | W7: meting | X7: nee | Y7: hoog | Z7: 2 | AA7: 5 | AB7: 0 | AC7: 0 | AD7: ja | AE7: ja | AF7: core of measurement-based uncompute | in nieuw ontwerp: T6 | AH7: =IF(H7="ja",1,0) -> 0 | AI7: =IF(J7="schoon",1,IF(J7="vuil",0.5,0)) -> 0 | AJ7: =K7/5 -> 0.2 | AK7: =IF(L7="ja",1,0) -> 0 | AL7: =IF(M7="ja",1,0) -> 1 | AM7: =IF(N7="ja",1,0) -> 1 | AN7: =IF(O7="exact",1,0) -> 1 | AO7: =IF(T7="ja",1,0) -> 1 | AP7: =IF(U7="ja",1,0) -> 0 | AQ7: =IF(V7="ja",1,0) -> 0 | AR7: =IF(W7="Bennett",1,IF(W7="meting",0.5,0)) -> 0.5 | AS7: =IF(X7="ja",1,0) -> 0 | AT7: =Z7/5 -> 0.4 | AU7: =AA7/5 -> 1
A8: B05 | B8: [3 qubits] Toffoli (CCX) / CCZ | C8: gate | D8: computer science | E8: 1980 | F8: Toffoli 1980 | G8: basis | H8: nee | I8: 0 | J8: geen | K8: 1 | L8: ja | M8: nee | N8: nee | O8: exact | P8: 0 | Q8: 1 T | R8: - | S8: O(1) | T8: ja | U8: nee | V8: nee | W8: Bennett | X8: nee | Y8: laag | Z8: 1 | AA8: 5 | AB8: 0 | AC8: 0 | AD8: ja | AE8: ja | AF8: the scored gate | in nieuw ontwerp: T6,S | AH8: =IF(H8="ja",1,0) -> 0 | AI8: =IF(J8="schoon",1,IF(J8="vuil",0.5,0)) -> 0 | AJ8: =K8/5 -> 0.2 | AK8: =IF(L8="ja",1,0) -> 1 | AL8: =IF(M8="ja",1,0) -> 0 | AM8: =IF(N8="ja",1,0) -> 0 | AN8: =IF(O8="exact",1,0) -> 1 | AO8: =IF(T8="ja",1,0) -> 1 | AP8: =IF(U8="ja",1,0) -> 0 | AQ8: =IF(V8="ja",1,0) -> 0 | AR8: =IF(W8="Bennett",1,IF(W8="meting",0.5,0)) -> 1 | AS8: =IF(X8="ja",1,0) -> 0 | AT8: =Z8/5 -> 0.2 | AU8: =AA8/5 -> 1
A9: B06 | B9: [3 qubits] Fredkin (controlled SWAP) | C9: gate | D9: computer science | E9: 1982 | F9: Fredkin-Toffoli 1982 | G9: basis | H9: nee | I9: 0 | J9: geen | K9: 1 | L9: ja | M9: nee | N9: nee | O9: exact | P9: 0 | Q9: 1 T | R9: - | S9: O(1) | T9: ja | U9: nee | V9: nee | W9: Bennett | X9: nee | Y9: laag | Z9: 1 | AA9: 5 | AB9: 0 | AC9: 0 | AD9: ja | AE9: ja | AF9: payload and rail swaps in divsteps | in nieuw ontwerp: T6,S | AH9: =IF(H9="ja",1,0) -> 0 | AI9: =IF(J9="schoon",1,IF(J9="vuil",0.5,0)) -> 0 | AJ9: =K9/5 -> 0.2 | AK9: =IF(L9="ja",1,0) -> 1 | AL9: =IF(M9="ja",1,0) -> 0 | AM9: =IF(N9="ja",1,0) -> 0 | AN9: =IF(O9="exact",1,0) -> 1 | AO9: =IF(T9="ja",1,0) -> 1 | AP9: =IF(U9="ja",1,0) -> 0 | AQ9: =IF(V9="ja",1,0) -> 0 | AR9: =IF(W9="Bennett",1,IF(W9="meting",0.5,0)) -> 1 | AS9: =IF(X9="ja",1,0) -> 0 | AT9: =Z9/5 -> 0.2 | AU9: =AA9/5 -> 1
A10: B07 | B10: [3 qubits] Peres gate (Toffoli + CNOT) | C10: gate | D10: computer science | E10: 1985 | F10: Peres 1985 | G10: T | H10: nee | I10: 0 | J10: geen | K10: 1 | L10: ja | M10: nee | N10: nee | O10: exact | P10: 0 | Q10: 1 T | R10: - | S10: O(1) | T10: ja | U10: nee | V10: nee | W10: Bennett | X10: nee | Y10: laag | Z10: 1 | AA10: 5 | AB10: 0 | AC10: 0 | AD10: deels | AE10: ja | AF10: same Toffoli count as Toffoli+CNOT | in nieuw ontwerp: - | AH10: =IF(H10="ja",1,0) -> 0 | AI10: =IF(J10="schoon",1,IF(J10="vuil",0.5,0)) -> 0 | AJ10: =K10/5 -> 0.2 | AK10: =IF(L10="ja",1,0) -> 1 | AL10: =IF(M10="ja",1,0) -> 0 | AM10: =IF(N10="ja",1,0) -> 0 | AN10: =IF(O10="exact",1,0) -> 1 | AO10: =IF(T10="ja",1,0) -> 1 | AP10: =IF(U10="ja",1,0) -> 0 | AQ10: =IF(V10="ja",1,0) -> 0 | AR10: =IF(W10="Bennett",1,IF(W10="meting",0.5,0)) -> 1 | AS10: =IF(X10="ja",1,0) -> 0 | AT10: =Z10/5 -> 0.2 | AU10: =AA10/5 -> 1
A11: B08 | B11: [3 qubits] Temporary logical-AND (measurement uncompute) | C11: gate | D11: physics | E11: 2013 | F11: Jones 2013; Gidney 2018 | G11: T | H11: ja | I11: 1 | J11: schoon | K11: 1 | L11: ja | M11: ja | N11: ja | O11: exact | P11: 0 | Q11: 1 T (uncompute 0) | R11: O(1) | S11: O(1) | T11: ja | U11: nee | V11: nee | W11: meting | X11: nee | Y11: midden | Z11: 2 | AA11: 5 | AB11: 0 | AC11: 0 | AD11: ja | AE11: ja | AF11: halves adder Toffolis | in nieuw ontwerp: T6 | AH11: =IF(H11="ja",1,0) -> 1 | AI11: =IF(J11="schoon",1,IF(J11="vuil",0.5,0)) -> 1 | AJ11: =K11/5 -> 0.2 | AK11: =IF(L11="ja",1,0) -> 1 | AL11: =IF(M11="ja",1,0) -> 1 | AM11: =IF(N11="ja",1,0) -> 1 | AN11: =IF(O11="exact",1,0) -> 1 | AO11: =IF(T11="ja",1,0) -> 1 | AP11: =IF(U11="ja",1,0) -> 0 | AQ11: =IF(V11="ja",1,0) -> 0 | AR11: =IF(W11="Bennett",1,IF(W11="meting",0.5,0)) -> 0.5 | AS11: =IF(X11="ja",1,0) -> 0 | AT11: =Z11/5 -> 0.4 | AU11: =AA11/5 -> 1
A12: B09 | B12: [4 qubits] Half adder (Toffoli + CNOT) | C12: adder | D12: computer science | E12: 1996 | F12: Vedral-Barenco-Ekert 1996 | G12: basis | H12: ja | I12: 1 | J12: schoon | K12: 1 | L12: ja | M12: nee | N12: nee | O12: exact | P12: 0 | Q12: 1 T | R12: O(1) | S12: O(1) | T12: ja | U12: nee | V12: nee | W12: Bennett | X12: nee | Y12: laag | Z12: 1 | AA12: 5 | AB12: 0 | AC12: 0 | AD12: ja | AE12: ja | AF12: | in nieuw ontwerp: S | AH12: =IF(H12="ja",1,0) -> 1 | AI12: =IF(J12="schoon",1,IF(J12="vuil",0.5,0)) -> 1 | AJ12: =K12/5 -> 0.2 | AK12: =IF(L12="ja",1,0) -> 1 | AL12: =IF(M12="ja",1,0) -> 0 | AM12: =IF(N12="ja",1,0) -> 0 | AN12: =IF(O12="exact",1,0) -> 1 | AO12: =IF(T12="ja",1,0) -> 1 | AP12: =IF(U12="ja",1,0) -> 0 | AQ12: =IF(V12="ja",1,0) -> 0 | AR12: =IF(W12="Bennett",1,IF(W12="meting",0.5,0)) -> 1 | AS12: =IF(X12="ja",1,0) -> 0 | AT12: =Z12/5 -> 0.2 | AU12: =AA12/5 -> 1
A13: B10 | B13: [4 qubits] Full adder MAJ / UMA (Cuccaro) | C13: adder | D13: computer science | E13: 2004 | F13: Cuccaro et al. 2004 | G13: basis | H13: ja | I13: 1 | J13: schoon | K13: 1 | L13: ja | M13: nee | N13: nee | O13: exact | P13: 0 | Q13: 2 T | R13: O(1) | S13: O(1) | T13: ja | U13: nee | V13: nee | W13: Bennett | X13: nee | Y13: laag | Z13: 1 | AA13: 5 | AB13: 0 | AC13: 0 | AD13: nee | AE13: ja | AF13: building block of CDKM | in nieuw ontwerp: S | AH13: =IF(H13="ja",1,0) -> 1 | AI13: =IF(J13="schoon",1,IF(J13="vuil",0.5,0)) -> 1 | AJ13: =K13/5 -> 0.2 | AK13: =IF(L13="ja",1,0) -> 1 | AL13: =IF(M13="ja",1,0) -> 0 | AM13: =IF(N13="ja",1,0) -> 0 | AN13: =IF(O13="exact",1,0) -> 1 | AO13: =IF(T13="ja",1,0) -> 1 | AP13: =IF(U13="ja",1,0) -> 0 | AQ13: =IF(V13="ja",1,0) -> 0 | AR13: =IF(W13="Bennett",1,IF(W13="meting",0.5,0)) -> 1 | AS13: =IF(X13="ja",1,0) -> 0 | AT13: =Z13/5 -> 0.2 | AU13: =AA13/5 -> 1
A14: B11 | B14: [n-bit] VBE ripple adder | C14: adder | D14: computer science | E14: 1996 | F14: Vedral-Barenco-Ekert 1996 | G14: T | H14: ja | I14: 256 | J14: schoon | K14: 2 | L14: ja | M14: nee | N14: nee | O14: exact | P14: 0 | Q14: ~4n | R14: O(2n) | S14: O(n) | T14: ja | U14: nee | V14: nee | W14: Bennett | X14: nee | Y14: laag | Z14: 1 | AA14: 5 | AB14: 200 | AC14: 256 | AD14: nee | AE14: nee | AF14: historical; 4n T | in nieuw ontwerp: - | AH14: =IF(H14="ja",1,0) -> 1 | AI14: =IF(J14="schoon",1,IF(J14="vuil",0.5,0)) -> 1 | AJ14: =K14/5 -> 0.4 | AK14: =IF(L14="ja",1,0) -> 1 | AL14: =IF(M14="ja",1,0) -> 0 | AM14: =IF(N14="ja",1,0) -> 0 | AN14: =IF(O14="exact",1,0) -> 1 | AO14: =IF(T14="ja",1,0) -> 1 | AP14: =IF(U14="ja",1,0) -> 0 | AQ14: =IF(V14="ja",1,0) -> 0 | AR14: =IF(W14="Bennett",1,IF(W14="meting",0.5,0)) -> 1 | AS14: =IF(X14="ja",1,0) -> 0 | AT14: =Z14/5 -> 0.2 | AU14: =AA14/5 -> 1
A15: B12 | B15: [n-bit] CDKM / Cuccaro ripple adder | C15: adder | D15: computer science | E15: 2004 | F15: Cuccaro et al. 2004 | G15: Q | H15: ja | I15: 1 | J15: schoon | K15: 2 | L15: ja | M15: nee | N15: nee | O15: exact | P15: 0 | Q15: 2n-1 | R15: O(1) | S15: O(n) | T15: ja | U15: nee | V15: nee | W15: Bennett | X15: nee | Y15: laag | Z15: 1 | AA15: 5 | AB15: 25 | AC15: -60 | AD15: nee | AE15: ja | AF15: strict design's adder | in nieuw ontwerp: S | AH15: =IF(H15="ja",1,0) -> 1 | AI15: =IF(J15="schoon",1,IF(J15="vuil",0.5,0)) -> 1 | AJ15: =K15/5 -> 0.4 | AK15: =IF(L15="ja",1,0) -> 1 | AL15: =IF(M15="ja",1,0) -> 0 | AM15: =IF(N15="ja",1,0) -> 0 | AN15: =IF(O15="exact",1,0) -> 1 | AO15: =IF(T15="ja",1,0) -> 1 | AP15: =IF(U15="ja",1,0) -> 0 | AQ15: =IF(V15="ja",1,0) -> 0 | AR15: =IF(W15="Bennett",1,IF(W15="meting",0.5,0)) -> 1 | AS15: =IF(X15="ja",1,0) -> 0 | AT15: =Z15/5 -> 0.2 | AU15: =AA15/5 -> 1
... A36: B33 | B36: [n-bit] QROM unary iteration lookup | C36: lookup | D36: computer science | E36: 2018 | F36: Babbush et al. 2018 | G36: T | H36: ja | I36: 10 | J36: schoon | K36: 2 | L36: ja | M36: ja | N36: ja | O36: exact | P36: 0 | Q36: L-1 | R36: O(log L) | S36: O(L) | T36: ja | U36: nee | V36: nee | W36: meting | X36: ja | Y36: midden | Z36: 3 | AA36: 5 | AB36: 0 | AC36: 0 | AD36: nee | AE36: ja | AF36: no table pays here (crossfield doc) | in nieuw ontwerp: - | AH36: =IF(H36="ja",1,0) -> 1 | AI36: =IF(J36="schoon",1,IF(J36="vuil",0.5,0)) -> 1 | AJ36: =K36/5 -> 0.4 | AK36: =IF(L36="ja",1,0) -> 1 | AL36: =IF(M36="ja",1,0) -> 1 | AM36: =IF(N36="ja",1,0) -> 1 | AN36: =IF(O36="exact",1,0) -> 1 | AO36: =IF(T36="ja",1,0) -> 1 | AP36: =IF(U36="ja",1,0) -> 0 | AQ36: =IF(V36="ja",1,0) -> 0 | AR36: =IF(W36="Bennett",1,IF(W36="meting",0.5,0)) -> 0.5 | AS36: =IF(X36="ja",1,0) -> 1 | AT36: =Z36/5 -> 0.6 | AU36: =AA36/5 -> 1
A37: B34 | B37: [n-bit] QFT (Fourier transform) | C37: transform | D37: physics | E37: 1994 | F37: Shor 1994; Coppersmith 1994 | G37: basis | H37: nee | I37: 0 | J37: geen | K37: 4 | L37: ja | M37: nee | N37: nee | O37: exact | P37: 0 | Q37: rotations | R37: O(n) | S37: O(n log n) | T37: nee | U37: ja | V37: nee | W37: geen | X37: nee | Y37: hoog | Z37: 2 | AA37: 5 | AB37: n.a. | AC37: n.a. | AD37: nee | AE37: nee | AF37: outer algorithm; gate set excludes | in nieuw ontwerp: - | AH37: =IF(H37="ja",1,0) -> 0 | AI37: =IF(J37="schoon",1,IF(J37="vuil",0.5,0)) -> 0 | AJ37: =K37/5 -> 0.8 | AK37: =IF(L37="ja",1,0) -> 1 | AL37: =IF(M37="ja",1,0) -> 0 | AM37: =IF(N37="ja",1,0) -> 0 | AN37: =IF(O37="exact",1,0) -> 1 | AO37: =IF(T37="ja",1,0) -> 0 | AP37: =IF(U37="ja",1,0) -> 1 | AQ37: =IF(V37="ja",1,0) -> 0 | AR37: =IF(W37="Bennett",1,IF(W37="meting",0.5,0)) -> 0 | AS37: =IF(X37="ja",1,0) -> 0 | AT37: =Z37/5 -> 0.4 | AU37: =AA37/5 -> 1
A38: B35 | B38: [n-bit] Half-delta divsteps step (swap, add/sub, halve) | C38: inversion | D38: mathematics | E38: 2021 | F38: Bernstein-Yang 2019; sipa | G38: exactness | H38: ja | I38: 2 | J38: schoon | K38: 3 | L38: ja | M38: nee | N38: nee | O38: exact | P38: 0 | Q38: ~2w + payload | R38: O(n) | S38: O(n) | T38: ja | U38: nee | V38: ja | W38: Bennett | X38: nee | Y38: laag | Z38: 3 | AA38: 4 | AB38: 40 | AC38: 500 | AD38: nee | AE38: ja | AF38: core of the novel design | in nieuw ontwerp: T6,S | AH38: =IF(H38="ja",1,0) -> 1 | AI38: =IF(J38="schoon",1,IF(J38="vuil",0.5,0)) -> 1 | AJ38: =K38/5 -> 0.6 | AK38: =IF(L38="ja",1,0) -> 1 | AL38: =IF(M38="ja",1,0) -> 0 | AM38: =IF(N38="ja",1,0) -> 0 | AN38: =IF(O38="exact",1,0) -> 1 | AO38: =IF(T38="ja",1,0) -> 1 | AP38: =IF(U38="ja",1,0) -> 0 | AQ38: =IF(V38="ja",1,0) -> 1 | AR38: =IF(W38="Bennett",1,IF(W38="meting",0.5,0)) -> 1 | AS38: =IF(X38="ja",1,0) -> 0 | AT38: =Z38/5 -> 0.6 | AU38: =AA38/5 -> 0.8

Sheet Weging
A1: Gewichtenmodel: gewogen geschiktheid van elke kandidaat (Ongebruikt + Tekstboek). Pas de gele gewichten aan.
A3: Kenmerk | B3: Gewicht
A4: T-winst (T-effect, -10% = 1) | B4: 3
A5: Q-winst (Q-effect, -200 = 1) | B5: 3
A6: Exact | B6: 2
A7: Challenge-gateset | B7: 3
A8: Volwassenheid | B8: 1
A9: Lage complexiteit | B9: 1
A10: Nieuwheid (Gelijkheid) | B10: 1
A11: Toepasbaar op inversie | B11: 2
A12: Toepasbaar op payload | B12: 1
A13: Toepasbaar op breedte | B13: 1
A14: Combineerbaar met leader | B14: 1
A15: Bewijs / meting | B15: 1
A16: Som gewichten | B16: =SUM(B4:B15) -> 20
A18: ID | B18: Techniek | C18: Bron-blad | D18: f T-winst | E18: f Q-winst | F18: f exact | G18: f gateset | H18: f volwassen | I18: f eenvoud | J18: f nieuwheid | K18: Inversie (0-1) | L18: Payload (0-1) | M18: Breedte (0-1) | N18: Combineerbaar (0-1) | O18: Bewijs (0/0.5/1) | P18: Gewogen score | Q18: Rang
A19: =Ongebruikt!A4 -> U01 | B19: =Ongebruikt!B4 -> Half-delta divsteps (Bernstein-Yang hddivsteps) | C19: Ongebruikt | D19: =IF(ISNUMBER(Ongebruikt!AB4),MAX(-1,MIN(1,-Ongebruikt!AB4/10)),0) -> -1 | E19: =IF(ISNUMBER(Ongebruikt!AC4),MAX(-1,MIN(1,-Ongebruikt!AC4/200)),0) -> -1 | F19: =IF(Ongebruikt!O4="exact",1,0) -> 1 | G19: =IF(Ongebruikt!T4="ja",1,0) -> 1 | H19: =Ongebruikt!AA4/5 -> 0.8 | I19: =1-Ongebruikt!Z4/5 -> 0.4 | J19: =INDEX(Gelijkheid!$C:$C,MATCH(A19,Gelijkheid!$A:$A,0)) -> 0.014285714 | K19: 1 | L19: 0.3 | M19: 0 | N19: 0.5 | O19: 1 | P19: =($B$4*D19+$B$5*E19+$B$6*F19+$B$7*G19+$B$8*H19+$B$9*I19+$B$10*J19+$B$11*K19+$B$12*L19+$B$13*M19+$B$14*N19+$B$15*O19)/$B$16 -> 0.20071429 | Q19: =RANK(P19,$P$19:$P$89) -> 60
A20: =Ongebruikt!A5 -> U02 | B20: =Ongebruikt!B5 -> safegcd jump matrices (62-step batches from low bits) | C20: Ongebruikt | D20: =IF(ISNUMBER(Ongebruikt!AB5),MAX(-1,MIN(1,-Ongebruikt!AB5/10)),0) -> -1 | E20: =IF(ISNUMBER(Ongebruikt!AC5),MAX(-1,MIN(1,-Ongebruikt!AC5/200)),0) -> -1 | F20: =IF(Ongebruikt!O5="exact",1,0) -> 1 | G20: =IF(Ongebruikt!T5="ja",1,0) -> 1 | H20: =Ongebruikt!AA5/5 -> 0.6 | I20: =1-Ongebruikt!Z5/5 -> 0.2 | J20: =INDEX(Gelijkheid!$C:$C,MATCH(A20,Gelijkheid!$A:$A,0)) -> 0.014285714 | K20: 1 | L20: 0.3 | M20: 0 | N20: 0.5 | O20: 0 | P20: =($B$4*D20+$B$5*E20+$B$6*F20+$B$7*G20+$B$8*H20+$B$9*I20+$B$10*J20+$B$11*K20+$B$12*L20+$B$13*M20+$B$14*N20+$B$15*O20)/$B$16 -> 0.13071429 | Q20: =RANK(P20,$P$19:$P$89) -> 69
A21: =Ongebruikt!A6 -> U03 | B21: =Ongebruikt!B6 -> k-ary GCD with small-multiplier table (Sorenson/Weber) | C21: Ongebruikt | D21: =IF(ISNUMBER(Ongebruikt!AB6),MAX(-1,MIN(1,-Ongebruikt!AB6/10)),0) -> -1 | E21: =IF(ISNUMBER(Ongebruikt!AC6),MAX(-1,MIN(1,-Ongebruikt!AC6/200)),0) -> -1 | F21: =IF(Ongebruikt!O6="exact",1,0) -> 1 | G21: =IF(Ongebruikt!T6="ja",1,0) -> 1 | H21: =Ongebruikt!AA6/5 -> 0.4 | I21: =1-Ongebruikt!Z6/5 -> 0.2 | J21: =INDEX(Gelijkheid!$C:$C,MATCH(A21,Gelijkheid!$A:$A,0)) -> 0.1 | K21: 1 | L21: 0.3 | M21: 0 | N21: 0.5 | O21: 0 | P21: =($B$4*D21+$B$5*E21+$B$6*F21+$B$7*G21+$B$8*H21+$B$9*I21+$B$10*J21+$B$11*K21+$B$12*L21+$B$13*M21+$B$14*N21+$B$15*O21)/$B$16 -> 0.125 | Q21: =RANK(P21,$P$19:$P$89) -> 70
A22: =Ongebruikt!A7 -> U04 | B22: =Ongebruikt!B7 -> Lehmer / half-GCD (Schonhage, Stehle-Zimmermann) | C22: Ongebruikt | D22: =IF(ISNUMBER(Ongebruikt!AB7),MAX(-1,MIN(1,-Ongebruikt!AB7/10)),0) -> -1 | E22: =IF(ISNUMBER(Ongebruikt!AC7),MAX(-1,MIN(1,-Ongebruikt!AC7/200)),0) -> -1 | F22: =IF(Ongebruikt!O7="exact",1,0) -> 1 | G22: =IF(Ongebruikt!T7="ja",1,0) -> 1 | H22: =Ongebruikt!AA7/5 -> 0.4 | I22: =1-Ongebruikt!Z7/5 -> 0 | J22: =INDEX(Gelijkheid!$C:$C,MATCH(A22,Gelijkheid!$A:$A,0)) -> 0.057142857 | K22: 1 | L22: 0.3 | M22: 0 | N22: 0.5 | O22: 0 | P22: =($B$4*D22+$B$5*E22+$B$6*F22+$B$7*G22+$B$8*H22+$B$9*I22+$B$10*J22+$B$11*K22+$B$12*L22+$B$13*M22+$B$14*N22+$B$15*O22)/$B$16 -> 0.11285714 | Q22: =RANK(P22,$P$19:$P$89) -> 71
A23: =Ongebruikt!A8 -> U05 | B23: =Ongebruikt!B8 -> Extended Euclid with quotients + register sharing (Proos-Zalka) | C23: Ongebruikt | D23: =IF(ISNUMBER(Ongebruikt!AB8),MAX(-1,MIN(1,-Ongebruikt!AB8/10)),0) -> -1 | E23: =IF(ISNUMBER(Ongebruikt!AC8),MAX(-1,MIN(1,-Ongebruikt!AC8/200)),0) -> 1 | F23: =IF(Ongebruikt!O8="exact",1,0) -> 1 | G23: =IF(Ongebruikt!T8="ja",1,0) -> 1 | H23: =Ongebruikt!AA8/5 -> 0.6 | I23: =1-Ongebruikt!Z8/5 -> 0 | J23: =INDEX(Gelijkheid!$C:$C,MATCH(A23,Gelijkheid!$A:$A,0)) -> 0.057142857 | K23: 1 | L23: 0.3 | M23: 0 | N23: 0.5 | O23: 0 | P23: =($B$4*D23+$B$5*E23+$B$6*F23+$B$7*G23+$B$8*H23+$B$9*I23+$B$10*J23+$B$11*K23+$B$12*L23+$B$13*M23+$B$14*N23+$B$15*O23)/$B$16 -> 0.42285714 | Q23: =RANK(P23,$P$19:$P$89) -> 18
A24: =Ongebruikt!A9 -> U06 | B24: =Ongebruikt!B9 -> Kaliski Montgomery inverse with comparisons | C24: Ongebruikt | D24: =IF(ISNUMBER(Ongebruikt!AB9),MAX(-1,MIN(1,-Ongebruikt!AB9/10)),0) -> -1 | E24: =IF(ISNUMBER(Ongebruikt!AC9),MAX(-1,MIN(1,-Ongebruikt!AC9/200)),0) -> -1 | F24: =IF(Ongebruikt!O9="exact",1,0) -> 1 | G24: =IF(Ongebruikt!T9="ja",1,0) -> 1 | H24: =Ongebruikt!AA9/5 -> 1 | I24: =1-Ongebruikt!Z9/5 -> 0.4 | J24: =INDEX(Gelijkheid!$C:$C,MATCH(A24,Gelijkheid!$A:$A,0)) -> 0.028571429 | K24: 1 | L24: 0.3 | M24: 0 | N24: 0.5 | O24: 0 | P24: =($B$4*D24+$B$5*E24+$B$6*F24+$B$7*G24+$B$8*H24+$B$9*I24+$B$10*J24+$B$11*K24+$B$12*L24+$B$13*M24+$B$14*N24+$B$15*O24)/$B$16 -> 0.16142857 | Q24: =RANK(P24,$P$19:$P$89) -> 68
A25: =Ongebruikt!A10 -> U07 | B25: =Ongebruikt!B10 -> Fermat inversion a^(p-2) via addition chain | C25: Ongebruikt | D25: =IF(ISNUMBER(Ongebruikt!AB10),MAX(-1,MIN(1,-Ongebruikt!AB10/10)),0) -> -1 | E25: =IF(ISNUMBER(Ongebruikt!AC10),MAX(-1,MIN(1,-Ongebruikt!AC10/200)),0) -> -1 | F25: =IF(Ongebruikt!O10="exact",1,0) -> 1 | G25: =IF(Ongebruikt!T10="ja",1,0) -> 1 | H25: =Ongebruikt!AA10/5 -> 1 | I25: =1-Ongebruikt!Z10/5 -> 0.6 | J25: =INDEX(Gelijkheid!$C:$C,MATCH(A25,Gelijkheid!$A:$A,0)) -> 0.042857143 | K25: 1 | L25: 0.3 | M25: 0 | N25: 0.5 | O25: 1 | P25: =($B$4*D25+$B$5*E25+$B$6*F25+$B$7*G25+$B$8*H25+$B$9*I25+$B$10*J25+$B$11*K25+$B$12*L25+$B$13*M25+$B$14*N25+$B$15*O25)/$B$16 -> 0.22214286 | Q25: =RANK(P25,$P$19:$P$89) -> 58
A26: =Ongebruikt!A11 -> U08 | B26: =Ongebruikt!B11 -> Spooky pebbling (measurement-based pebble game) | C26: Ongebruikt | D26: =IF(ISNUMBER(Ongebruikt!AB11),MAX(-1,MIN(1,-Ongebruikt!AB11/10)),0) -> -1 | E26: =IF(ISNUMBER(Ongebruikt!AC11),MAX(-1,MIN(1,-Ongebruikt!AC11/200)),0) -> 0.75 | F26: =IF(Ongebruikt!O11="exact",1,0) -> 1 | G26: =IF(Ongebruikt!T11="ja",1,0) -> 1 | H26: =Ongebruikt!AA11/5 -> 0.6 | I26: =1-Ongebruikt!Z11/5 -> 0.2 | J26: =INDEX(Gelijkheid!$C:$C,MATCH(A26,Gelijkheid!$A:$A,0)) -> 0.11428571 | K26: 0.3 | L26: 0 | M26: 1 | N26: 0.5 | O26: 0 | P26: =($B$4*D26+$B$5*E26+$B$6*F26+$B$7*G26+$B$8*H26+$B$9*I26+$B$10*J26+$B$11*K26+$B$12*L26+$B$13*M26+$B$14*N26+$B$15*O26)/$B$16 -> 0.36321429 | Q26: =RANK(P26,$P$19:$P$89) -> 38
A27: =Ongebruikt!A12 -> U09 | B27: =Ongebruikt!B12 -> Knill optimal reversible pebbling | C27: Ongebruikt | D27: =IF(ISNUMBER(Ongebruikt!AB12),MAX(-1,MIN(1,-Ongebruikt!AB12/10)),0) -> -1 | E27: =IF(ISNUMBER(Ongebruikt!AC12),MAX(-1,MIN(1,-Ongebruikt!AC12/200)),0) -> 0.5 | F27: =IF(Ongebruikt!O12="exact",1,0) -> 1 | G27: =IF(Ongebruikt!T12="ja",1,0) -> 1 | H27: =Ongebruikt!AA12/5 -> 1 | I27: =1-Ongebruikt!Z12/5 -> 0.6 | J27: =INDEX(Gelijkheid!$C:$C,MATCH(A27,Gelijkheid!$A:$A,0)) -> 0.17857143 | K27: 0.3 | L27: 0 | M27: 1 | N27: 0.5 | O27: 1 | P27: =($B$4*D27+$B$5*E27+$B$6*F27+$B$7*G27+$B$8*H27+$B$9*I27+$B$10*J27+$B$11*K27+$B$12*L27+$B$13*M27+$B$14*N27+$B$15*O27)/$B$16 -> 0.41892857 | Q27: =RANK(P27,$P$19:$P$89) -> 19
A28: =Ongebruikt!A13 -> U10 | B28: =Ongebruikt!B13 -> SAT-based reversible pebbling (Meuli et al.) | C28: Ongebruikt | D28: =IF(ISNUMBER(Ongebruikt!AB13),MAX(-1,MIN(1,-Ongebruikt!AB13/10)),0) -> -1 | E28: =IF(ISNUMBER(Ongebruikt!AC13),MAX(-1,MIN(1,-Ongebruikt!AC13/200)),0) -> 0.4 | F28: =IF(Ongebruikt!O13="exact",1,0) -> 1 | G28: =IF(Ongebruikt!T13="ja",1,0) -> 1 | H28: =Ongebruikt!AA13/5 -> 0.6 | I28: =1-Ongebruikt!Z13/5 -> 0.4 | J28: =INDEX(Gelijkheid!$C:$C,MATCH(A28,Gelijkheid!$A:$A,0)) -> 0.16428571 | K28: 0.3 | L28: 0 | M28: 1 | N28: 0.5 | O28: 1 | P28: =($B$4*D28+$B$5*E28+$B$6*F28+$B$7*G28+$B$8*H28+$B$9*I28+$B$10*J28+$B$11*K28+$B$12*L28+$B$13*M28+$B$14*N28+$B$15*O28)/$B$16 -> 0.37321429 | Q28: =RANK(P28,$P$19:$P$89) -> 35
A29: =Ongebruikt!A14 -> U11 | B29: =Ongebruikt!B14 -> Coset representation of modular integers | C29: Ongebruikt | D29: =IF(ISNUMBER(Ongebruikt!AB14),MAX(-1,MIN(1,-Ongebruikt!AB14/10)),0) -> 0.3 | E29: =IF(ISNUMBER(Ongebruikt!AC14),MAX(-1,MIN(1,-Ongebruikt!AC14/200)),0) -> -0.24 | F29: =IF(Ongebruikt!O14="exact",1,0) -> 0 | G29: =IF(Ongebruikt!T14="ja",1,0) -> 1 | H29: =Ongebruikt!AA14/5 -> 0.8 | I29: =1-Ongebruikt!Z14/5 -> 0.4 | J29: =INDEX(Gelijkheid!$C:$C,MATCH(A29,Gelijkheid!$A:$A,0)) -> 0.13571429 | K29: 0.3 | L29: 1 | M29: 0 | N29: 0.5 | O29: 0 | P29: =($B$4*D29+$B$5*E29+$B$6*F29+$B$7*G29+$B$8*H29+$B$9*I29+$B$10*J29+$B$11*K29+$B$12*L29+$B$13*M29+$B$14*N29+$B$15*O29)/$B$16 -> 0.33078571 | Q29: =RANK(P29,$P$19:$P$89) -> 43
A30: =Ongebruikt!A15 -> U12 | B30: =Ongebruikt!B15 -> Oblivious carry runways (piecewise adders) | C30: Ongebruikt | D30: =IF(ISNUMBER(Ongebruikt!AB15),MAX(-1,MIN(1,-Ongebruikt!AB15/10)),0) -> -0.2 | E30: =IF(ISNUMBER(Ongebruikt!AC15),MAX(-1,MIN(1,-Ongebruikt!AC15/200)),0) -> -0.2 | F30: =IF(Ongebruikt!O15="exact",1,0) -> 0 | G30: =IF(Ongebruikt!T15="ja",1,0) -> 1 | H30: =Ongebruikt!AA15/5 -> 0.8 | I30: =1-Ongebruikt!Z15/5 -> 0.4 | J30: =INDEX(Gelijkheid!$C:$C,MATCH(A30,Gelijkheid!$A:$A,0)) -> 0.15 | K30: 0.3 | L30: 1 | M30: 0.3 | N30: 0.5 | O30: 0 | P30: =($B$4*D30+$B$5*E30+$B$6*F30+$B$7*G30+$B$8*H30+$B$9*I30+$B$10*J30+$B$11*K30+$B$12*L30+$B$13*M30+$B$14*N30+$B$15*O30)/$B$16 -> 0.2775 | Q30: =RANK(P30,$P$19:$P$89) -> 54
... A54: =Ongebruikt!A39 -> U36 | B54: =Ongebruikt!B39 -> ZK-proof validation of withheld circuits | C54: Ongebruikt | D54: =IF(ISNUMBER(Ongebruikt!AB39),MAX(-1,MIN(1,-Ongebruikt!AB39/10)),0) -> 0 | E54: =IF(ISNUMBER(Ongebruikt!AC39),MAX(-1,MIN(1,-Ongebruikt!AC39/200)),0) -> 0 | F54: =IF(Ongebruikt!O39="exact",1,0) -> 1 | G54: =IF(Ongebruikt!T39="ja",1,0) -> 1 | H54: =Ongebruikt!AA39/5 -> 0.6 | I54: =1-Ongebruikt!Z39/5 -> 0 | J54: =INDEX(Gelijkheid!$C:$C,MATCH(A54,Gelijkheid!$A:$A,0)) -> 0.042857143 | K54: 0 | L54: 0 | M54: 0 | N54: 0 | O54: 0 | P54: =($B$4*D54+$B$5*E54+$B$6*F54+$B$7*G54+$B$8*H54+$B$9*I54+$B$10*J54+$B$11*K54+$B$12*L54+$B$13*M54+$B$14*N54+$B$15*O54)/$B$16 -> 0.28214286 | Q54: =RANK(P54,$P$19:$P$89) -> 52
A55: =Tekstboek!A4 -> B01 | B55: =Tekstboek!B4 -> [2 qubits] CNOT / CZ | C55: Tekstboek | D55: =IF(ISNUMBER(Tekstboek!AB4),MAX(-1,MIN(1,-Tekstboek!AB4/10)),0) -> 0 | E55: =IF(ISNUMBER(Tekstboek!AC4),MAX(-1,MIN(1,-Tekstboek!AC4/200)),0) -> 0 | F55: =IF(Tekstboek!O4="exact",1,0) -> 1 | G55: =IF(Tekstboek!T4="ja",1,0) -> 1 | H55: =Tekstboek!AA4/5 -> 1 | I55: =1-Tekstboek!Z4/5 -> 0.8 | J55: =INDEX(Gelijkheid!$C:$C,MATCH(A55,Gelijkheid!$A:$A,0)) -> 0.11428571 | K55: 0 | L55: 0 | M55: 0 | N55: 0.5 | O55: 0.5 | P55: =($B$4*D55+$B$5*E55+$B$6*F55+$B$7*G55+$B$8*H55+$B$9*I55+$B$10*J55+$B$11*K55+$B$12*L55+$B$13*M55+$B$14*N55+$B$15*O55)/$B$16 -> 0.39571429 | Q55: =RANK(P55,$P$19:$P$89) -> 26
A56: =Tekstboek!A5 -> B02 | B56: =Tekstboek!B5 -> [2 qubits] SWAP (3 CNOT) / wire relabel | C56: Tekstboek | D56: =IF(ISNUMBER(Tekstboek!AB5),MAX(-1,MIN(1,-Tekstboek!AB5/10)),0) -> 0 | E56: =IF(ISNUMBER(Tekstboek!AC5),MAX(-1,MIN(1,-Tekstboek!AC5/200)),0) -> 0 | F56: =IF(Tekstboek!O5="exact",1,0) -> 1 | G56: =IF(Tekstboek!T5="ja",1,0) -> 1 | H56: =Tekstboek!AA5/5 -> 1 | I56: =1-Tekstboek!Z5/5 -> 0.8 | J56: =INDEX(Gelijkheid!$C:$C,MATCH(A56,Gelijkheid!$A:$A,0)) -> 0.042857143 | K56: 0 | L56: 0 | M56: 0 | N56: 0.5 | O56: 0.5 | P56: =($B$4*D56+$B$5*E56+$B$6*F56+$B$7*G56+$B$8*H56+$B$9*I56+$B$10*J56+$B$11*K56+$B$12*L56+$B$13*M56+$B$14*N56+$B$15*O56)/$B$16 -> 0.39214286 | Q56: =RANK(P56,$P$19:$P$89) -> 28
A57: =Tekstboek!A6 -> B03 | B57: =Tekstboek!B6 -> [2 qubits] Z-basis measurement + reset | C57: Tekstboek | D57: =IF(ISNUMBER(Tekstboek!AB6),MAX(-1,MIN(1,-Tekstboek!AB6/10)),0) -> 0 | E57: =IF(ISNUMBER(Tekstboek!AC6),MAX(-1,MIN(1,-Tekstboek!AC6/200)),0) -> 0 | F57: =IF(Tekstboek!O6="exact",1,0) -> 1 | G57: =IF(Tekstboek!T6="ja",1,0) -> 1 | H57: =Tekstboek!AA6/5 -> 1 | I57: =1-Tekstboek!Z6/5 -> 0.8 | J57: =INDEX(Gelijkheid!$C:$C,MATCH(A57,Gelijkheid!$A:$A,0)) -> 0.1 | K57: 0 | L57: 0 | M57: 0 | N57: 0.5 | O57: 0.5 | P57: =($B$4*D57+$B$5*E57+$B$6*F57+$B$7*G57+$B$8*H57+$B$9*I57+$B$10*J57+$B$11*K57+$B$12*L57+$B$13*M57+$B$14*N57+$B$15*O57)/$B$16 -> 0.395 | Q57: =RANK(P57,$P$19:$P$89) -> 27
A58: =Tekstboek!A7 -> B04 | B58: =Tekstboek!B7 -> [2 qubits] X-basis measurement (HMR) + classically controlled CZ | C58: Tekstboek | D58: =IF(ISNUMBER(Tekstboek!AB7),MAX(-1,MIN(1,-Tekstboek!AB7/10)),0) -> 0 | E58: =IF(ISNUMBER(Tekstboek!AC7),MAX(-1,MIN(1,-Tekstboek!AC7/200)),0) -> 0 | F58: =IF(Tekstboek!O7="exact",1,0) -> 1 | G58: =IF(Tekstboek!T7="ja",1,0) -> 1 | H58: =Tekstboek!AA7/5 -> 1 | I58: =1-Tekstboek!Z7/5 -> 0.6 | J58: =INDEX(Gelijkheid!$C:$C,MATCH(A58,Gelijkheid!$A:$A,0)) -> 0.028571429 | K58: 0 | L58: 0 | M58: 0 | N58: 0.5 | O58: 0.5 | P58: =($B$4*D58+$B$5*E58+$B$6*F58+$B$7*G58+$B$8*H58+$B$9*I58+$B$10*J58+$B$11*K58+$B$12*L58+$B$13*M58+$B$14*N58+$B$15*O58)/$B$16 -> 0.38142857 | Q58: =RANK(P58,$P$19:$P$89) -> 34
A59: =Tekstboek!A8 -> B05 | B59: =Tekstboek!B8 -> [3 qubits] Toffoli (CCX) / CCZ | C59: Tekstboek | D59: =IF(ISNUMBER(Tekstboek!AB8),MAX(-1,MIN(1,-Tekstboek!AB8/10)),0) -> 0 | E59: =IF(ISNUMBER(Tekstboek!AC8),MAX(-1,MIN(1,-Tekstboek!AC8/200)),0) -> 0 | F59: =IF(Tekstboek!O8="exact",1,0) -> 1 | G59: =IF(Tekstboek!T8="ja",1,0) -> 1 | H59: =Tekstboek!AA8/5 -> 1 | I59: =1-Tekstboek!Z8/5 -> 0.8 | J59: =INDEX(Gelijkheid!$C:$C,MATCH(A59,Gelijkheid!$A:$A,0)) -> 0.15 | K59: 0 | L59: 0 | M59: 0 | N59: 0.5 | O59: 0.5 | P59: =($B$4*D59+$B$5*E59+$B$6*F59+$B$7*G59+$B$8*H59+$B$9*I59+$B$10*J59+$B$11*K59+$B$12*L59+$B$13*M59+$B$14*N59+$B$15*O59)/$B$16 -> 0.3975 | Q59: =RANK(P59,$P$19:$P$89) -> 23
A60: =Tekstboek!A9 -> B06 | B60: =Tekstboek!B9 -> [3 qubits] Fredkin (controlled SWAP) | C60: Tekstboek | D60: =IF(ISNUMBER(Tekstboek!AB9),MAX(-1,MIN(1,-Tekstboek!AB9/10)),0) -> 0 | E60: =IF(ISNUMBER(Tekstboek!AC9),MAX(-1,MIN(1,-Tekstboek!AC9/200)),0) -> 0 | F60: =IF(Tekstboek!O9="exact",1,0) -> 1 | G60: =IF(Tekstboek!T9="ja",1,0) -> 1 | H60: =Tekstboek!AA9/5 -> 1 | I60: =1-Tekstboek!Z9/5 -> 0.8 | J60: =INDEX(Gelijkheid!$C:$C,MATCH(A60,Gelijkheid!$A:$A,0)) -> 0.15 | K60: 0 | L60: 0 | M60: 0 | N60: 0.5 | O60: 0.5 | P60: =($B$4*D60+$B$5*E60+$B$6*F60+$B$7*G60+$B$8*H60+$B$9*I60+$B$10*J60+$B$11*K60+$B$12*L60+$B$13*M60+$B$14*N60+$B$15*O60)/$B$16 -> 0.3975 | Q60: =RANK(P60,$P$19:$P$89) -> 23
A61: =Tekstboek!A10 -> B07 | B61: =Tekstboek!B10 -> [3 qubits] Peres gate (Toffoli + CNOT) | C61: Tekstboek | D61: =IF(ISNUMBER(Tekstboek!AB10),MAX(-1,MIN(1,-Tekstboek!AB10/10)),0) -> 0 | E61: =IF(ISNUMBER(Tekstboek!AC10),MAX(-1,MIN(1,-Tekstboek!AC10/200)),0) -> 0 | F61: =IF(Tekstboek!O10="exact",1,0) -> 1 | G61: =IF(Tekstboek!T10="ja",1,0) -> 1 | H61: =Tekstboek!AA10/5 -> 1 | I61: =1-Tekstboek!Z10/5 -> 0.8 | J61: =INDEX(Gelijkheid!$C:$C,MATCH(A61,Gelijkheid!$A:$A,0)) -> 0.15 | K61: 0 | L61: 0 | M61: 0 | N61: 0.5 | O61: 0.5 | P61: =($B$4*D61+$B$5*E61+$B$6*F61+$B$7*G61+$B$8*H61+$B$9*I61+$B$10*J61+$B$11*K61+$B$12*L61+$B$13*M61+$B$14*N61+$B$15*O61)/$B$16 -> 0.3975 | Q61: =RANK(P61,$P$19:$P$89) -> 23
A62: =Tekstboek!A11 -> B08 | B62: =Tekstboek!B11 -> [3 qubits] Temporary logical-AND (measurement uncompute) | C62: Tekstboek | D62: =IF(ISNUMBER(Tekstboek!AB11),MAX(-1,MIN(1,-Tekstboek!AB11/10)),0) -> 0 | E62: =IF(ISNUMBER(Tekstboek!AC11),MAX(-1,MIN(1,-Tekstboek!AC11/200)),0) -> 0 | F62: =IF(Tekstboek!O11="exact",1,0) -> 1 | G62: =IF(Tekstboek!T11="ja",1,0) -> 1 | H62: =Tekstboek!AA11/5 -> 1 | I62: =1-Tekstboek!Z11/5 -> 0.6 | J62: =INDEX(Gelijkheid!$C:$C,MATCH(A62,Gelijkheid!$A:$A,0)) -> 0.22857143 | K62: 0 | L62: 0 | M62: 0 | N62: 0.5 | O62: 0.5 | P62: =($B$4*D62+$B$5*E62+$B$6*F62+$B$7*G62+$B$8*H62+$B$9*I62+$B$10*J62+$B$11*K62+$B$12*L62+$B$13*M62+$B$14*N62+$B$15*O62)/$B$16 -> 0.39142857 | Q62: =RANK(P62,$P$19:$P$89) -> 29
A63: =Tekstboek!A12 -> B09 | B63: =Tekstboek!B12 -> [4 qubits] Half adder (Toffoli + CNOT) | C63: Tekstboek | D63: =IF(ISNUMBER(Tekstboek!AB12),MAX(-1,MIN(1,-Tekstboek!AB12/10)),0) -> 0 | E63: =IF(ISNUMBER(Tekstboek!AC12),MAX(-1,MIN(1,-Tekstboek!AC12/200)),0) -> 0 | F63: =IF(Tekstboek!O12="exact",1,0) -> 1 | G63: =IF(Tekstboek!T12="ja",1,0) -> 1 | H63: =Tekstboek!AA12/5 -> 1 | I63: =1-Tekstboek!Z12/5 -> 0.8 | J63: =INDEX(Gelijkheid!$C:$C,MATCH(A63,Gelijkheid!$A:$A,0)) -> 0.12857143 | K63: 0.3 | L63: 1 | M63: 0.3 | N63: 0.5 | O63: 0.5 | P63: =($B$4*D63+$B$5*E63+$B$6*F63+$B$7*G63+$B$8*H63+$B$9*I63+$B$10*J63+$B$11*K63+$B$12*L63+$B$13*M63+$B$14*N63+$B$15*O63)/$B$16 -> 0.49142857 | Q63: =RANK(P63,$P$19:$P$89) -> 5
A64: =Tekstboek!A13 -> B10 | B64: =Tekstboek!B13 -> [4 qubits] Full adder MAJ / UMA (Cuccaro) | C64: Tekstboek | D64: =IF(ISNUMBER(Tekstboek!AB13),MAX(-1,MIN(1,-Tekstboek!AB13/10)),0) -> 0 | E64: =IF(ISNUMBER(Tekstboek!AC13),MAX(-1,MIN(1,-Tekstboek!AC13/200)),0) -> 0 | F64: =IF(Tekstboek!O13="exact",1,0) -> 1 | G64: =IF(Tekstboek!T13="ja",1,0) -> 1 | H64: =Tekstboek!AA13/5 -> 1 | I64: =1-Tekstboek!Z13/5 -> 0.8 | J64: =INDEX(Gelijkheid!$C:$C,MATCH(A64,Gelijkheid!$A:$A,0)) -> 0.12857143 | K64: 0.3 | L64: 1 | M64: 0.3 | N64: 0.5 | O64: 0.5 | P64: =($B$4*D64+$B$5*E64+$B$6*F64+$B$7*G64+$B$8*H64+$B$9*I64+$B$10*J64+$B$11*K64+$B$12*L64+$B$13*M64+$B$14*N64+$B$15*O64)/$B$16 -> 0.49142857 | Q64: =RANK(P64,$P$19:$P$89) -> 5
A65: =Tekstboek!A14 -> B11 | B65: =Tekstboek!B14 -> [n-bit] VBE ripple adder | C65: Tekstboek | D65: =IF(ISNUMBER(Tekstboek!AB14),MAX(-1,MIN(1,-Tekstboek!AB14/10)),0) -> -1 | E65: =IF(ISNUMBER(Tekstboek!AC14),MAX(-1,MIN(1,-Tekstboek!AC14/200)),0) -> -1 | F65: =IF(Tekstboek!O14="exact",1,0) -> 1 | G65: =IF(Tekstboek!T14="ja",1,0) -> 1 | H65: =Tekstboek!AA14/5 -> 1 | I65: =1-Tekstboek!Z14/5 -> 0.8 | J65: =INDEX(Gelijkheid!$C:$C,MATCH(A65,Gelijkheid!$A:$A,0)) -> 0.11428571 | K65: 0.3 | L65: 1 | M65: 0.3 | N65: 0.5 | O65: 0.5 | P65: =($B$4*D65+$B$5*E65+$B$6*F65+$B$7*G65+$B$8*H65+$B$9*I65+$B$10*J65+$B$11*K65+$B$12*L65+$B$13*M65+$B$14*N65+$B$15*O65)/$B$16 -> 0.19071429 | Q65: =RANK(P65,$P$19:$P$89) -> 62
A66: =Tekstboek!A15 -> B12 | B66: =Tekstboek!B15 -> [n-bit] CDKM / Cuccaro ripple adder | C66: Tekstboek | D66: =IF(ISNUMBER(Tekstboek!AB15),MAX(-1,MIN(1,-Tekstboek!AB15/10)),0) -> -1 | E66: =IF(ISNUMBER(Tekstboek!AC15),MAX(-1,MIN(1,-Tekstboek!AC15/200)),0) -> 0.3 | F66: =IF(Tekstboek!O15="exact",1,0) -> 1 | G66: =IF(Tekstboek!T15="ja",1,0) -> 1 | H66: =Tekstboek!AA15/5 -> 1 | I66: =1-Tekstboek!Z15/5 -> 0.8 | J66: =INDEX(Gelijkheid!$C:$C,MATCH(A66,Gelijkheid!$A:$A,0)) -> 0.11428571 | K66: 0.3 | L66: 1 | M66: 0.3 | N66: 0.5 | O66: 0.5 | P66: =($B$4*D66+$B$5*E66+$B$6*F66+$B$7*G66+$B$8*H66+$B$9*I66+$B$10*J66+$B$11*K66+$B$12*L66+$B$13*M66+$B$14*N66+$B$15*O66)/$B$16 -> 0.38571429 | Q66: =RANK(P66,$P$19:$P$89) -> 32
... A89: =Tekstboek!A38 -> B35 | B89: =Tekstboek!B38 -> [n-bit] Half-delta divsteps step (swap, add/sub, halve) | C89: Tekstboek | D89: =IF(ISNUMBER(Tekstboek!AB38),MAX(-1,MIN(1,-Tekstboek!AB38/10)),0) -> -1 | E89: =IF(ISNUMBER(Tekstboek!AC38),MAX(-1,MIN(1,-Tekstboek!AC38/200)),0) -> -1 | F89: =IF(Tekstboek!O38="exact",1,0) -> 1 | G89: =IF(Tekstboek!T38="ja",1,0) -> 1 | H89: =Tekstboek!AA38/5 -> 0.8 | I89: =1-Tekstboek!Z38/5 -> 0.4 | J89: =INDEX(Gelijkheid!$C:$C,MATCH(A89,Gelijkheid!$A:$A,0)) -> 0.085714286 | K89: 1 | L89: 0.3 | M89: 0 | N89: 0.5 | O89: 0.5 | P89: =($B$4*D89+$B$5*E89+$B$6*F89+$B$7*G89+$B$8*H89+$B$9*I89+$B$10*J89+$B$11*K89+$B$12*L89+$B$13*M89+$B$14*N89+$B$15*O89)/$B$16 -> 0.17928571 | Q89: =RANK(P89,$P$19:$P$89) -> 65
A91: Extra eigenschappen (Inversie/Payload/Breedte/Combineerbaar/Bewijs) zijn oordelen per categorie; Bewijs = 1 als in deze repo gemeten, 0.5 voor tekstboek-primitieven met bekende formule.

Sheet Gelijkheid
A1: Gower-gelijkenis = 1 - gemiddelde |verschil| over 14 kenmerken (f:-kolommen van de catalogi). Nieuwheid = 1 - max gelijkenis met de gebruikte set.
A3: ID | B3: Techniek | C3: Nieuwheid | D3: Max gelijkenis | E3: Meest gelijkende gebruikte techniek | F3: =Gebruikt!A4 -> G01 | G3: =Gebruikt!A5 -> G02 | H3: =Gebruikt!A6 -> G03 | I3: =Gebruikt!A7 -> G04 | J3: =Gebruikt!A8 -> G05 | K3: =Gebruikt!A9 -> G06 | L3: =Gebruikt!A10 -> G07 | M3: =Gebruikt!A11 -> G08 | N3: =Gebruikt!A12 -> G09 | O3: =Gebruikt!A13 -> G10 | P3: =Gebruikt!A14 -> G11 | Q3: =Gebruikt!A15 -> G12 | R3: =Gebruikt!A16 -> G13 | S3: =Gebruikt!A17 -> G14 | T3: =Gebruikt!A18 -> G15 | U3: =Gebruikt!A19 -> G16 | V3: =Gebruikt!A20 -> G17 | W3: =Gebruikt!A21 -> G18 | X3: =Gebruikt!A22 -> G19 | Y3: =Gebruikt!A23 -> G20 | Z3: =Gebruikt!A24 -> G21 | AA3: =Gebruikt!A25 -> G22 | AB3: =Gebruikt!A26 -> G23 | AC3: =Gebruikt!A27 -> G24 | AD3: =Gebruikt!A28 -> G25 | AE3: =Gebruikt!A29 -> G26 | AF3: =Gebruikt!A30 -> G27 | AG3: =Gebruikt!A31 -> G28 | AH3: =Gebruikt!A32 -> G29 | AI3: =Gebruikt!A33 -> G30 | AJ3: =Gebruikt!A34 -> G31 | AK3: =Gebruikt!A35 -> G32 | AL3: =Gebruikt!A36 -> G33 | AM3: =Gebruikt!A37 -> G34 | AN3: =Gebruikt!A38 -> G35 | AO3: =Gebruikt!A39 -> G36 | AP3: =Gebruikt!A40 -> G37 | AQ3: =Gebruikt!A41 -> G38 | AR3: =Gebruikt!A42 -> G39 | AS3: =Gebruikt!A43 -> G40 | AT3: =Gebruikt!A44 -> G41 | AU3: =Gebruikt!A45 -> G42 | AV3: =Gebruikt!A46 -> G43 | AW3: =Gebruikt!A47 -> G44 | AX3: =Gebruikt!A48 -> G45
A4: =Ongebruikt!A4 -> U01 | B4: =Ongebruikt!B4 -> Half-delta divsteps (Bernstein-Yang hddivsteps) | C4: =1-D4 -> 0.014285714 | D4: =MAX(F4:AX4) -> 0.98571429 | E4: =INDEX(Gebruikt!$B$4:$B$48,MATCH(D4,F4:AX4,0)) -> Multi-bit shift per GCD step (jump-GCD K=2 to 8-way barrel e<=7) | F4: =1-SUMPRODUCT(ABS(Ongebruikt!$AH$4:$AU$4-Gebruikt!$AH$4:$AU$4))/14 -> 0.91428571 | G4: =1-SUMPRODUCT(ABS(Ongebruikt!$AH$4:$AU$4-Gebruikt!$AH$5:$AU$5))/14 -> 0.68571429 | H4: =1-SUMPRODUCT(ABS(Ongebruikt!$AH$4:$AU$4-Gebruikt!$AH$6:$AU$6))/14 -> 0.68571429 | I4: =1-SUMPRODUCT(ABS(Ongebruikt!$AH$4:$AU$4-Gebruikt!$AH$7:$AU$7))/14 -> 0.61428571 | J4: =1-SUMPRODUCT(ABS(Ongebruikt!$AH$4:$AU$4-Gebruikt!$AH$8:$AU$8))/14 -> 0.72142857 | K4: =1-SUMPRODUCT(ABS(Ongebruikt!$AH$4:$AU$4-Gebruikt!$AH$9:$AU$9))/14 -> 0.65714286 | L4: =1-SUMPRODUCT(ABS(Ongebruikt!$AH$4:$AU$4-Gebruikt!$AH$10:$AU$10))/14 -> 0.65714286 | M4: =1-SUMPRODUCT(ABS(Ongebruikt!$AH$4:$AU$4-Gebruikt!$AH$11:$AU$11))/14 -> 0.65714286 | N4: =1-SUMPRODUCT(ABS(Ongebruikt!$AH$4:$AU$4-Gebruikt!$AH$12:$AU$12))/14 -> 0.62142857 | O4: =1-SUMPRODUCT(ABS(Ongebruikt!$AH$4:$AU$4-Gebruikt!$AH$13:$AU$13))/14 -> 0.77142857 | P4: =1-SUMPRODUCT(ABS(Ongebruikt!$AH$4:$AU$4-Gebruikt!$AH$14:$AU$14))/14 -> 0.58571429 | Q4: =1-SUMPRODUCT(ABS(Ongebruikt!$AH$4:$AU$4-Gebruikt!$AH$15:$AU$15))/14 -> 0.65714286 | R4: =1-SUMPRODUCT(ABS(Ongebruikt!$AH$4:$AU$4-Gebruikt!$AH$16:$AU$16))/14 -> 0.65714286 | S4: =1-SUMPRODUCT(ABS(Ongebruikt!$AH$4:$AU$4-Gebruikt!$AH$17:$AU$17))/14 -> 0.57857143 | T4: =1-SUMPRODUCT(ABS(Ongebruikt!$AH$4:$AU$4-Gebruikt!$AH$18:$AU$18))/14 -> 0.91428571 | U4: =1-SUMPRODUCT(ABS(Ongebruikt!$AH$4:$AU$4-Gebruikt!$AH$19:$AU$19))/14 -> 0.97142857 | V4: =1-SUMPRODUCT(ABS(Ongebruikt!$AH$4:$AU$4-Gebruikt!$AH$20:$AU$20))/14 -> 0.65714286 | W4: =1-SUMPRODUCT(ABS(Ongebruikt!$AH$4:$AU$4-Gebruikt!$AH$21:$AU$21))/14 -> 0.68571429 | X4: =1-SUMPRODUCT(ABS(Ongebruikt!$AH$4:$AU$4-Gebruikt!$AH$22:$AU$22))/14 -> 0.70714286 | Y4: =1-SUMPRODUCT(ABS(Ongebruikt!$AH$4:$AU$4-Gebruikt!$AH$23:$AU$23))/14 -> 0.72142857 | Z4: =1-SUMPRODUCT(ABS(Ongebruikt!$AH$4:$AU$4-Gebruikt!$AH$24:$AU$24))/14 -> 0.72142857 | AA4: =1-SUMPRODUCT(ABS(Ongebruikt!$AH$4:$AU$4-Gebruikt!$AH$25:$AU$25))/14 -> 0.91428571 | AB4: =1-SUMPRODUCT(ABS(Ongebruikt!$AH$4:$AU$4-Gebruikt!$AH$26:$AU$26))/14 -> 0.77142857 | AC4: =1-SUMPRODUCT(ABS(Ongebruikt!$AH$4:$AU$4-Gebruikt!$AH$27:$AU$27))/14 -> 0.84285714 | AD4: =1-SUMPRODUCT(ABS(Ongebruikt!$AH$4:$AU$4-Gebruikt!$AH$28:$AU$28))/14 -> 0.77142857 | AE4: =1-SUMPRODUCT(ABS(Ongebruikt!$AH$4:$AU$4-Gebruikt!$AH$29:$AU$29))/14 -> 0.57857143 | AF4: =1-SUMPRODUCT(ABS(Ongebruikt!$AH$4:$AU$4-Gebruikt!$AH$30:$AU$30))/14 -> 0.49285714 | AG4: =1-SUMPRODUCT(ABS(Ongebruikt!$AH$4:$AU$4-Gebruikt!$AH$31:$AU$31))/14 -> 0.98571429 | AH4: =1-SUMPRODUCT(ABS(Ongebruikt!$AH$4:$AU$4-Gebruikt!$AH$32:$AU$32))/14 -> 0.91428571 | AI4: =1-SUMPRODUCT(ABS(Ongebruikt!$AH$4:$AU$4-Gebruikt!$AH$33:$AU$33))/14 -> 0.57857143 | AJ4: =1-SUMPRODUCT(ABS(Ongebruikt!$AH$4:$AU$4-Gebruikt!$AH$34:$AU$34))/14 -> 0.68571429 | AK4: =1-SUMPRODUCT(ABS(Ongebruikt!$AH$4:$AU$4-Gebruikt!$AH$35:$AU$35))/14 -> 0.72142857 | AL4: =1-SUMPRODUCT(ABS(Ongebruikt!$AH$4:$AU$4-Gebruikt!$AH$36:$AU$36))/14 -> 0.98571429 | AM4: =1-SUMPRODUCT(ABS(Ongebruikt!$AH$4:$AU$4-Gebruikt!$AH$37:$AU$37))/14 -> 0.84285714 | AN4: =1-SUMPRODUCT(ABS(Ongebruikt!$AH$4:$AU$4-Gebruikt!$AH$38:$AU$38))/14 -> 0.57857143 | AO4: =1-SUMPRODUCT(ABS(Ongebruikt!$AH$4:$AU$4-Gebruikt!$AH$39:$AU$39))/14 -> 0.82857143 | AP4: =1-SUMPRODUCT(ABS(Ongebruikt!$AH$4:$AU$4-Gebruikt!$AH$40:$AU$40))/14 -> 0.65714286 | AQ4: =1-SUMPRODUCT(ABS(Ongebruikt!$AH$4:$AU$4-Gebruikt!$AH$41:$AU$41))/14 -> 0.56428571 | AR4: =1-SUMPRODUCT(ABS(Ongebruikt!$AH$4:$AU$4-Gebruikt!$AH$42:$AU$42))/14 -> 0.65714286 | AS4: =1-SUMPRODUCT(ABS(Ongebruikt!$AH$4:$AU$4-Gebruikt!$AH$43:$AU$43))/14 -> 0.57857143 | AT4: =1-SUMPRODUCT(ABS(Ongebruikt!$AH$4:$AU$4-Gebruikt!$AH$44:$AU$44))/14 -> 0.72142857 | AU4: =1-SUMPRODUCT(ABS(Ongebruikt!$AH$4:$AU$4-Gebruikt!$AH$45:$AU$45))/14 -> 0.57857143 | AV4: =1-SUMPRODUCT(ABS(Ongebruikt!$AH$4:$AU$4-Gebruikt!$AH$46:$AU$46))/14 -> 0.85 | AW4: =1-SUMPRODUCT(ABS(Ongebruikt!$AH$4:$AU$4-Gebruikt!$AH$47:$AU$47))/14 -> 0.65714286 | AX4: =1-SUMPRODUCT(ABS(Ongebruikt!$AH$4:$AU$4-Gebruikt!$AH$48:$AU$48))/14 -> 0.57857143
A5: =Ongebruikt!A5 -> U02 | B5: =Ongebruikt!B5 -> safegcd jump matrices (62-step batches from low bits) | C5: =1-D5 -> 0.014285714 | D5: =MAX(F5:AX5) -> 0.98571429 | E5: =INDEX(Gebruikt!$B$4:$B$48,MATCH(D5,F5:AX5,0)) -> Multi-bit shift per GCD step (jump-GCD K=2 to 8-way barrel e<=7) | F5: =1-SUMPRODUCT(ABS(Ongebruikt!$AH$5:$AU$5-Gebruikt!$AH$4:$AU$4))/14 -> 0.91428571 | G5: =1-SUMPRODUCT(ABS(Ongebruikt!$AH$5:$AU$5-Gebruikt!$AH$5:$AU$5))/14 -> 0.68571429 | H5: =1-SUMPRODUCT(ABS(Ongebruikt!$AH$5:$AU$5-Gebruikt!$AH$6:$AU$6))/14 -> 0.68571429 | I5: =1-SUMPRODUCT(ABS(Ongebruikt!$AH$5:$AU$5-Gebruikt!$AH$7:$AU$7))/14 -> 0.61428571 | J5: =1-SUMPRODUCT(ABS(Ongebruikt!$AH$5:$AU$5-Gebruikt!$AH$8:$AU$8))/14 -> 0.72142857 | K5: =1-SUMPRODUCT(ABS(Ongebruikt!$AH$5:$AU$5-Gebruikt!$AH$9:$AU$9))/14 -> 0.65714286 | L5: =1-SUMPRODUCT(ABS(Ongebruikt!$AH$5:$AU$5-Gebruikt!$AH$10:$AU$10))/14 -> 0.65714286 | M5: =1-SUMPRODUCT(ABS(Ongebruikt!$AH$5:$AU$5-Gebruikt!$AH$11:$AU$11))/14 -> 0.65714286 | N5: =1-SUMPRODUCT(ABS(Ongebruikt!$AH$5:$AU$5-Gebruikt!$AH$12:$AU$12))/14 -> 0.62142857 | O5: =1-SUMPRODUCT(ABS(Ongebruikt!$AH$5:$AU$5-Gebruikt!$AH$13:$AU$13))/14 -> 0.74285714 | P5: =1-SUMPRODUCT(ABS(Ongebruikt!$AH$5:$AU$5-Gebruikt!$AH$14:$AU$14))/14 -> 0.58571429 | Q5: =1-SUMPRODUCT(ABS(Ongebruikt!$AH$5:$AU$5-Gebruikt!$AH$15:$AU$15))/14 -> 0.65714286 | R5: =1-SUMPRODUCT(ABS(Ongebruikt!$AH$5:$AU$5-Gebruikt!$AH$16:$AU$16))/14 -> 0.65714286 | S5: =1-SUMPRODUCT(ABS(Ongebruikt!$AH$5:$AU$5-Gebruikt!$AH$17:$AU$17))/14 -> 0.55 | T5: =1-SUMPRODUCT(ABS(Ongebruikt!$AH$5:$AU$5-Gebruikt!$AH$18:$AU$18))/14 -> 0.91428571 | U5: =1-SUMPRODUCT(ABS(Ongebruikt!$AH$5:$AU$5-Gebruikt!$AH$19:$AU$19))/14 -> 0.97142857 | V5: =1-SUMPRODUCT(ABS(Ongebruikt!$AH$5:$AU$5-Gebruikt!$AH$20:$AU$20))/14 -> 0.65714286 | W5: =1-SUMPRODUCT(ABS(Ongebruikt!$AH$5:$AU$5-Gebruikt!$AH$21:$AU$21))/14 -> 0.68571429 | X5: =1-SUMPRODUCT(ABS(Ongebruikt!$AH$5:$AU$5-Gebruikt!$AH$22:$AU$22))/14 -> 0.67857143 | Y5: =1-SUMPRODUCT(ABS(Ongebruikt!$AH$5:$AU$5-Gebruikt!$AH$23:$AU$23))/14 -> 0.72142857 | Z5: =1-SUMPRODUCT(ABS(Ongebruikt!$AH$5:$AU$5-Gebruikt!$AH$24:$AU$24))/14 -> 0.72142857 | AA5: =1-SUMPRODUCT(ABS(Ongebruikt!$AH$5:$AU$5-Gebruikt!$AH$25:$AU$25))/14 -> 0.88571429 | AB5: =1-SUMPRODUCT(ABS(Ongebruikt!$AH$5:$AU$5-Gebruikt!$AH$26:$AU$26))/14 -> 0.74285714 | AC5: =1-SUMPRODUCT(ABS(Ongebruikt!$AH$5:$AU$5-Gebruikt!$AH$27:$AU$27))/14 -> 0.81428571 | AD5: =1-SUMPRODUCT(ABS(Ongebruikt!$AH$5:$AU$5-Gebruikt!$AH$28:$AU$28))/14 -> 0.74285714 | AE5: =1-SUMPRODUCT(ABS(Ongebruikt!$AH$5:$AU$5-Gebruikt!$AH$29:$AU$29))/14 -> 0.57857143 | AF5: =1-SUMPRODUCT(ABS(Ongebruikt!$AH$5:$AU$5-Gebruikt!$AH$30:$AU$30))/14 -> 0.46428571 | AG5: =1-SUMPRODUCT(ABS(Ongebruikt!$AH$5:$AU$5-Gebruikt!$AH$31:$AU$31))/14 -> 0.98571429 | AH5: =1-SUMPRODUCT(ABS(Ongebruikt!$AH$5:$AU$5-Gebruikt!$AH$32:$AU$32))/14 -> 0.91428571 | AI5: =1-SUMPRODUCT(ABS(Ongebruikt!$AH$5:$AU$5-Gebruikt!$AH$33:$AU$33))/14 -> 0.57857143 | AJ5: =1-SUMPRODUCT(ABS(Ongebruikt!$AH$5:$AU$5-Gebruikt!$AH$34:$AU$34))/14 -> 0.68571429 | AK5: =1-SUMPRODUCT(ABS(Ongebruikt!$AH$5:$AU$5-Gebruikt!$AH$35:$AU$35))/14 -> 0.72142857 | AL5: =1-SUMPRODUCT(ABS(Ongebruikt!$AH$5:$AU$5-Gebruikt!$AH$36:$AU$36))/14 -> 0.98571429 | AM5: =1-SUMPRODUCT(ABS(Ongebruikt!$AH$5:$AU$5-Gebruikt!$AH$37:$AU$37))/14 -> 0.84285714 | AN5: =1-SUMPRODUCT(ABS(Ongebruikt!$AH$5:$AU$5-Gebruikt!$AH$38:$AU$38))/14 -> 0.57857143 | AO5: =1-SUMPRODUCT(ABS(Ongebruikt!$AH$5:$AU$5-Gebruikt!$AH$39:$AU$39))/14 -> 0.82857143 | AP5: =1-SUMPRODUCT(ABS(Ongebruikt!$AH$5:$AU$5-Gebruikt!$AH$40:$AU$40))/14 -> 0.65714286 | AQ5: =1-SUMPRODUCT(ABS(Ongebruikt!$AH$5:$AU$5-Gebruikt!$AH$41:$AU$41))/14 -> 0.53571429 | AR5: =1-SUMPRODUCT(ABS(Ongebruikt!$AH$5:$AU$5-Gebruikt!$AH$42:$AU$42))/14 -> 0.65714286 | AS5: =1-SUMPRODUCT(ABS(Ongebruikt!$AH$5:$AU$5-Gebruikt!$AH$43:$AU$43))/14 -> 0.55 | AT5: =1-SUMPRODUCT(ABS(Ongebruikt!$AH$5:$AU$5-Gebruikt!$AH$44:$AU$44))/14 -> 0.69285714 | AU5: =1-SUMPRODUCT(ABS(Ongebruikt!$AH$5:$AU$5-Gebruikt!$AH$45:$AU$45))/14 -> 0.55 | AV5: =1-SUMPRODUCT(ABS(Ongebruikt!$AH$5:$AU$5-Gebruikt!$AH$46:$AU$46))/14 -> 0.82142857 | AW5: =1-SUMPRODUCT(ABS(Ongebruikt!$AH$5:$AU$5-Gebruikt!$AH$47:$AU$47))/14 -> 0.65714286 | AX5: =1-SUMPRODUCT(ABS(Ongebruikt!$AH$5:$AU$5-Gebruikt!$AH$48:$AU$48))/14 -> 0.55
A6: =Ongebruikt!A6 -> U03 | B6: =Ongebruikt!B6 -> k-ary GCD with small-multiplier table (Sorenson/Weber) | C6: =1-D6 -> 0.1 | D6: =MAX(F6:AX6) -> 0.9 | E6: =INDEX(Gebruikt!$B$4:$B$48,MATCH(D6,F6:AX6,0)) -> Multi-bit shift per GCD step (jump-GCD K=2 to 8-way barrel e<=7) | F6: =1-SUMPRODUCT(ABS(Ongebruikt!$AH$6:$AU$6-Gebruikt!$AH$4:$AU$4))/14 -> 0.82857143 | G6: =1-SUMPRODUCT(ABS(Ongebruikt!$AH$6:$AU$6-Gebruikt!$AH$5:$AU$5))/14 -> 0.6 | H6: =1-SUMPRODUCT(ABS(Ongebruikt!$AH$6:$AU$6-Gebruikt!$AH$6:$AU$6))/14 -> 0.6 | I6: =1-SUMPRODUCT(ABS(Ongebruikt!$AH$6:$AU$6-Gebruikt!$AH$7:$AU$7))/14 -> 0.52857143 | J6: =1-SUMPRODUCT(ABS(Ongebruikt!$AH$6:$AU$6-Gebruikt!$AH$8:$AU$8))/14 -> 0.63571429 | K6: =1-SUMPRODUCT(ABS(Ongebruikt!$AH$6:$AU$6-Gebruikt!$AH$9:$AU$9))/14 -> 0.57142857 | L6: =1-SUMPRODUCT(ABS(Ongebruikt!$AH$6:$AU$6-Gebruikt!$AH$10:$AU$10))/14 -> 0.57142857 | M6: =1-SUMPRODUCT(ABS(Ongebruikt!$AH$6:$AU$6-Gebruikt!$AH$11:$AU$11))/14 -> 0.57142857 | N6: =1-SUMPRODUCT(ABS(Ongebruikt!$AH$6:$AU$6-Gebruikt!$AH$12:$AU$12))/14 -> 0.53571429 | O6: =1-SUMPRODUCT(ABS(Ongebruikt!$AH$6:$AU$6-Gebruikt!$AH$13:$AU$13))/14 -> 0.8 | P6: =1-SUMPRODUCT(ABS(Ongebruikt!$AH$6:$AU$6-Gebruikt!$AH$14:$AU$14))/14 -> 0.5 | Q6: =1-SUMPRODUCT(ABS(Ongebruikt!$AH$6:$AU$6-Gebruikt!$AH$15:$AU$15))/14 -> 0.57142857 | R6: =1-SUMPRODUCT(ABS(Ongebruikt!$AH$6:$AU$6-Gebruikt!$AH$16:$AU$16))/14 -> 0.57142857 | S6: =1-SUMPRODUCT(ABS(Ongebruikt!$AH$6:$AU$6-Gebruikt!$AH$17:$AU$17))/14 -> 0.46428571 | T6: =1-SUMPRODUCT(ABS(Ongebruikt!$AH$6:$AU$6-Gebruikt!$AH$18:$AU$18))/14 -> 0.82857143 | U6: =1-SUMPRODUCT(ABS(Ongebruikt!$AH$6:$AU$6-Gebruikt!$AH$19:$AU$19))/14 -> 0.88571429 | V6: =1-SUMPRODUCT(ABS(Ongebruikt!$AH$6:$AU$6-Gebruikt!$AH$20:$AU$20))/14 -> 0.57142857 | W6: =1-SUMPRODUCT(ABS(Ongebruikt!$AH$6:$AU$6-Gebruikt!$AH$21:$AU$21))/14 -> 0.6 | X6: =1-SUMPRODUCT(ABS(Ongebruikt!$AH$6:$AU$6-Gebruikt!$AH$22:$AU$22))/14 -> 0.59285714 | Y6: =1-SUMPRODUCT(ABS(Ongebruikt!$AH$6:$AU$6-Gebruikt!$AH$23:$AU$23))/14 -> 0.63571429 | Z6: =1-SUMPRODUCT(ABS(Ongebruikt!$AH$6:$AU$6-Gebruikt!$AH$24:$AU$24))/14 -> 0.63571429 | AA6: =1-SUMPRODUCT(ABS(Ongebruikt!$AH$6:$AU$6-Gebruikt!$AH$25:$AU$25))/14 -> 0.8 | AB6: =1-SUMPRODUCT(ABS(Ongebruikt!$AH$6:$AU$6-Gebruikt!$AH$26:$AU$26))/14 -> 0.65714286 | AC6: =1-SUMPRODUCT(ABS(Ongebruikt!$AH$6:$AU$6-Gebruikt!$AH$27:$AU$27))/14 -> 0.87142857 | AD6: =1-SUMPRODUCT(ABS(Ongebruikt!$AH$6:$AU$6-Gebruikt!$AH$28:$AU$28))/14 -> 0.8 | AE6: =1-SUMPRODUCT(ABS(Ongebruikt!$AH$6:$AU$6-Gebruikt!$AH$29:$AU$29))/14 -> 0.49285714 | AF6: =1-SUMPRODUCT(ABS(Ongebruikt!$AH$6:$AU$6-Gebruikt!$AH$30:$AU$30))/14 -> 0.52142857 | AG6: =1-SUMPRODUCT(ABS(Ongebruikt!$AH$6:$AU$6-Gebruikt!$AH$31:$AU$31))/14 -> 0.9 | AH6: =1-SUMPRODUCT(ABS(Ongebruikt!$AH$6:$AU$6-Gebruikt!$AH$32:$AU$32))/14 -> 0.82857143 | AI6: =1-SUMPRODUCT(ABS(Ongebruikt!$AH$6:$AU$6-Gebruikt!$AH$33:$AU$33))/14 -> 0.49285714 | AJ6: =1-SUMPRODUCT(ABS(Ongebruikt!$AH$6:$AU$6-Gebruikt!$AH$34:$AU$34))/14 -> 0.6 | AK6: =1-SUMPRODUCT(ABS(Ongebruikt!$AH$6:$AU$6-Gebruikt!$AH$35:$AU$35))/14 -> 0.63571429 | AL6: =1-SUMPRODUCT(ABS(Ongebruikt!$AH$6:$AU$6-Gebruikt!$AH$36:$AU$36))/14 -> 0.9 | AM6: =1-SUMPRODUCT(ABS(Ongebruikt!$AH$6:$AU$6-Gebruikt!$AH$37:$AU$37))/14 -> 0.75714286 | AN6: =1-SUMPRODUCT(ABS(Ongebruikt!$AH$6:$AU$6-Gebruikt!$AH$38:$AU$38))/14 -> 0.49285714 | AO6: =1-SUMPRODUCT(ABS(Ongebruikt!$AH$6:$AU$6-Gebruikt!$AH$39:$AU$39))/14 -> 0.74285714 | AP6: =1-SUMPRODUCT(ABS(Ongebruikt!$AH$6:$AU$6-Gebruikt!$AH$40:$AU$40))/14 -> 0.57142857 | AQ6: =1-SUMPRODUCT(ABS(Ongebruikt!$AH$6:$AU$6-Gebruikt!$AH$41:$AU$41))/14 -> 0.59285714 | AR6: =1-SUMPRODUCT(ABS(Ongebruikt!$AH$6:$AU$6-Gebruikt!$AH$42:$AU$42))/14 -> 0.57142857 | AS6: =1-SUMPRODUCT(ABS(Ongebruikt!$AH$6:$AU$6-Gebruikt!$AH$43:$AU$43))/14 -> 0.46428571 | AT6: =1-SUMPRODUCT(ABS(Ongebruikt!$AH$6:$AU$6-Gebruikt!$AH$44:$AU$44))/14 -> 0.60714286 | AU6: =1-SUMPRODUCT(ABS(Ongebruikt!$AH$6:$AU$6-Gebruikt!$AH$45:$AU$45))/14 -> 0.46428571 | AV6: =1-SUMPRODUCT(ABS(Ongebruikt!$AH$6:$AU$6-Gebruikt!$AH$46:$AU$46))/14 -> 0.73571429 | AW6: =1-SUMPRODUCT(ABS(Ongebruikt!$AH$6:$AU$6-Gebruikt!$AH$47:$AU$47))/14 -> 0.57142857 | AX6: =1-SUMPRODUCT(ABS(Ongebruikt!$AH$6:$AU$6-Gebruikt!$AH$48:$AU$48))/14 -> 0.46428571
A7: =Ongebruikt!A7 -> U04 | B7: =Ongebruikt!B7 -> Lehmer / half-GCD (Schonhage, Stehle-Zimmermann) | C7: =1-D7 -> 0.057142857 | D7: =MAX(F7:AX7) -> 0.94285714 | E7: =INDEX(Gebruikt!$B$4:$B$48,MATCH(D7,F7:AX7,0)) -> Multi-bit shift per GCD step (jump-GCD K=2 to 8-way barrel e<=7) | F7: =1-SUMPRODUCT(ABS(Ongebruikt!$AH$7:$AU$7-Gebruikt!$AH$4:$AU$4))/14 -> 0.87142857 | G7: =1-SUMPRODUCT(ABS(Ongebruikt!$AH$7:$AU$7-Gebruikt!$AH$5:$AU$5))/14 -> 0.64285714 | H7: =1-SUMPRODUCT(ABS(Ongebruikt!$AH$7:$AU$7-Gebruikt!$AH$6:$AU$6))/14 -> 0.64285714 | I7: =1-SUMPRODUCT(ABS(Ongebruikt!$AH$7:$AU$7-Gebruikt!$AH$7:$AU$7))/14 -> 0.57142857 | J7: =1-SUMPRODUCT(ABS(Ongebruikt!$AH$7:$AU$7-Gebruikt!$AH$8:$AU$8))/14 -> 0.67857143 | K7: =1-SUMPRODUCT(ABS(Ongebruikt!$AH$7:$AU$7-Gebruikt!$AH$9:$AU$9))/14 -> 0.61428571 | L7: =1-SUMPRODUCT(ABS(Ongebruikt!$AH$7:$AU$7-Gebruikt!$AH$10:$AU$10))/14 -> 0.61428571 | M7: =1-SUMPRODUCT(ABS(Ongebruikt!$AH$7:$AU$7-Gebruikt!$AH$11:$AU$11))/14 -> 0.61428571 | N7: =1-SUMPRODUCT(ABS(Ongebruikt!$AH$7:$AU$7-Gebruikt!$AH$12:$AU$12))/14 -> 0.57857143 | O7: =1-SUMPRODUCT(ABS(Ongebruikt!$AH$7:$AU$7-Gebruikt!$AH$13:$AU$13))/14 -> 0.7 | P7: =1-SUMPRODUCT(ABS(Ongebruikt!$AH$7:$AU$7-Gebruikt!$AH$14:$AU$14))/14 -> 0.54285714 | Q7: =1-SUMPRODUCT(ABS(Ongebruikt!$AH$7:$AU$7-Gebruikt!$AH$15:$AU$15))/14 -> 0.61428571 | R7: =1-SUMPRODUCT(ABS(Ongebruikt!$AH$7:$AU$7-Gebruikt!$AH$16:$AU$16))/14 -> 0.61428571 | S7: =1-SUMPRODUCT(ABS(Ongebruikt!$AH$7:$AU$7-Gebruikt!$AH$17:$AU$17))/14 -> 0.50714286 | T7: =1-SUMPRODUCT(ABS(Ongebruikt!$AH$7:$AU$7-Gebruikt!$AH$18:$AU$18))/14 -> 0.87142857 | U7: =1-SUMPRODUCT(ABS(Ongebruikt!$AH$7:$AU$7-Gebruikt!$AH$19:$AU$19))/14 -> 0.92857143 | V7: =1-SUMPRODUCT(ABS(Ongebruikt!$AH$7:$AU$7-Gebruikt!$AH$20:$AU$20))/14 -> 0.61428571 | W7: =1-SUMPRODUCT(ABS(Ongebruikt!$AH$7:$AU$7-Gebruikt!$AH$21:$AU$21))/14 -> 0.64285714 | X7: =1-SUMPRODUCT(ABS(Ongebruikt!$AH$7:$AU$7-Gebruikt!$AH$22:$AU$22))/14 -> 0.63571429 | Y7: =1-SUMPRODUCT(ABS(Ongebruikt!$AH$7:$AU$7-Gebruikt!$AH$23:$AU$23))/14 -> 0.67857143 | Z7: =1-SUMPRODUCT(ABS(Ongebruikt!$AH$7:$AU$7-Gebruikt!$AH$24:$AU$24))/14 -> 0.67857143 | AA7: =1-SUMPRODUCT(ABS(Ongebruikt!$AH$7:$AU$7-Gebruikt!$AH$25:$AU$25))/14 -> 0.84285714 | AB7: =1-SUMPRODUCT(ABS(Ongebruikt!$AH$7:$AU$7-Gebruikt!$AH$26:$AU$26))/14 -> 0.7 | AC7: =1-SUMPRODUCT(ABS(Ongebruikt!$AH$7:$AU$7-Gebruikt!$AH$27:$AU$27))/14 -> 0.77142857 | AD7: =1-SUMPRODUCT(ABS(Ongebruikt!$AH$7:$AU$7-Gebruikt!$AH$28:$AU$28))/14 -> 0.7 | AE7: =1-SUMPRODUCT(ABS(Ongebruikt!$AH$7:$AU$7-Gebruikt!$AH$29:$AU$29))/14 -> 0.53571429 | AF7: =1-SUMPRODUCT(ABS(Ongebruikt!$AH$7:$AU$7-Gebruikt!$AH$30:$AU$30))/14 -> 0.42142857 | AG7: =1-SUMPRODUCT(ABS(Ongebruikt!$AH$7:$AU$7-Gebruikt!$AH$31:$AU$31))/14 -> 0.94285714 | AH7: =1-SUMPRODUCT(ABS(Ongebruikt!$AH$7:$AU$7-Gebruikt!$AH$32:$AU$32))/14 -> 0.87142857 | AI7: =1-SUMPRODUCT(ABS(Ongebruikt!$AH$7:$AU$7-Gebruikt!$AH$33:$AU$33))/14 -> 0.53571429 | AJ7: =1-SUMPRODUCT(ABS(Ongebruikt!$AH$7:$AU$7-Gebruikt!$AH$34:$AU$34))/14 -> 0.64285714 | AK7: =1-SUMPRODUCT(ABS(Ongebruikt!$AH$7:$AU$7-Gebruikt!$AH$35:$AU$35))/14 -> 0.67857143 | AL7: =1-SUMPRODUCT(ABS(Ongebruikt!$AH$7:$AU$7-Gebruikt!$AH$36:$AU$36))/14 -> 0.94285714 | AM7: =1-SUMPRODUCT(ABS(Ongebruikt!$AH$7:$AU$7-Gebruikt!$AH$37:$AU$37))/14 -> 0.8 | AN7: =1-SUMPRODUCT(ABS(Ongebruikt!$AH$7:$AU$7-Gebruikt!$AH$38:$AU$38))/14 -> 0.53571429 | AO7: =1-SUMPRODUCT(ABS(Ongebruikt!$AH$7:$AU$7-Gebruikt!$AH$39:$AU$39))/14 -> 0.78571429 | AP7: =1-SUMPRODUCT(ABS(Ongebruikt!$AH$7:$AU$7-Gebruikt!$AH$40:$AU$40))/14 -> 0.61428571 | AQ7: =1-SUMPRODUCT(ABS(Ongebruikt!$AH$7:$AU$7-Gebruikt!$AH$41:$AU$41))/14 -> 0.49285714 | AR7: =1-SUMPRODUCT(ABS(Ongebruikt!$AH$7:$AU$7-Gebruikt!$AH$42:$AU$42))/14 -> 0.61428571 | AS7: =1-SUMPRODUCT(ABS(Ongebruikt!$AH$7:$AU$7-Gebruikt!$AH$43:$AU$43))/14 -> 0.50714286 | AT7: =1-SUMPRODUCT(ABS(Ongebruikt!$AH$7:$AU$7-Gebruikt!$AH$44:$AU$44))/14 -> 0.65 | AU7: =1-SUMPRODUCT(ABS(Ongebruikt!$AH$7:$AU$7-Gebruikt!$AH$45:$AU$45))/14 -> 0.50714286 | AV7: =1-SUMPRODUCT(ABS(Ongebruikt!$AH$7:$AU$7-Gebruikt!$AH$46:$AU$46))/14 -> 0.77857143 | AW7: =1-SUMPRODUCT(ABS(Ongebruikt!$AH$7:$AU$7-Gebruikt!$AH$47:$AU$47))/14 -> 0.61428571 | AX7: =1-SUMPRODUCT(ABS(Ongebruikt!$AH$7:$AU$7-Gebruikt!$AH$48:$AU$48))/14 -> 0.50714286
A8: =Ongebruikt!A8 -> U05 | B8: =Ongebruikt!B8 -> Extended Euclid with quotients + register sharing (Proos-Zalka) | C8: =1-D8 -> 0.057142857 | D8: =MAX(F8:AX8) -> 0.94285714 | E8: =INDEX(Gebruikt!$B$4:$B$48,MATCH(D8,F8:AX8,0)) -> Multi-bit shift per GCD step (jump-GCD K=2 to 8-way barrel e<=7) | F8: =1-SUMPRODUCT(ABS(Ongebruikt!$AH$8:$AU$8-Gebruikt!$AH$4:$AU$4))/14 -> 0.87142857 | G8: =1-SUMPRODUCT(ABS(Ongebruikt!$AH$8:$AU$8-Gebruikt!$AH$5:$AU$5))/14 -> 0.64285714 | H8: =1-SUMPRODUCT(ABS(Ongebruikt!$AH$8:$AU$8-Gebruikt!$AH$6:$AU$6))/14 -> 0.64285714 | I8: =1-SUMPRODUCT(ABS(Ongebruikt!$AH$8:$AU$8-Gebruikt!$AH$7:$AU$7))/14 -> 0.57142857 | J8: =1-SUMPRODUCT(ABS(Ongebruikt!$AH$8:$AU$8-Gebruikt!$AH$8:$AU$8))/14 -> 0.67857143 | K8: =1-SUMPRODUCT(ABS(Ongebruikt!$AH$8:$AU$8-Gebruikt!$AH$9:$AU$9))/14 -> 0.61428571 | L8: =1-SUMPRODUCT(ABS(Ongebruikt!$AH$8:$AU$8-Gebruikt!$AH$10:$AU$10))/14 -> 0.61428571 | M8: =1-SUMPRODUCT(ABS(Ongebruikt!$AH$8:$AU$8-Gebruikt!$AH$11:$AU$11))/14 -> 0.61428571 | N8: =1-SUMPRODUCT(ABS(Ongebruikt!$AH$8:$AU$8-Gebruikt!$AH$12:$AU$12))/14 -> 0.57857143 | O8: =1-SUMPRODUCT(ABS(Ongebruikt!$AH$8:$AU$8-Gebruikt!$AH$13:$AU$13))/14 -> 0.7 | P8: =1-SUMPRODUCT(ABS(Ongebruikt!$AH$8:$AU$8-Gebruikt!$AH$14:$AU$14))/14 -> 0.54285714 | Q8: =1-SUMPRODUCT(ABS(Ongebruikt!$AH$8:$AU$8-Gebruikt!$AH$15:$AU$15))/14 -> 0.61428571 | R8: =1-SUMPRODUCT(ABS(Ongebruikt!$AH$8:$AU$8-Gebruikt!$AH$16:$AU$16))/14 -> 0.61428571 | S8: =1-SUMPRODUCT(ABS(Ongebruikt!$AH$8:$AU$8-Gebruikt!$AH$17:$AU$17))/14 -> 0.50714286 | T8: =1-SUMPRODUCT(ABS(Ongebruikt!$AH$8:$AU$8-Gebruikt!$AH$18:$AU$18))/14 -> 0.87142857 | U8: =1-SUMPRODUCT(ABS(Ongebruikt!$AH$8:$AU$8-Gebruikt!$AH$19:$AU$19))/14 -> 0.92857143 | V8: =1-SUMPRODUCT(ABS(Ongebruikt!$AH$8:$AU$8-Gebruikt!$AH$20:$AU$20))/14 -> 0.61428571 | W8: =1-SUMPRODUCT(ABS(Ongebruikt!$AH$8:$AU$8-Gebruikt!$AH$21:$AU$21))/14 -> 0.64285714 | X8: =1-SUMPRODUCT(ABS(Ongebruikt!$AH$8:$AU$8-Gebruikt!$AH$22:$AU$22))/14 -> 0.63571429 | Y8: =1-SUMPRODUCT(ABS(Ongebruikt!$AH$8:$AU$8-Gebruikt!$AH$23:$AU$23))/14 -> 0.67857143 | Z8: =1-SUMPRODUCT(ABS(Ongebruikt!$AH$8:$AU$8-Gebruikt!$AH$24:$AU$24))/14 -> 0.67857143 | AA8: =1-SUMPRODUCT(ABS(Ongebruikt!$AH$8:$AU$8-Gebruikt!$AH$25:$AU$25))/14 -> 0.84285714 | AB8: =1-SUMPRODUCT(ABS(Ongebruikt!$AH$8:$AU$8-Gebruikt!$AH$26:$AU$26))/14 -> 0.7 | AC8: =1-SUMPRODUCT(ABS(Ongebruikt!$AH$8:$AU$8-Gebruikt!$AH$27:$AU$27))/14 -> 0.77142857 | AD8: =1-SUMPRODUCT(ABS(Ongebruikt!$AH$8:$AU$8-Gebruikt!$AH$28:$AU$28))/14 -> 0.7 | AE8: =1-SUMPRODUCT(ABS(Ongebruikt!$AH$8:$AU$8-Gebruikt!$AH$29:$AU$29))/14 -> 0.53571429 | AF8: =1-SUMPRODUCT(ABS(Ongebruikt!$AH$8:$AU$8-Gebruikt!$AH$30:$AU$30))/14 -> 0.42142857 | AG8: =1-SUMPRODUCT(ABS(Ongebruikt!$AH$8:$AU$8-Gebruikt!$AH$31:$AU$31))/14 -> 0.94285714 | AH8: =1-SUMPRODUCT(ABS(Ongebruikt!$AH$8:$AU$8-Gebruikt!$AH$32:$AU$32))/14 -> 0.87142857 | AI8: =1-SUMPRODUCT(ABS(Ongebruikt!$AH$8:$AU$8-Gebruikt!$AH$33:$AU$33))/14 -> 0.53571429 | AJ8: =1-SUMPRODUCT(ABS(Ongebruikt!$AH$8:$AU$8-Gebruikt!$AH$34:$AU$34))/14 -> 0.64285714 | AK8: =1-SUMPRODUCT(ABS(Ongebruikt!$AH$8:$AU$8-Gebruikt!$AH$35:$AU$35))/14 -> 0.67857143 | AL8: =1-SUMPRODUCT(ABS(Ongebruikt!$AH$8:$AU$8-Gebruikt!$AH$36:$AU$36))/14 -> 0.94285714 | AM8: =1-SUMPRODUCT(ABS(Ongebruikt!$AH$8:$AU$8-Gebruikt!$AH$37:$AU$37))/14 -> 0.8 | AN8: =1-SUMPRODUCT(ABS(Ongebruikt!$AH$8:$AU$8-Gebruikt!$AH$38:$AU$38))/14 -> 0.53571429 | AO8: =1-SUMPRODUCT(ABS(Ongebruikt!$AH$8:$AU$8-Gebruikt!$AH$39:$AU$39))/14 -> 0.78571429 | AP8: =1-SUMPRODUCT(ABS(Ongebruikt!$AH$8:$AU$8-Gebruikt!$AH$40:$AU$40))/14 -> 0.61428571 | AQ8: =1-SUMPRODUCT(ABS(Ongebruikt!$AH$8:$AU$8-Gebruikt!$AH$41:$AU$41))/14 -> 0.49285714 | AR8: =1-SUMPRODUCT(ABS(Ongebruikt!$AH$8:$AU$8-Gebruikt!$AH$42:$AU$42))/14 -> 0.61428571 | AS8: =1-SUMPRODUCT(ABS(Ongebruikt!$AH$8:$AU$8-Gebruikt!$AH$43:$AU$43))/14 -> 0.50714286 | AT8: =1-SUMPRODUCT(ABS(Ongebruikt!$AH$8:$AU$8-Gebruikt!$AH$44:$AU$44))/14 -> 0.65 | AU8: =1-SUMPRODUCT(ABS(Ongebruikt!$AH$8:$AU$8-Gebruikt!$AH$45:$AU$45))/14 -> 0.50714286 | AV8: =1-SUMPRODUCT(ABS(Ongebruikt!$AH$8:$AU$8-Gebruikt!$AH$46:$AU$46))/14 -> 0.77857143 | AW8: =1-SUMPRODUCT(ABS(Ongebruikt!$AH$8:$AU$8-Gebruikt!$AH$47:$AU$47))/14 -> 0.61428571 | AX8: =1-SUMPRODUCT(ABS(Ongebruikt!$AH$8:$AU$8-Gebruikt!$AH$48:$AU$48))/14 -> 0.50714286
A9: =Ongebruikt!A9 -> U06 | B9: =Ongebruikt!B9 -> Kaliski Montgomery inverse with comparisons | C9: =1-D9 -> 0.028571429 | D9: =MAX(F9:AX9) -> 0.97142857 | E9: =INDEX(Gebruikt!$B$4:$B$48,MATCH(D9,F9:AX9,0)) -> Multi-bit shift per GCD step (jump-GCD K=2 to 8-way barrel e<=7) | F9: =1-SUMPRODUCT(ABS(Ongebruikt!$AH$9:$AU$9-Gebruikt!$AH$4:$AU$4))/14 -> 0.9 | G9: =1-SUMPRODUCT(ABS(Ongebruikt!$AH$9:$AU$9-Gebruikt!$AH$5:$AU$5))/14 -> 0.67142857 | H9: =1-SUMPRODUCT(ABS(Ongebruikt!$AH$9:$AU$9-Gebruikt!$AH$6:$AU$6))/14 -> 0.67142857 | I9: =1-SUMPRODUCT(ABS(Ongebruikt!$AH$9:$AU$9-Gebruikt!$AH$7:$AU$7))/14 -> 0.6 | J9: =1-SUMPRODUCT(ABS(Ongebruikt!$AH$9:$AU$9-Gebruikt!$AH$8:$AU$8))/14 -> 0.70714286 | K9: =1-SUMPRODUCT(ABS(Ongebruikt!$AH$9:$AU$9-Gebruikt!$AH$9:$AU$9))/14 -> 0.64285714 | L9: =1-SUMPRODUCT(ABS(Ongebruikt!$AH$9:$AU$9-Gebruikt!$AH$10:$AU$10))/14 -> 0.64285714 | M9: =1-SUMPRODUCT(ABS(Ongebruikt!$AH$9:$AU$9-Gebruikt!$AH$11:$AU$11))/14 -> 0.64285714 | N9: =1-SUMPRODUCT(ABS(Ongebruikt!$AH$9:$AU$9-Gebruikt!$AH$12:$AU$12))/14 -> 0.60714286 | O9: =1-SUMPRODUCT(ABS(Ongebruikt!$AH$9:$AU$9-Gebruikt!$AH$13:$AU$13))/14 -> 0.75714286 | P9: =1-SUMPRODUCT(ABS(Ongebruikt!$AH$9:$AU$9-Gebruikt!$AH$14:$AU$14))/14 -> 0.57142857 | Q9: =1-SUMPRODUCT(ABS(Ongebruikt!$AH$9:$AU$9-Gebruikt!$AH$15:$AU$15))/14 -> 0.64285714 | R9: =1-SUMPRODUCT(ABS(Ongebruikt!$AH$9:$AU$9-Gebruikt!$AH$16:$AU$16))/14 -> 0.64285714 | S9: =1-SUMPRODUCT(ABS(Ongebruikt!$AH$9:$AU$9-Gebruikt!$AH$17:$AU$17))/14 -> 0.56428571 | T9: =1-SUMPRODUCT(ABS(Ongebruikt!$AH$9:$AU$9-Gebruikt!$AH$18:$AU$18))/14 -> 0.9 | U9: =1-SUMPRODUCT(ABS(Ongebruikt!$AH$9:$AU$9-Gebruikt!$AH$19:$AU$19))/14 -> 0.95714286 | V9: =1-SUMPRODUCT(ABS(Ongebruikt!$AH$9:$AU$9-Gebruikt!$AH$20:$AU$20))/14 -> 0.64285714 | W9: =1-SUMPRODUCT(ABS(Ongebruikt!$AH$9:$AU$9-Gebruikt!$AH$21:$AU$21))/14 -> 0.67142857 | X9: =1-SUMPRODUCT(ABS(Ongebruikt!$AH$9:$AU$9-Gebruikt!$AH$22:$AU$22))/14 -> 0.72142857 | Y9: =1-SUMPRODUCT(ABS(Ongebruikt!$AH$9:$AU$9-Gebruikt!$AH$23:$AU$23))/14 -> 0.70714286 | Z9: =1-SUMPRODUCT(ABS(Ongebruikt!$AH$9:$AU$9-Gebruikt!$AH$24:$AU$24))/14 -> 0.70714286 | AA9: =1-SUMPRODUCT(ABS(Ongebruikt!$AH$9:$AU$9-Gebruikt!$AH$25:$AU$25))/14 -> 0.92857143 | AB9: =1-SUMPRODUCT(ABS(Ongebruikt!$AH$9:$AU$9-Gebruikt!$AH$26:$AU$26))/14 -> 0.78571429 | AC9: =1-SUMPRODUCT(ABS(Ongebruikt!$AH$9:$AU$9-Gebruikt!$AH$27:$AU$27))/14 -> 0.82857143 | AD9: =1-SUMPRODUCT(ABS(Ongebruikt!$AH$9:$AU$9-Gebruikt!$AH$28:$AU$28))/14 -> 0.75714286 | AE9: =1-SUMPRODUCT(ABS(Ongebruikt!$AH$9:$AU$9-Gebruikt!$AH$29:$AU$29))/14 -> 0.56428571 | AF9: =1-SUMPRODUCT(ABS(Ongebruikt!$AH$9:$AU$9-Gebruikt!$AH$30:$AU$30))/14 -> 0.47857143 | AG9: =1-SUMPRODUCT(ABS(Ongebruikt!$AH$9:$AU$9-Gebruikt!$AH$31:$AU$31))/14 -> 0.97142857 | AH9: =1-SUMPRODUCT(ABS(Ongebruikt!$AH$9:$AU$9-Gebruikt!$AH$32:$AU$32))/14 -> 0.9 | AI9: =1-SUMPRODUCT(ABS(Ongebruikt!$AH$9:$AU$9-Gebruikt!$AH$33:$AU$33))/14 -> 0.56428571 | AJ9: =1-SUMPRODUCT(ABS(Ongebruikt!$AH$9:$AU$9-Gebruikt!$AH$34:$AU$34))/14 -> 0.67142857 | AK9: =1-SUMPRODUCT(ABS(Ongebruikt!$AH$9:$AU$9-Gebruikt!$AH$35:$AU$35))/14 -> 0.70714286 | AL9: =1-SUMPRODUCT(ABS(Ongebruikt!$AH$9:$AU$9-Gebruikt!$AH$36:$AU$36))/14 -> 0.97142857 | AM9: =1-SUMPRODUCT(ABS(Ongebruikt!$AH$9:$AU$9-Gebruikt!$AH$37:$AU$37))/14 -> 0.82857143 | AN9: =1-SUMPRODUCT(ABS(Ongebruikt!$AH$9:$AU$9-Gebruikt!$AH$38:$AU$38))/14 -> 0.56428571 | AO9: =1-SUMPRODUCT(ABS(Ongebruikt!$AH$9:$AU$9-Gebruikt!$AH$39:$AU$39))/14 -> 0.81428571 | AP9: =1-SUMPRODUCT(ABS(Ongebruikt!$AH$9:$AU$9-Gebruikt!$AH$40:$AU$40))/14 -> 0.64285714 | AQ9: =1-SUMPRODUCT(ABS(Ongebruikt!$AH$9:$AU$9-Gebruikt!$AH$41:$AU$41))/14 -> 0.55 | AR9: =1-SUMPRODUCT(ABS(Ongebruikt!$AH$9:$AU$9-Gebruikt!$AH$42:$AU$42))/14 -> 0.64285714 | AS9: =1-SUMPRODUCT(ABS(Ongebruikt!$AH$9:$AU$9-Gebruikt!$AH$43:$AU$43))/14 -> 0.56428571 | AT9: =1-SUMPRODUCT(ABS(Ongebruikt!$AH$9:$AU$9-Gebruikt!$AH$44:$AU$44))/14 -> 0.70714286 | AU9: =1-SUMPRODUCT(ABS(Ongebruikt!$AH$9:$AU$9-Gebruikt!$AH$45:$AU$45))/14 -> 0.56428571 | AV9: =1-SUMPRODUCT(ABS(Ongebruikt!$AH$9:$AU$9-Gebruikt!$AH$46:$AU$46))/14 -> 0.86428571 | AW9: =1-SUMPRODUCT(ABS(Ongebruikt!$AH$9:$AU$9-Gebruikt!$AH$47:$AU$47))/14 -> 0.64285714 | AX9: =1-SUMPRODUCT(ABS(Ongebruikt!$AH$9:$AU$9-Gebruikt!$AH$48:$AU$48))/14 -> 0.56428571
A10: =Ongebruikt!A10 -> U07 | B10: =Ongebruikt!B10 -> Fermat inversion a^(p-2) via addition chain | C10: =1-D10 -> 0.042857143 | D10: =MAX(F10:AX10) -> 0.95714286 | E10: =INDEX(Gebruikt!$B$4:$B$48,MATCH(D10,F10:AX10,0)) -> Karatsuba squaring (recursive, in place) | F10: =1-SUMPRODUCT(ABS(Ongebruikt!$AH$10:$AU$10-Gebruikt!$AH$4:$AU$4))/14 -> 0.78571429 | G10: =1-SUMPRODUCT(ABS(Ongebruikt!$AH$10:$AU$10-Gebruikt!$AH$5:$AU$5))/14 -> 0.7 | H10: =1-SUMPRODUCT(ABS(Ongebruikt!$AH$10:$AU$10-Gebruikt!$AH$6:$AU$6))/14 -> 0.7 | I10: =1-SUMPRODUCT(ABS(Ongebruikt!$AH$10:$AU$10-Gebruikt!$AH$7:$AU$7))/14 -> 0.62857143 | J10: =1-SUMPRODUCT(ABS(Ongebruikt!$AH$10:$AU$10-Gebruikt!$AH$8:$AU$8))/14 -> 0.73571429 | K10: =1-SUMPRODUCT(ABS(Ongebruikt!$AH$10:$AU$10-Gebruikt!$AH$9:$AU$9))/14 -> 0.55714286 | L10: =1-SUMPRODUCT(ABS(Ongebruikt!$AH$10:$AU$10-Gebruikt!$AH$10:$AU$10))/14 -> 0.55714286 | M10: =1-SUMPRODUCT(ABS(Ongebruikt!$AH$10:$AU$10-Gebruikt!$AH$11:$AU$11))/14 -> 0.55714286 | N10: =1-SUMPRODUCT(ABS(Ongebruikt!$AH$10:$AU$10-Gebruikt!$AH$12:$AU$12))/14 -> 0.52142857 | O10: =1-SUMPRODUCT(ABS(Ongebruikt!$AH$10:$AU$10-Gebruikt!$AH$13:$AU$13))/14 -> 0.78571429 | P10: =1-SUMPRODUCT(ABS(Ongebruikt!$AH$10:$AU$10-Gebruikt!$AH$14:$AU$14))/14 -> 0.62857143 | Q10: =1-SUMPRODUCT(ABS(Ongebruikt!$AH$10:$AU$10-Gebruikt!$AH$15:$AU$15))/14 -> 0.7 | R10: =1-SUMPRODUCT(ABS(Ongebruikt!$AH$10:$AU$10-Gebruikt!$AH$16:$AU$16))/14 -> 0.7 | S10: =1-SUMPRODUCT(ABS(Ongebruikt!$AH$10:$AU$10-Gebruikt!$AH$17:$AU$17))/14 -> 0.59285714 | T10: =1-SUMPRODUCT(ABS(Ongebruikt!$AH$10:$AU$10-Gebruikt!$AH$18:$AU$18))/14 -> 0.78571429 | U10: =1-SUMPRODUCT(ABS(Ongebruikt!$AH$10:$AU$10-Gebruikt!$AH$19:$AU$19))/14 -> 0.84285714 | V10: =1-SUMPRODUCT(ABS(Ongebruikt!$AH$10:$AU$10-Gebruikt!$AH$20:$AU$20))/14 -> 0.55714286 | W10: =1-SUMPRODUCT(ABS(Ongebruikt!$AH$10:$AU$10-Gebruikt!$AH$21:$AU$21))/14 -> 0.7 | X10: =1-SUMPRODUCT(ABS(Ongebruikt!$AH$10:$AU$10-Gebruikt!$AH$22:$AU$22))/14 -> 0.77857143 | Y10: =1-SUMPRODUCT(ABS(Ongebruikt!$AH$10:$AU$10-Gebruikt!$AH$23:$AU$23))/14 -> 0.73571429 | Z10: =1-SUMPRODUCT(ABS(Ongebruikt!$AH$10:$AU$10-Gebruikt!$AH$24:$AU$24))/14 -> 0.73571429 | AA10: =1-SUMPRODUCT(ABS(Ongebruikt!$AH$10:$AU$10-Gebruikt!$AH$25:$AU$25))/14 -> 0.95714286 | AB10: =1-SUMPRODUCT(ABS(Ongebruikt!$AH$10:$AU$10-Gebruikt!$AH$26:$AU$26))/14 -> 0.81428571 | AC10: =1-SUMPRODUCT(ABS(Ongebruikt!$AH$10:$AU$10-Gebruikt!$AH$27:$AU$27))/14 -> 0.85714286 | AD10: =1-SUMPRODUCT(ABS(Ongebruikt!$AH$10:$AU$10-Gebruikt!$AH$28:$AU$28))/14 -> 0.78571429 | AE10: =1-SUMPRODUCT(ABS(Ongebruikt!$AH$10:$AU$10-Gebruikt!$AH$29:$AU$29))/14 -> 0.59285714 | AF10: =1-SUMPRODUCT(ABS(Ongebruikt!$AH$10:$AU$10-Gebruikt!$AH$30:$AU$30))/14 -> 0.53571429 | AG10: =1-SUMPRODUCT(ABS(Ongebruikt!$AH$10:$AU$10-Gebruikt!$AH$31:$AU$31))/14 -> 0.85714286 | AH10: =1-SUMPRODUCT(ABS(Ongebruikt!$AH$10:$AU$10-Gebruikt!$AH$32:$AU$32))/14 -> 0.78571429 | AI10: =1-SUMPRODUCT(ABS(Ongebruikt!$AH$10:$AU$10-Gebruikt!$AH$33:$AU$33))/14 -> 0.59285714 | AJ10: =1-SUMPRODUCT(ABS(Ongebruikt!$AH$10:$AU$10-Gebruikt!$AH$34:$AU$34))/14 -> 0.7 | AK10: =1-SUMPRODUCT(ABS(Ongebruikt!$AH$10:$AU$10-Gebruikt!$AH$35:$AU$35))/14 -> 0.73571429 | AL10: =1-SUMPRODUCT(ABS(Ongebruikt!$AH$10:$AU$10-Gebruikt!$AH$36:$AU$36))/14 -> 0.85714286 | AM10: =1-SUMPRODUCT(ABS(Ongebruikt!$AH$10:$AU$10-Gebruikt!$AH$37:$AU$37))/14 -> 0.71428571 | AN10: =1-SUMPRODUCT(ABS(Ongebruikt!$AH$10:$AU$10-Gebruikt!$AH$38:$AU$38))/14 -> 0.59285714 | AO10: =1-SUMPRODUCT(ABS(Ongebruikt!$AH$10:$AU$10-Gebruikt!$AH$39:$AU$39))/14 -> 0.7 | AP10: =1-SUMPRODUCT(ABS(Ongebruikt!$AH$10:$AU$10-Gebruikt!$AH$40:$AU$40))/14 -> 0.55714286 | AQ10: =1-SUMPRODUCT(ABS(Ongebruikt!$AH$10:$AU$10-Gebruikt!$AH$41:$AU$41))/14 -> 0.60714286 | AR10: =1-SUMPRODUCT(ABS(Ongebruikt!$AH$10:$AU$10-Gebruikt!$AH$42:$AU$42))/14 -> 0.55714286 | AS10: =1-SUMPRODUCT(ABS(Ongebruikt!$AH$10:$AU$10-Gebruikt!$AH$43:$AU$43))/14 -> 0.59285714 | AT10: =1-SUMPRODUCT(ABS(Ongebruikt!$AH$10:$AU$10-Gebruikt!$AH$44:$AU$44))/14 -> 0.73571429 | AU10: =1-SUMPRODUCT(ABS(Ongebruikt!$AH$10:$AU$10-Gebruikt!$AH$45:$AU$45))/14 -> 0.59285714 | AV10: =1-SUMPRODUCT(ABS(Ongebruikt!$AH$10:$AU$10-Gebruikt!$AH$46:$AU$46))/14 -> 0.92142857 | AW10: =1-SUMPRODUCT(ABS(Ongebruikt!$AH$10:$AU$10-Gebruikt!$AH$47:$AU$47))/14 -> 0.55714286 | AX10: =1-SUMPRODUCT(ABS(Ongebruikt!$AH$10:$AU$10-Gebruikt!$AH$48:$AU$48))/14 -> 0.59285714
A11: =Ongebruikt!A11 -> U08 | B11: =Ongebruikt!B11 -> Spooky pebbling (measurement-based pebble game) | C11: =1-D11 -> 0.11428571 | D11: =MAX(F11:AX11) -> 0.88571429 | E11: =INDEX(Gebruikt!$B$4:$B$48,MATCH(D11,F11:AX11,0)) -> Conditional replay exploiting average-executed Toffoli | F11: =1-SUMPRODUCT(ABS(Ongebruikt!$AH$11:$AU$11-Gebruikt!$AH$4:$AU$4))/14 -> 0.72142857 | G11: =1-SUMPRODUCT(ABS(Ongebruikt!$AH$11:$AU$11-Gebruikt!$AH$5:$AU$5))/14 -> 0.70714286 | H11: =1-SUMPRODUCT(ABS(Ongebruikt!$AH$11:$AU$11-Gebruikt!$AH$6:$AU$6))/14 -> 0.70714286 | I11: =1-SUMPRODUCT(ABS(Ongebruikt!$AH$11:$AU$11-Gebruikt!$AH$7:$AU$7))/14 -> 0.70714286 | J11: =1-SUMPRODUCT(ABS(Ongebruikt!$AH$11:$AU$11-Gebruikt!$AH$8:$AU$8))/14 -> 0.67142857 | K11: =1-SUMPRODUCT(ABS(Ongebruikt!$AH$11:$AU$11-Gebruikt!$AH$9:$AU$9))/14 -> 0.67857143 | L11: =1-SUMPRODUCT(ABS(Ongebruikt!$AH$11:$AU$11-Gebruikt!$AH$10:$AU$10))/14 -> 0.67857143 | M11: =1-SUMPRODUCT(ABS(Ongebruikt!$AH$11:$AU$11-Gebruikt!$AH$11:$AU$11))/14 -> 0.67857143 | N11: =1-SUMPRODUCT(ABS(Ongebruikt!$AH$11:$AU$11-Gebruikt!$AH$12:$AU$12))/14 -> 0.78571429 | O11: =1-SUMPRODUCT(ABS(Ongebruikt!$AH$11:$AU$11-Gebruikt!$AH$13:$AU$13))/14 -> 0.40714286 | P11: =1-SUMPRODUCT(ABS(Ongebruikt!$AH$11:$AU$11-Gebruikt!$AH$14:$AU$14))/14 -> 0.60714286 | Q11: =1-SUMPRODUCT(ABS(Ongebruikt!$AH$11:$AU$11-Gebruikt!$AH$15:$AU$15))/14 -> 0.67857143 | R11: =1-SUMPRODUCT(ABS(Ongebruikt!$AH$11:$AU$11-Gebruikt!$AH$16:$AU$16))/14 -> 0.67857143 | S11: =1-SUMPRODUCT(ABS(Ongebruikt!$AH$11:$AU$11-Gebruikt!$AH$17:$AU$17))/14 -> 0.85714286 | T11: =1-SUMPRODUCT(ABS(Ongebruikt!$AH$11:$AU$11-Gebruikt!$AH$18:$AU$18))/14 -> 0.72142857 | U11: =1-SUMPRODUCT(ABS(Ongebruikt!$AH$11:$AU$11-Gebruikt!$AH$19:$AU$19))/14 -> 0.63571429 | V11: =1-SUMPRODUCT(ABS(Ongebruikt!$AH$11:$AU$11-Gebruikt!$AH$20:$AU$20))/14 -> 0.67857143 | W11: =1-SUMPRODUCT(ABS(Ongebruikt!$AH$11:$AU$11-Gebruikt!$AH$21:$AU$21))/14 -> 0.70714286 | X11: =1-SUMPRODUCT(ABS(Ongebruikt!$AH$11:$AU$11-Gebruikt!$AH$22:$AU$22))/14 -> 0.55714286 | Y11: =1-SUMPRODUCT(ABS(Ongebruikt!$AH$11:$AU$11-Gebruikt!$AH$23:$AU$23))/14 -> 0.67142857 | Z11: =1-SUMPRODUCT(ABS(Ongebruikt!$AH$11:$AU$11-Gebruikt!$AH$24:$AU$24))/14 -> 0.67142857 | AA11: =1-SUMPRODUCT(ABS(Ongebruikt!$AH$11:$AU$11-Gebruikt!$AH$25:$AU$25))/14 -> 0.55 | AB11: =1-SUMPRODUCT(ABS(Ongebruikt!$AH$11:$AU$11-Gebruikt!$AH$26:$AU$26))/14 -> 0.55 | AC11: =1-SUMPRODUCT(ABS(Ongebruikt!$AH$11:$AU$11-Gebruikt!$AH$27:$AU$27))/14 -> 0.47857143 | AD11: =1-SUMPRODUCT(ABS(Ongebruikt!$AH$11:$AU$11-Gebruikt!$AH$28:$AU$28))/14 -> 0.40714286 | AE11: =1-SUMPRODUCT(ABS(Ongebruikt!$AH$11:$AU$11-Gebruikt!$AH$29:$AU$29))/14 -> 0.88571429 | AF11: =1-SUMPRODUCT(ABS(Ongebruikt!$AH$11:$AU$11-Gebruikt!$AH$30:$AU$30))/14 -> 0.77142857 | AG11: =1-SUMPRODUCT(ABS(Ongebruikt!$AH$11:$AU$11-Gebruikt!$AH$31:$AU$31))/14 -> 0.65 | AH11: =1-SUMPRODUCT(ABS(Ongebruikt!$AH$11:$AU$11-Gebruikt!$AH$32:$AU$32))/14 -> 0.72142857 | AI11: =1-SUMPRODUCT(ABS(Ongebruikt!$AH$11:$AU$11-Gebruikt!$AH$33:$AU$33))/14 -> 0.74285714 | AJ11: =1-SUMPRODUCT(ABS(Ongebruikt!$AH$11:$AU$11-Gebruikt!$AH$34:$AU$34))/14 -> 0.70714286 | AK11: =1-SUMPRODUCT(ABS(Ongebruikt!$AH$11:$AU$11-Gebruikt!$AH$35:$AU$35))/14 -> 0.67142857 | AL11: =1-SUMPRODUCT(ABS(Ongebruikt!$AH$11:$AU$11-Gebruikt!$AH$36:$AU$36))/14 -> 0.65 | AM11: =1-SUMPRODUCT(ABS(Ongebruikt!$AH$11:$AU$11-Gebruikt!$AH$37:$AU$37))/14 -> 0.65 | AN11: =1-SUMPRODUCT(ABS(Ongebruikt!$AH$11:$AU$11-Gebruikt!$AH$38:$AU$38))/14 -> 0.88571429 | AO11: =1-SUMPRODUCT(ABS(Ongebruikt!$AH$11:$AU$11-Gebruikt!$AH$39:$AU$39))/14 -> 0.63571429 | AP11: =1-SUMPRODUCT(ABS(Ongebruikt!$AH$11:$AU$11-Gebruikt!$AH$40:$AU$40))/14 -> 0.67857143 | AQ11: =1-SUMPRODUCT(ABS(Ongebruikt!$AH$11:$AU$11-Gebruikt!$AH$41:$AU$41))/14 -> 0.7 | AR11: =1-SUMPRODUCT(ABS(Ongebruikt!$AH$11:$AU$11-Gebruikt!$AH$42:$AU$42))/14 -> 0.67857143 | AS11: =1-SUMPRODUCT(ABS(Ongebruikt!$AH$11:$AU$11-Gebruikt!$AH$43:$AU$43))/14 -> 0.71428571 | AT11: =1-SUMPRODUCT(ABS(Ongebruikt!$AH$11:$AU$11-Gebruikt!$AH$44:$AU$44))/14 -> 0.71428571 | AU11: =1-SUMPRODUCT(ABS(Ongebruikt!$AH$11:$AU$11-Gebruikt!$AH$45:$AU$45))/14 -> 0.71428571 | AV11: =1-SUMPRODUCT(ABS(Ongebruikt!$AH$11:$AU$11-Gebruikt!$AH$46:$AU$46))/14 -> 0.55714286 | AW11: =1-SUMPRODUCT(ABS(Ongebruikt!$AH$11:$AU$11-Gebruikt!$AH$47:$AU$47))/14 -> 0.67857143 | AX11: =1-SUMPRODUCT(ABS(Ongebruikt!$AH$11:$AU$11-Gebruikt!$AH$48:$AU$48))/14 -> 0.85714286
A12: =Ongebruikt!A12 -> U09 | B12: =Ongebruikt!B12 -> Knill optimal reversible pebbling | C12: =1-D12 -> 0.17857143 | D12: =MAX(F12:AX12) -> 0.82142857 | E12: =INDEX(Gebruikt!$B$4:$B$48,MATCH(D12,F12:AX12,0)) -> Exact AND cache in idle wires | F12: =1-SUMPRODUCT(ABS(Ongebruikt!$AH$12:$AU$12-Gebruikt!$AH$4:$AU$4))/14 -> 0.72857143 | G12: =1-SUMPRODUCT(ABS(Ongebruikt!$AH$12:$AU$12-Gebruikt!$AH$5:$AU$5))/14 -> 0.78571429 | H12: =1-SUMPRODUCT(ABS(Ongebruikt!$AH$12:$AU$12-Gebruikt!$AH$6:$AU$6))/14 -> 0.78571429 | I12: =1-SUMPRODUCT(ABS(Ongebruikt!$AH$12:$AU$12-Gebruikt!$AH$7:$AU$7))/14 -> 0.64285714 | J12: =1-SUMPRODUCT(ABS(Ongebruikt!$AH$12:$AU$12-Gebruikt!$AH$8:$AU$8))/14 -> 0.75 | K12: =1-SUMPRODUCT(ABS(Ongebruikt!$AH$12:$AU$12-Gebruikt!$AH$9:$AU$9))/14 -> 0.78571429 | L12: =1-SUMPRODUCT(ABS(Ongebruikt!$AH$12:$AU$12-Gebruikt!$AH$10:$AU$10))/14 -> 0.78571429 | M12: =1-SUMPRODUCT(ABS(Ongebruikt!$AH$12:$AU$12-Gebruikt!$AH$11:$AU$11))/14 -> 0.78571429 | N12: =1-SUMPRODUCT(ABS(Ongebruikt!$AH$12:$AU$12-Gebruikt!$AH$12:$AU$12))/14 -> 0.75 | O12: =1-SUMPRODUCT(ABS(Ongebruikt!$AH$12:$AU$12-Gebruikt!$AH$13:$AU$13))/14 -> 0.58571429 | P12: =1-SUMPRODUCT(ABS(Ongebruikt!$AH$12:$AU$12-Gebruikt!$AH$14:$AU$14))/14 -> 0.71428571 | Q12: =1-SUMPRODUCT(ABS(Ongebruikt!$AH$12:$AU$12-Gebruikt!$AH$15:$AU$15))/14 -> 0.78571429 | R12: =1-SUMPRODUCT(ABS(Ongebruikt!$AH$12:$AU$12-Gebruikt!$AH$16:$AU$16))/14 -> 0.78571429 | S12: =1-SUMPRODUCT(ABS(Ongebruikt!$AH$12:$AU$12-Gebruikt!$AH$17:$AU$17))/14 -> 0.67857143 | T12: =1-SUMPRODUCT(ABS(Ongebruikt!$AH$12:$AU$12-Gebruikt!$AH$18:$AU$18))/14 -> 0.72857143 | U12: =1-SUMPRODUCT(ABS(Ongebruikt!$AH$12:$AU$12-Gebruikt!$AH$19:$AU$19))/14 -> 0.78571429 | V12: =1-SUMPRODUCT(ABS(Ongebruikt!$AH$12:$AU$12-Gebruikt!$AH$20:$AU$20))/14 -> 0.78571429 | W12: =1-SUMPRODUCT(ABS(Ongebruikt!$AH$12:$AU$12-Gebruikt!$AH$21:$AU$21))/14 -> 0.78571429 | X12: =1-SUMPRODUCT(ABS(Ongebruikt!$AH$12:$AU$12-Gebruikt!$AH$22:$AU$22))/14 -> 0.57857143 | Y12: =1-SUMPRODUCT(ABS(Ongebruikt!$AH$12:$AU$12-Gebruikt!$AH$23:$AU$23))/14 -> 0.75 | Z12: =1-SUMPRODUCT(ABS(Ongebruikt!$AH$12:$AU$12-Gebruikt!$AH$24:$AU$24))/14 -> 0.75 | AA12: =1-SUMPRODUCT(ABS(Ongebruikt!$AH$12:$AU$12-Gebruikt!$AH$25:$AU$25))/14 -> 0.75714286 | AB12: =1-SUMPRODUCT(ABS(Ongebruikt!$AH$12:$AU$12-Gebruikt!$AH$26:$AU$26))/14 -> 0.61428571 | AC12: =1-SUMPRODUCT(ABS(Ongebruikt!$AH$12:$AU$12-Gebruikt!$AH$27:$AU$27))/14 -> 0.65714286 | AD12: =1-SUMPRODUCT(ABS(Ongebruikt!$AH$12:$AU$12-Gebruikt!$AH$28:$AU$28))/14 -> 0.58571429 | AE12: =1-SUMPRODUCT(ABS(Ongebruikt!$AH$12:$AU$12-Gebruikt!$AH$29:$AU$29))/14 -> 0.67857143 | AF12: =1-SUMPRODUCT(ABS(Ongebruikt!$AH$12:$AU$12-Gebruikt!$AH$30:$AU$30))/14 -> 0.62142857 | AG12: =1-SUMPRODUCT(ABS(Ongebruikt!$AH$12:$AU$12-Gebruikt!$AH$31:$AU$31))/14 -> 0.8 | AH12: =1-SUMPRODUCT(ABS(Ongebruikt!$AH$12:$AU$12-Gebruikt!$AH$32:$AU$32))/14 -> 0.72857143 | AI12: =1-SUMPRODUCT(ABS(Ongebruikt!$AH$12:$AU$12-Gebruikt!$AH$33:$AU$33))/14 -> 0.67857143 | AJ12: =1-SUMPRODUCT(ABS(Ongebruikt!$AH$12:$AU$12-Gebruikt!$AH$34:$AU$34))/14 -> 0.78571429 | AK12: =1-SUMPRODUCT(ABS(Ongebruikt!$AH$12:$AU$12-Gebruikt!$AH$35:$AU$35))/14 -> 0.75 | AL12: =1-SUMPRODUCT(ABS(Ongebruikt!$AH$12:$AU$12-Gebruikt!$AH$36:$AU$36))/14 -> 0.8 | AM12: =1-SUMPRODUCT(ABS(Ongebruikt!$AH$12:$AU$12-Gebruikt!$AH$37:$AU$37))/14 -> 0.65714286 | AN12: =1-SUMPRODUCT(ABS(Ongebruikt!$AH$12:$AU$12-Gebruikt!$AH$38:$AU$38))/14 -> 0.67857143 | AO12: =1-SUMPRODUCT(ABS(Ongebruikt!$AH$12:$AU$12-Gebruikt!$AH$39:$AU$39))/14 -> 0.64285714 | AP12: =1-SUMPRODUCT(ABS(Ongebruikt!$AH$12:$AU$12-Gebruikt!$AH$40:$AU$40))/14 -> 0.78571429 | AQ12: =1-SUMPRODUCT(ABS(Ongebruikt!$AH$12:$AU$12-Gebruikt!$AH$41:$AU$41))/14 -> 0.69285714 | AR12: =1-SUMPRODUCT(ABS(Ongebruikt!$AH$12:$AU$12-Gebruikt!$AH$42:$AU$42))/14 -> 0.78571429 | AS12: =1-SUMPRODUCT(ABS(Ongebruikt!$AH$12:$AU$12-Gebruikt!$AH$43:$AU$43))/14 -> 0.67857143 | AT12: =1-SUMPRODUCT(ABS(Ongebruikt!$AH$12:$AU$12-Gebruikt!$AH$44:$AU$44))/14 -> 0.82142857 | AU12: =1-SUMPRODUCT(ABS(Ongebruikt!$AH$12:$AU$12-Gebruikt!$AH$45:$AU$45))/14 -> 0.67857143 | AV12: =1-SUMPRODUCT(ABS(Ongebruikt!$AH$12:$AU$12-Gebruikt!$AH$46:$AU$46))/14 -> 0.72142857 | AW12: =1-SUMPRODUCT(ABS(Ongebruikt!$AH$12:$AU$12-Gebruikt!$AH$47:$AU$47))/14 -> 0.78571429 | AX12: =1-SUMPRODUCT(ABS(Ongebruikt!$AH$12:$AU$12-Gebruikt!$AH$48:$AU$48))/14 -> 0.67857143
A13: =Ongebruikt!A13 -> U10 | B13: =Ongebruikt!B13 -> SAT-based reversible pebbling (Meuli et al.) | C13: =1-D13 -> 0.16428571 | D13: =MAX(F13:AX13) -> 0.83571429 | E13: =INDEX(Gebruikt!$B$4:$B$48,MATCH(D13,F13:AX13,0)) -> Exact AND cache in idle wires | F13: =1-SUMPRODUCT(ABS(Ongebruikt!$AH$13:$AU$13-Gebruikt!$AH$4:$AU$4))/14 -> 0.74285714 | G13: =1-SUMPRODUCT(ABS(Ongebruikt!$AH$13:$AU$13-Gebruikt!$AH$5:$AU$5))/14 -> 0.82857143 | H13: =1-SUMPRODUCT(ABS(Ongebruikt!$AH$13:$AU$13-Gebruikt!$AH$6:$AU$6))/14 -> 0.82857143 | I13: =1-SUMPRODUCT(ABS(Ongebruikt!$AH$13:$AU$13-Gebruikt!$AH$7:$AU$7))/14 -> 0.68571429 | J13: =1-SUMPRODUCT(ABS(Ongebruikt!$AH$13:$AU$13-Gebruikt!$AH$8:$AU$8))/14 -> 0.79285714 | K13: =1-SUMPRODUCT(ABS(Ongebruikt!$AH$13:$AU$13-Gebruikt!$AH$9:$AU$9))/14 -> 0.8 | L13: =1-SUMPRODUCT(ABS(Ongebruikt!$AH$13:$AU$13-Gebruikt!$AH$10:$AU$10))/14 -> 0.8 | M13: =1-SUMPRODUCT(ABS(Ongebruikt!$AH$13:$AU$13-Gebruikt!$AH$11:$AU$11))/14 -> 0.8 | N13: =1-SUMPRODUCT(ABS(Ongebruikt!$AH$13:$AU$13-Gebruikt!$AH$12:$AU$12))/14 -> 0.76428571 | O13: =1-SUMPRODUCT(ABS(Ongebruikt!$AH$13:$AU$13-Gebruikt!$AH$13:$AU$13))/14 -> 0.6 | P13: =1-SUMPRODUCT(ABS(Ongebruikt!$AH$13:$AU$13-Gebruikt!$AH$14:$AU$14))/14 -> 0.72857143 | Q13: =1-SUMPRODUCT(ABS(Ongebruikt!$AH$13:$AU$13-Gebruikt!$AH$15:$AU$15))/14 -> 0.8 | R13: =1-SUMPRODUCT(ABS(Ongebruikt!$AH$13:$AU$13-Gebruikt!$AH$16:$AU$16))/14 -> 0.8 | S13: =1-SUMPRODUCT(ABS(Ongebruikt!$AH$13:$AU$13-Gebruikt!$AH$17:$AU$17))/14 -> 0.69285714 | T13: =1-SUMPRODUCT(ABS(Ongebruikt!$AH$13:$AU$13-Gebruikt!$AH$18:$AU$18))/14 -> 0.74285714 | U13: =1-SUMPRODUCT(ABS(Ongebruikt!$AH$13:$AU$13-Gebruikt!$AH$19:$AU$19))/14 -> 0.82857143 | V13: =1-SUMPRODUCT(ABS(Ongebruikt!$AH$13:$AU$13-Gebruikt!$AH$20:$AU$20))/14 -> 0.8 | W13: =1-SUMPRODUCT(ABS(Ongebruikt!$AH$13:$AU$13-Gebruikt!$AH$21:$AU$21))/14 -> 0.82857143 | X13: =1-SUMPRODUCT(ABS(Ongebruikt!$AH$13:$AU$13-Gebruikt!$AH$22:$AU$22))/14 -> 0.53571429 | Y13: =1-SUMPRODUCT(ABS(Ongebruikt!$AH$13:$AU$13-Gebruikt!$AH$23:$AU$23))/14 -> 0.79285714 | Z13: =1-SUMPRODUCT(ABS(Ongebruikt!$AH$13:$AU$13-Gebruikt!$AH$24:$AU$24))/14 -> 0.79285714 | AA13: =1-SUMPRODUCT(ABS(Ongebruikt!$AH$13:$AU$13-Gebruikt!$AH$25:$AU$25))/14 -> 0.74285714 | AB13: =1-SUMPRODUCT(ABS(Ongebruikt!$AH$13:$AU$13-Gebruikt!$AH$26:$AU$26))/14 -> 0.6 | AC13: =1-SUMPRODUCT(ABS(Ongebruikt!$AH$13:$AU$13-Gebruikt!$AH$27:$AU$27))/14 -> 0.67142857 | AD13: =1-SUMPRODUCT(ABS(Ongebruikt!$AH$13:$AU$13-Gebruikt!$AH$28:$AU$28))/14 -> 0.6 | AE13: =1-SUMPRODUCT(ABS(Ongebruikt!$AH$13:$AU$13-Gebruikt!$AH$29:$AU$29))/14 -> 0.72142857 | AF13: =1-SUMPRODUCT(ABS(Ongebruikt!$AH$13:$AU$13-Gebruikt!$AH$30:$AU$30))/14 -> 0.60714286 | AG13: =1-SUMPRODUCT(ABS(Ongebruikt!$AH$13:$AU$13-Gebruikt!$AH$31:$AU$31))/14 -> 0.81428571 | AH13: =1-SUMPRODUCT(ABS(Ongebruikt!$AH$13:$AU$13-Gebruikt!$AH$32:$AU$32))/14 -> 0.74285714 | AI13: =1-SUMPRODUCT(ABS(Ongebruikt!$AH$13:$AU$13-Gebruikt!$AH$33:$AU$33))/14 -> 0.72142857 | AJ13: =1-SUMPRODUCT(ABS(Ongebruikt!$AH$13:$AU$13-Gebruikt!$AH$34:$AU$34))/14 -> 0.82857143 | AK13: =1-SUMPRODUCT(ABS(Ongebruikt!$AH$13:$AU$13-Gebruikt!$AH$35:$AU$35))/14 -> 0.79285714 | AL13: =1-SUMPRODUCT(ABS(Ongebruikt!$AH$13:$AU$13-Gebruikt!$AH$36:$AU$36))/14 -> 0.81428571 | AM13: =1-SUMPRODUCT(ABS(Ongebruikt!$AH$13:$AU$13-Gebruikt!$AH$37:$AU$37))/14 -> 0.67142857 | AN13: =1-SUMPRODUCT(ABS(Ongebruikt!$AH$13:$AU$13-Gebruikt!$AH$38:$AU$38))/14 -> 0.72142857 | AO13: =1-SUMPRODUCT(ABS(Ongebruikt!$AH$13:$AU$13-Gebruikt!$AH$39:$AU$39))/14 -> 0.68571429 | AP13: =1-SUMPRODUCT(ABS(Ongebruikt!$AH$13:$AU$13-Gebruikt!$AH$40:$AU$40))/14 -> 0.8 | AQ13: =1-SUMPRODUCT(ABS(Ongebruikt!$AH$13:$AU$13-Gebruikt!$AH$41:$AU$41))/14 -> 0.67857143 | AR13: =1-SUMPRODUCT(ABS(Ongebruikt!$AH$13:$AU$13-Gebruikt!$AH$42:$AU$42))/14 -> 0.8 | AS13: =1-SUMPRODUCT(ABS(Ongebruikt!$AH$13:$AU$13-Gebruikt!$AH$43:$AU$43))/14 -> 0.69285714 | AT13: =1-SUMPRODUCT(ABS(Ongebruikt!$AH$13:$AU$13-Gebruikt!$AH$44:$AU$44))/14 -> 0.83571429 | AU13: =1-SUMPRODUCT(ABS(Ongebruikt!$AH$13:$AU$13-Gebruikt!$AH$45:$AU$45))/14 -> 0.69285714 | AV13: =1-SUMPRODUCT(ABS(Ongebruikt!$AH$13:$AU$13-Gebruikt!$AH$46:$AU$46))/14 -> 0.67857143 | AW13: =1-SUMPRODUCT(ABS(Ongebruikt!$AH$13:$AU$13-Gebruikt!$AH$47:$AU$47))/14 -> 0.8 | AX13: =1-SUMPRODUCT(ABS(Ongebruikt!$AH$13:$AU$13-Gebruikt!$AH$48:$AU$48))/14 -> 0.69285714
A14: =Ongebruikt!A14 -> U11 | B14: =Ongebruikt!B14 -> Coset representation of modular integers | C14: =1-D14 -> 0.13571429 | D14: =MAX(F14:AX14) -> 0.86428571 | E14: =INDEX(Gebruikt!$B$4:$B$48,MATCH(D14,F14:AX14,0)) -> Chunked/windowed adders with measured boundary-carry erasure | F14: =1-SUMPRODUCT(ABS(Ongebruikt!$AH$14:$AU$14-Gebruikt!$AH$4:$AU$4))/14 -> 0.68571429 | G14: =1-SUMPRODUCT(ABS(Ongebruikt!$AH$14:$AU$14-Gebruikt!$AH$5:$AU$5))/14 -> 0.77142857 | H14: =1-SUMPRODUCT(ABS(Ongebruikt!$AH$14:$AU$14-Gebruikt!$AH$6:$AU$6))/14 -> 0.77142857 | I14: =1-SUMPRODUCT(ABS(Ongebruikt!$AH$14:$AU$14-Gebruikt!$AH$7:$AU$7))/14 -> 0.77142857 | J14: =1-SUMPRODUCT(ABS(Ongebruikt!$AH$14:$AU$14-Gebruikt!$AH$8:$AU$8))/14 -> 0.80714286 | K14: =1-SUMPRODUCT(ABS(Ongebruikt!$AH$14:$AU$14-Gebruikt!$AH$9:$AU$9))/14 -> 0.74285714 | L14: =1-SUMPRODUCT(ABS(Ongebruikt!$AH$14:$AU$14-Gebruikt!$AH$10:$AU$10))/14 -> 0.74285714 | M14: =1-SUMPRODUCT(ABS(Ongebruikt!$AH$14:$AU$14-Gebruikt!$AH$11:$AU$11))/14 -> 0.74285714 | N14: =1-SUMPRODUCT(ABS(Ongebruikt!$AH$14:$AU$14-Gebruikt!$AH$12:$AU$12))/14 -> 0.63571429 | O14: =1-SUMPRODUCT(ABS(Ongebruikt!$AH$14:$AU$14-Gebruikt!$AH$13:$AU$13))/14 -> 0.85714286 | P14: =1-SUMPRODUCT(ABS(Ongebruikt!$AH$14:$AU$14-Gebruikt!$AH$14:$AU$14))/14 -> 0.81428571 | Q14: =1-SUMPRODUCT(ABS(Ongebruikt!$AH$14:$AU$14-Gebruikt!$AH$15:$AU$15))/14 -> 0.74285714 | R14: =1-SUMPRODUCT(ABS(Ongebruikt!$AH$14:$AU$14-Gebruikt!$AH$16:$AU$16))/14 -> 0.74285714 | S14: =1-SUMPRODUCT(ABS(Ongebruikt!$AH$14:$AU$14-Gebruikt!$AH$17:$AU$17))/14 -> 0.59285714 | T14: =1-SUMPRODUCT(ABS(Ongebruikt!$AH$14:$AU$14-Gebruikt!$AH$18:$AU$18))/14 -> 0.68571429 | U14: =1-SUMPRODUCT(ABS(Ongebruikt!$AH$14:$AU$14-Gebruikt!$AH$19:$AU$19))/14 -> 0.77142857 | V14: =1-SUMPRODUCT(ABS(Ongebruikt!$AH$14:$AU$14-Gebruikt!$AH$20:$AU$20))/14 -> 0.74285714 | W14: =1-SUMPRODUCT(ABS(Ongebruikt!$AH$14:$AU$14-Gebruikt!$AH$21:$AU$21))/14 -> 0.77142857 | X14: =1-SUMPRODUCT(ABS(Ongebruikt!$AH$14:$AU$14-Gebruikt!$AH$22:$AU$22))/14 -> 0.86428571 | Y14: =1-SUMPRODUCT(ABS(Ongebruikt!$AH$14:$AU$14-Gebruikt!$AH$23:$AU$23))/14 -> 0.80714286 | Z14: =1-SUMPRODUCT(ABS(Ongebruikt!$AH$14:$AU$14-Gebruikt!$AH$24:$AU$24))/14 -> 0.80714286 | AA14: =1-SUMPRODUCT(ABS(Ongebruikt!$AH$14:$AU$14-Gebruikt!$AH$25:$AU$25))/14 -> 0.82857143 | AB14: =1-SUMPRODUCT(ABS(Ongebruikt!$AH$14:$AU$14-Gebruikt!$AH$26:$AU$26))/14 -> 0.82857143 | AC14: =1-SUMPRODUCT(ABS(Ongebruikt!$AH$14:$AU$14-Gebruikt!$AH$27:$AU$27))/14 -> 0.78571429 | AD14: =1-SUMPRODUCT(ABS(Ongebruikt!$AH$14:$AU$14-Gebruikt!$AH$28:$AU$28))/14 -> 0.85714286 | AE14: =1-SUMPRODUCT(ABS(Ongebruikt!$AH$14:$AU$14-Gebruikt!$AH$29:$AU$29))/14 -> 0.59285714 | AF14: =1-SUMPRODUCT(ABS(Ongebruikt!$AH$14:$AU$14-Gebruikt!$AH$30:$AU$30))/14 -> 0.50714286 | AG14: =1-SUMPRODUCT(ABS(Ongebruikt!$AH$14:$AU$14-Gebruikt!$AH$31:$AU$31))/14 -> 0.75714286 | AH14: =1-SUMPRODUCT(ABS(Ongebruikt!$AH$14:$AU$14-Gebruikt!$AH$32:$AU$32))/14 -> 0.68571429 | AI14: =1-SUMPRODUCT(ABS(Ongebruikt!$AH$14:$AU$14-Gebruikt!$AH$33:$AU$33))/14 -> 0.73571429 | AJ14: =1-SUMPRODUCT(ABS(Ongebruikt!$AH$14:$AU$14-Gebruikt!$AH$34:$AU$34))/14 -> 0.77142857 | AK14: =1-SUMPRODUCT(ABS(Ongebruikt!$AH$14:$AU$14-Gebruikt!$AH$35:$AU$35))/14 -> 0.80714286 | AL14: =1-SUMPRODUCT(ABS(Ongebruikt!$AH$14:$AU$14-Gebruikt!$AH$36:$AU$36))/14 -> 0.75714286 | AM14: =1-SUMPRODUCT(ABS(Ongebruikt!$AH$14:$AU$14-Gebruikt!$AH$37:$AU$37))/14 -> 0.75714286 | AN14: =1-SUMPRODUCT(ABS(Ongebruikt!$AH$14:$AU$14-Gebruikt!$AH$38:$AU$38))/14 -> 0.59285714 | AO14: =1-SUMPRODUCT(ABS(Ongebruikt!$AH$14:$AU$14-Gebruikt!$AH$39:$AU$39))/14 -> 0.77142857 | AP14: =1-SUMPRODUCT(ABS(Ongebruikt!$AH$14:$AU$14-Gebruikt!$AH$40:$AU$40))/14 -> 0.74285714 | AQ14: =1-SUMPRODUCT(ABS(Ongebruikt!$AH$14:$AU$14-Gebruikt!$AH$41:$AU$41))/14 -> 0.57857143 | AR14: =1-SUMPRODUCT(ABS(Ongebruikt!$AH$14:$AU$14-Gebruikt!$AH$42:$AU$42))/14 -> 0.74285714 | AS14: =1-SUMPRODUCT(ABS(Ongebruikt!$AH$14:$AU$14-Gebruikt!$AH$43:$AU$43))/14 -> 0.73571429 | AT14: =1-SUMPRODUCT(ABS(Ongebruikt!$AH$14:$AU$14-Gebruikt!$AH$44:$AU$44))/14 -> 0.73571429 | AU14: =1-SUMPRODUCT(ABS(Ongebruikt!$AH$14:$AU$14-Gebruikt!$AH$45:$AU$45))/14 -> 0.73571429 | AV14: =1-SUMPRODUCT(ABS(Ongebruikt!$AH$14:$AU$14-Gebruikt!$AH$46:$AU$46))/14 -> 0.86428571 | AW14: =1-SUMPRODUCT(ABS(Ongebruikt!$AH$14:$AU$14-Gebruikt!$AH$47:$AU$47))/14 -> 0.74285714 | AX14: =1-SUMPRODUCT(ABS(Ongebruikt!$AH$14:$AU$14-Gebruikt!$AH$48:$AU$48))/14 -> 0.59285714
A15: =Ongebruikt!A15 -> U12 | B15: =Ongebruikt!B15 -> Oblivious carry runways (piecewise adders) | C15: =1-D15 -> 0.15 | D15: =MAX(F15:AX15) -> 0.85 | E15: =INDEX(Gebruikt!$B$4:$B$48,MATCH(D15,F15:AX15,0)) -> Chunked/windowed adders with measured boundary-carry erasure | F15: =1-SUMPRODUCT(ABS(Ongebruikt!$AH$15:$AU$15-Gebruikt!$AH$4:$AU$4))/14 -> 0.67142857 | G15: =1-SUMPRODUCT(ABS(Ongebruikt!$AH$15:$AU$15-Gebruikt!$AH$5:$AU$5))/14 -> 0.75714286 | H15: =1-SUMPRODUCT(ABS(Ongebruikt!$AH$15:$AU$15-Gebruikt!$AH$6:$AU$6))/14 -> 0.75714286 | I15: =1-SUMPRODUCT(ABS(Ongebruikt!$AH$15:$AU$15-Gebruikt!$AH$7:$AU$7))/14 -> 0.75714286 | J15: =1-SUMPRODUCT(ABS(Ongebruikt!$AH$15:$AU$15-Gebruikt!$AH$8:$AU$8))/14 -> 0.79285714 | K15: =1-SUMPRODUCT(ABS(Ongebruikt!$AH$15:$AU$15-Gebruikt!$AH$9:$AU$9))/14 -> 0.75714286 | L15: =1-SUMPRODUCT(ABS(Ongebruikt!$AH$15:$AU$15-Gebruikt!$AH$10:$AU$10))/14 -> 0.75714286 | M15: =1-SUMPRODUCT(ABS(Ongebruikt!$AH$15:$AU$15-Gebruikt!$AH$11:$AU$11))/14 -> 0.75714286 | N15: =1-SUMPRODUCT(ABS(Ongebruikt!$AH$15:$AU$15-Gebruikt!$AH$12:$AU$12))/14 -> 0.65 | O15: =1-SUMPRODUCT(ABS(Ongebruikt!$AH$15:$AU$15-Gebruikt!$AH$13:$AU$13))/14 -> 0.84285714 | P15: =1-SUMPRODUCT(ABS(Ongebruikt!$AH$15:$AU$15-Gebruikt!$AH$14:$AU$14))/14 -> 0.82857143 | Q15: =1-SUMPRODUCT(ABS(Ongebruikt!$AH$15:$AU$15-Gebruikt!$AH$15:$AU$15))/14 -> 0.75714286 | R15: =1-SUMPRODUCT(ABS(Ongebruikt!$AH$15:$AU$15-Gebruikt!$AH$16:$AU$16))/14 -> 0.75714286 | S15: =1-SUMPRODUCT(ABS(Ongebruikt!$AH$15:$AU$15-Gebruikt!$AH$17:$AU$17))/14 -> 0.60714286 | T15: =1-SUMPRODUCT(ABS(Ongebruikt!$AH$15:$AU$15-Gebruikt!$AH$18:$AU$18))/14 -> 0.67142857 | U15: =1-SUMPRODUCT(ABS(Ongebruikt!$AH$15:$AU$15-Gebruikt!$AH$19:$AU$19))/14 -> 0.75714286 | V15: =1-SUMPRODUCT(ABS(Ongebruikt!$AH$15:$AU$15-Gebruikt!$AH$20:$AU$20))/14 -> 0.75714286 | W15: =1-SUMPRODUCT(ABS(Ongebruikt!$AH$15:$AU$15-Gebruikt!$AH$21:$AU$21))/14 -> 0.75714286 | X15: =1-SUMPRODUCT(ABS(Ongebruikt!$AH$15:$AU$15-Gebruikt!$AH$22:$AU$22))/14 -> 0.85 | Y15: =1-SUMPRODUCT(ABS(Ongebruikt!$AH$15:$AU$15-Gebruikt!$AH$23:$AU$23))/14 -> 0.79285714 | Z15: =1-SUMPRODUCT(ABS(Ongebruikt!$AH$15:$AU$15-Gebruikt!$AH$24:$AU$24))/14 -> 0.79285714 | AA15: =1-SUMPRODUCT(ABS(Ongebruikt!$AH$15:$AU$15-Gebruikt!$AH$25:$AU$25))/14 -> 0.81428571 | AB15: =1-SUMPRODUCT(ABS(Ongebruikt!$AH$15:$AU$15-Gebruikt!$AH$26:$AU$26))/14 -> 0.81428571 | AC15: =1-SUMPRODUCT(ABS(Ongebruikt!$AH$15:$AU$15-Gebruikt!$AH$27:$AU$27))/14 -> 0.77142857 | AD15: =1-SUMPRODUCT(ABS(Ongebruikt!$AH$15:$AU$15-Gebruikt!$AH$28:$AU$28))/14 -> 0.84285714 | AE15: =1-SUMPRODUCT(ABS(Ongebruikt!$AH$15:$AU$15-Gebruikt!$AH$29:$AU$29))/14 -> 0.57857143 | AF15: =1-SUMPRODUCT(ABS(Ongebruikt!$AH$15:$AU$15-Gebruikt!$AH$30:$AU$30))/14 -> 0.52142857 | AG15: =1-SUMPRODUCT(ABS(Ongebruikt!$AH$15:$AU$15-Gebruikt!$AH$31:$AU$31))/14 -> 0.74285714 | AH15: =1-SUMPRODUCT(ABS(Ongebruikt!$AH$15:$AU$15-Gebruikt!$AH$32:$AU$32))/14 -> 0.67142857 | AI15: =1-SUMPRODUCT(ABS(Ongebruikt!$AH$15:$AU$15-Gebruikt!$AH$33:$AU$33))/14 -> 0.72142857 | AJ15: =1-SUMPRODUCT(ABS(Ongebruikt!$AH$15:$AU$15-Gebruikt!$AH$34:$AU$34))/14 -> 0.75714286 | AK15: =1-SUMPRODUCT(ABS(Ongebruikt!$AH$15:$AU$15-Gebruikt!$AH$35:$AU$35))/14 -> 0.79285714 | AL15: =1-SUMPRODUCT(ABS(Ongebruikt!$AH$15:$AU$15-Gebruikt!$AH$36:$AU$36))/14 -> 0.74285714 | AM15: =1-SUMPRODUCT(ABS(Ongebruikt!$AH$15:$AU$15-Gebruikt!$AH$37:$AU$37))/14 -> 0.74285714 | AN15: =1-SUMPRODUCT(ABS(Ongebruikt!$AH$15:$AU$15-Gebruikt!$AH$38:$AU$38))/14 -> 0.57857143 | AO15: =1-SUMPRODUCT(ABS(Ongebruikt!$AH$15:$AU$15-Gebruikt!$AH$39:$AU$39))/14 -> 0.75714286 | AP15: =1-SUMPRODUCT(ABS(Ongebruikt!$AH$15:$AU$15-Gebruikt!$AH$40:$AU$40))/14 -> 0.75714286 | AQ15: =1-SUMPRODUCT(ABS(Ongebruikt!$AH$15:$AU$15-Gebruikt!$AH$41:$AU$41))/14 -> 0.59285714 | AR15: =1-SUMPRODUCT(ABS(Ongebruikt!$AH$15:$AU$15-Gebruikt!$AH$42:$AU$42))/14 -> 0.75714286 | AS15: =1-SUMPRODUCT(ABS(Ongebruikt!$AH$15:$AU$15-Gebruikt!$AH$43:$AU$43))/14 -> 0.75 | AT15: =1-SUMPRODUCT(ABS(Ongebruikt!$AH$15:$AU$15-Gebruikt!$AH$44:$AU$44))/14 -> 0.75 | AU15: =1-SUMPRODUCT(ABS(Ongebruikt!$AH$15:$AU$15-Gebruikt!$AH$45:$AU$45))/14 -> 0.75 | AV15: =1-SUMPRODUCT(ABS(Ongebruikt!$AH$15:$AU$15-Gebruikt!$AH$46:$AU$46))/14 -> 0.85 | AW15: =1-SUMPRODUCT(ABS(Ongebruikt!$AH$15:$AU$15-Gebruikt!$AH$47:$AU$47))/14 -> 0.75714286 | AX15: =1-SUMPRODUCT(ABS(Ongebruikt!$AH$15:$AU$15-Gebruikt!$AH$48:$AU$48))/14 -> 0.60714286
A16: =Ongebruikt!A16 -> U13 | B16: =Ongebruikt!B16 -> Residue number system arithmetic | C16: =1-D16 -> 0.25714286 | D16: =MAX(F16:AX16) -> 0.74285714 | E16: =INDEX(Gebruikt!$B$4:$B$48,MATCH(D16,F16:AX16,0)) -> Chunked/windowed adders with measured boundary-carry erasure | F16: =1-SUMPRODUCT(ABS(Ongebruikt!$AH$16:$AU$16-Gebruikt!$AH$4:$AU$4))/14 -> 0.62142857 | G16: =1-SUMPRODUCT(ABS(Ongebruikt!$AH$16:$AU$16-Gebruikt!$AH$5:$AU$5))/14 -> 0.46428571 | H16: =1-SUMPRODUCT(ABS(Ongebruikt!$AH$16:$AU$16-Gebruikt!$AH$6:$AU$6))/14 -> 0.46428571 | I16: =1-SUMPRODUCT(ABS(Ongebruikt!$AH$16:$AU$16-Gebruikt!$AH$7:$AU$7))/14 -> 0.67857143 | J16: =1-SUMPRODUCT(ABS(Ongebruikt!$AH$16:$AU$16-Gebruikt!$AH$8:$AU$8))/14 -> 0.5 | K16: =1-SUMPRODUCT(ABS(Ongebruikt!$AH$16:$AU$16-Gebruikt!$AH$9:$AU$9))/14 -> 0.43571429 | L16: =1-SUMPRODUCT(ABS(Ongebruikt!$AH$16:$AU$16-Gebruikt!$AH$10:$AU$10))/14 -> 0.43571429 | M16: =1-SUMPRODUCT(ABS(Ongebruikt!$AH$16:$AU$16-Gebruikt!$AH$11:$AU$11))/14 -> 0.43571429 | N16: =1-SUMPRODUCT(ABS(Ongebruikt!$AH$16:$AU$16-Gebruikt!$AH$12:$AU$12))/14 -> 0.54285714 | O16: =1-SUMPRODUCT(ABS(Ongebruikt!$AH$16:$AU$16-Gebruikt!$AH$13:$AU$13))/14 -> 0.73571429 | P16: =1-SUMPRODUCT(ABS(Ongebruikt!$AH$16:$AU$16-Gebruikt!$AH$14:$AU$14))/14 -> 0.50714286 | Q16: =1-SUMPRODUCT(ABS(Ongebruikt!$AH$16:$AU$16-Gebruikt!$AH$15:$AU$15))/14 -> 0.43571429 | R16: =1-SUMPRODUCT(ABS(Ongebruikt!$AH$16:$AU$16-Gebruikt!$AH$16:$AU$16))/14 -> 0.43571429 | S16: =1-SUMPRODUCT(ABS(Ongebruikt!$AH$16:$AU$16-Gebruikt!$AH$17:$AU$17))/14 -> 0.61428571 | T16: =1-SUMPRODUCT(ABS(Ongebruikt!$AH$16:$AU$16-Gebruikt!$AH$18:$AU$18))/14 -> 0.62142857 | U16: =1-SUMPRODUCT(ABS(Ongebruikt!$AH$16:$AU$16-Gebruikt!$AH$19:$AU$19))/14 -> 0.53571429 | V16: =1-SUMPRODUCT(ABS(Ongebruikt!$AH$16:$AU$16-Gebruikt!$AH$20:$AU$20))/14 -> 0.43571429 | W16: =1-SUMPRODUCT(ABS(Ongebruikt!$AH$16:$AU$16-Gebruikt!$AH$21:$AU$21))/14 -> 0.46428571 | X16: =1-SUMPRODUCT(ABS(Ongebruikt!$AH$16:$AU$16-Gebruikt!$AH$22:$AU$22))/14 -> 0.74285714 | Y16: =1-SUMPRODUCT(ABS(Ongebruikt!$AH$16:$AU$16-Gebruikt!$AH$23:$AU$23))/14 -> 0.5 | Z16: =1-SUMPRODUCT(ABS(Ongebruikt!$AH$16:$AU$16-Gebruikt!$AH$24:$AU$24))/14 -> 0.5 | AA16: =1-SUMPRODUCT(ABS(Ongebruikt!$AH$16:$AU$16-Gebruikt!$AH$25:$AU$25))/14 -> 0.59285714 | AB16: =1-SUMPRODUCT(ABS(Ongebruikt!$AH$16:$AU$16-Gebruikt!$AH$26:$AU$26))/14 -> 0.73571429 | AC16: =1-SUMPRODUCT(ABS(Ongebruikt!$AH$16:$AU$16-Gebruikt!$AH$27:$AU$27))/14 -> 0.66428571 | AD16: =1-SUMPRODUCT(ABS(Ongebruikt!$AH$16:$AU$16-Gebruikt!$AH$28:$AU$28))/14 -> 0.73571429 | AE16: =1-SUMPRODUCT(ABS(Ongebruikt!$AH$16:$AU$16-Gebruikt!$AH$29:$AU$29))/14 -> 0.64285714 | AF16: =1-SUMPRODUCT(ABS(Ongebruikt!$AH$16:$AU$16-Gebruikt!$AH$30:$AU$30))/14 -> 0.67142857 | AG16: =1-SUMPRODUCT(ABS(Ongebruikt!$AH$16:$AU$16-Gebruikt!$AH$31:$AU$31))/14 -> 0.55 | AH16: =1-SUMPRODUCT(ABS(Ongebruikt!$AH$16:$AU$16-Gebruikt!$AH$32:$AU$32))/14 -> 0.62142857 | AI16: =1-SUMPRODUCT(ABS(Ongebruikt!$AH$16:$AU$16-Gebruikt!$AH$33:$AU$33))/14 -> 0.64285714 | AJ16: =1-SUMPRODUCT(ABS(Ongebruikt!$AH$16:$AU$16-Gebruikt!$AH$34:$AU$34))/14 -> 0.46428571 | AK16: =1-SUMPRODUCT(ABS(Ongebruikt!$AH$16:$AU$16-Gebruikt!$AH$35:$AU$35))/14 -> 0.5 | AL16: =1-SUMPRODUCT(ABS(Ongebruikt!$AH$16:$AU$16-Gebruikt!$AH$36:$AU$36))/14 -> 0.55 | AM16: =1-SUMPRODUCT(ABS(Ongebruikt!$AH$16:$AU$16-Gebruikt!$AH$37:$AU$37))/14 -> 0.69285714 | AN16: =1-SUMPRODUCT(ABS(Ongebruikt!$AH$16:$AU$16-Gebruikt!$AH$38:$AU$38))/14 -> 0.64285714 | AO16: =1-SUMPRODUCT(ABS(Ongebruikt!$AH$16:$AU$16-Gebruikt!$AH$39:$AU$39))/14 -> 0.67857143 | AP16: =1-SUMPRODUCT(ABS(Ongebruikt!$AH$16:$AU$16-Gebruikt!$AH$40:$AU$40))/14 -> 0.43571429 | AQ16: =1-SUMPRODUCT(ABS(Ongebruikt!$AH$16:$AU$16-Gebruikt!$AH$41:$AU$41))/14 -> 0.6 | AR16: =1-SUMPRODUCT(ABS(Ongebruikt!$AH$16:$AU$16-Gebruikt!$AH$42:$AU$42))/14 -> 0.43571429 | AS16: =1-SUMPRODUCT(ABS(Ongebruikt!$AH$16:$AU$16-Gebruikt!$AH$43:$AU$43))/14 -> 0.61428571 | AT16: =1-SUMPRODUCT(ABS(Ongebruikt!$AH$16:$AU$16-Gebruikt!$AH$44:$AU$44))/14 -> 0.47142857 | AU16: =1-SUMPRODUCT(ABS(Ongebruikt!$AH$16:$AU$16-Gebruikt!$AH$45:$AU$45))/14 -> 0.61428571 | AV16: =1-SUMPRODUCT(ABS(Ongebruikt!$AH$16:$AU$16-Gebruikt!$AH$46:$AU$46))/14 -> 0.6 | AW16: =1-SUMPRODUCT(ABS(Ongebruikt!$AH$16:$AU$16-Gebruikt!$AH$47:$AU$47))/14 -> 0.43571429 | AX16: =1-SUMPRODUCT(ABS(Ongebruikt!$AH$16:$AU$16-Gebruikt!$AH$48:$AU$48))/14 -> 0.61428571
A17: =Ongebruikt!A17 -> U14 | B17: =Ongebruikt!B17 -> Approximate residue arithmetic (truncated outputs) | C17: =1-D17 -> 0.14285714 | D17: =MAX(F17:AX17) -> 0.85714286 | E17: =INDEX(Gebruikt!$B$4:$B$48,MATCH(D17,F17:AX17,0)) -> Classical offset point held in classical bit registers | F17: =1-SUMPRODUCT(ABS(Ongebruikt!$AH$17:$AU$17-Gebruikt!$AH$4:$AU$4))/14 -> 0.49285714 | G17: =1-SUMPRODUCT(ABS(Ongebruikt!$AH$17:$AU$17-Gebruikt!$AH$5:$AU$5))/14 -> 0.65 | H17: =1-SUMPRODUCT(ABS(Ongebruikt!$AH$17:$AU$17-Gebruikt!$AH$6:$AU$6))/14 -> 0.65 | I17: =1-SUMPRODUCT(ABS(Ongebruikt!$AH$17:$AU$17-Gebruikt!$AH$7:$AU$7))/14 -> 0.79285714 | J17: =1-SUMPRODUCT(ABS(Ongebruikt!$AH$17:$AU$17-Gebruikt!$AH$8:$AU$8))/14 -> 0.61428571 | K17: =1-SUMPRODUCT(ABS(Ongebruikt!$AH$17:$AU$17-Gebruikt!$AH$9:$AU$9))/14 -> 0.62142857 | L17: =1-SUMPRODUCT(ABS(Ongebruikt!$AH$17:$AU$17-Gebruikt!$AH$10:$AU$10))/14 -> 0.62142857 | M17: =1-SUMPRODUCT(ABS(Ongebruikt!$AH$17:$AU$17-Gebruikt!$AH$11:$AU$11))/14 -> 0.62142857 | N17: =1-SUMPRODUCT(ABS(Ongebruikt!$AH$17:$AU$17-Gebruikt!$AH$12:$AU$12))/14 -> 0.72857143 | O17: =1-SUMPRODUCT(ABS(Ongebruikt!$AH$17:$AU$17-Gebruikt!$AH$13:$AU$13))/14 -> 0.63571429 | P17: =1-SUMPRODUCT(ABS(Ongebruikt!$AH$17:$AU$17-Gebruikt!$AH$14:$AU$14))/14 -> 0.69285714 | Q17: =1-SUMPRODUCT(ABS(Ongebruikt!$AH$17:$AU$17-Gebruikt!$AH$15:$AU$15))/14 -> 0.62142857 | R17: =1-SUMPRODUCT(ABS(Ongebruikt!$AH$17:$AU$17-Gebruikt!$AH$16:$AU$16))/14 -> 0.62142857 | S17: =1-SUMPRODUCT(ABS(Ongebruikt!$AH$17:$AU$17-Gebruikt!$AH$17:$AU$17))/14 -> 0.8 | T17: =1-SUMPRODUCT(ABS(Ongebruikt!$AH$17:$AU$17-Gebruikt!$AH$18:$AU$18))/14 -> 0.49285714 | U17: =1-SUMPRODUCT(ABS(Ongebruikt!$AH$17:$AU$17-Gebruikt!$AH$19:$AU$19))/14 -> 0.43571429 | V17: =1-SUMPRODUCT(ABS(Ongebruikt!$AH$17:$AU$17-Gebruikt!$AH$20:$AU$20))/14 -> 0.62142857 | W17: =1-SUMPRODUCT(ABS(Ongebruikt!$AH$17:$AU$17-Gebruikt!$AH$21:$AU$21))/14 -> 0.65 | X17: =1-SUMPRODUCT(ABS(Ongebruikt!$AH$17:$AU$17-Gebruikt!$AH$22:$AU$22))/14 -> 0.64285714 | Y17: =1-SUMPRODUCT(ABS(Ongebruikt!$AH$17:$AU$17-Gebruikt!$AH$23:$AU$23))/14 -> 0.61428571 | Z17: =1-SUMPRODUCT(ABS(Ongebruikt!$AH$17:$AU$17-Gebruikt!$AH$24:$AU$24))/14 -> 0.61428571 | AA17: =1-SUMPRODUCT(ABS(Ongebruikt!$AH$17:$AU$17-Gebruikt!$AH$25:$AU$25))/14 -> 0.46428571 | AB17: =1-SUMPRODUCT(ABS(Ongebruikt!$AH$17:$AU$17-Gebruikt!$AH$26:$AU$26))/14 -> 0.60714286 | AC17: =1-SUMPRODUCT(ABS(Ongebruikt!$AH$17:$AU$17-Gebruikt!$AH$27:$AU$27))/14 -> 0.56428571 | AD17: =1-SUMPRODUCT(ABS(Ongebruikt!$AH$17:$AU$17-Gebruikt!$AH$28:$AU$28))/14 -> 0.63571429 | AE17: =1-SUMPRODUCT(ABS(Ongebruikt!$AH$17:$AU$17-Gebruikt!$AH$29:$AU$29))/14 -> 0.82857143 | AF17: =1-SUMPRODUCT(ABS(Ongebruikt!$AH$17:$AU$17-Gebruikt!$AH$30:$AU$30))/14 -> 0.85714286 | AG17: =1-SUMPRODUCT(ABS(Ongebruikt!$AH$17:$AU$17-Gebruikt!$AH$31:$AU$31))/14 -> 0.42142857 | AH17: =1-SUMPRODUCT(ABS(Ongebruikt!$AH$17:$AU$17-Gebruikt!$AH$32:$AU$32))/14 -> 0.49285714 | AI17: =1-SUMPRODUCT(ABS(Ongebruikt!$AH$17:$AU$17-Gebruikt!$AH$33:$AU$33))/14 -> 0.82857143 | AJ17: =1-SUMPRODUCT(ABS(Ongebruikt!$AH$17:$AU$17-Gebruikt!$AH$34:$AU$34))/14 -> 0.65 | AK17: =1-SUMPRODUCT(ABS(Ongebruikt!$AH$17:$AU$17-Gebruikt!$AH$35:$AU$35))/14 -> 0.61428571 | AL17: =1-SUMPRODUCT(ABS(Ongebruikt!$AH$17:$AU$17-Gebruikt!$AH$36:$AU$36))/14 -> 0.42142857 | AM17: =1-SUMPRODUCT(ABS(Ongebruikt!$AH$17:$AU$17-Gebruikt!$AH$37:$AU$37))/14 -> 0.56428571 | AN17: =1-SUMPRODUCT(ABS(Ongebruikt!$AH$17:$AU$17-Gebruikt!$AH$38:$AU$38))/14 -> 0.82857143 | AO17: =1-SUMPRODUCT(ABS(Ongebruikt!$AH$17:$AU$17-Gebruikt!$AH$39:$AU$39))/14 -> 0.57857143 | AP17: =1-SUMPRODUCT(ABS(Ongebruikt!$AH$17:$AU$17-Gebruikt!$AH$40:$AU$40))/14 -> 0.62142857 | AQ17: =1-SUMPRODUCT(ABS(Ongebruikt!$AH$17:$AU$17-Gebruikt!$AH$41:$AU$41))/14 -> 0.78571429 | AR17: =1-SUMPRODUCT(ABS(Ongebruikt!$AH$17:$AU$17-Gebruikt!$AH$42:$AU$42))/14 -> 0.62142857 | AS17: =1-SUMPRODUCT(ABS(Ongebruikt!$AH$17:$AU$17-Gebruikt!$AH$43:$AU$43))/14 -> 0.8 | AT17: =1-SUMPRODUCT(ABS(Ongebruikt!$AH$17:$AU$17-Gebruikt!$AH$44:$AU$44))/14 -> 0.65714286 | AU17: =1-SUMPRODUCT(ABS(Ongebruikt!$AH$17:$AU$17-Gebruikt!$AH$45:$AU$45))/14 -> 0.8 | AV17: =1-SUMPRODUCT(ABS(Ongebruikt!$AH$17:$AU$17-Gebruikt!$AH$46:$AU$46))/14 -> 0.5 | AW17: =1-SUMPRODUCT(ABS(Ongebruikt!$AH$17:$AU$17-Gebruikt!$AH$47:$AU$47))/14 -> 0.62142857 | AX17: =1-SUMPRODUCT(ABS(Ongebruikt!$AH$17:$AU$17-Gebruikt!$AH$48:$AU$48))/14 -> 0.8
A18: =Ongebruikt!A18 -> U15 | B18: =Ongebruikt!B18 -> Ekera-Hastad short discrete-log runs | C18: =1-D18 -> 0.1 | D18: =MAX(F18:AX18) -> 0.9 | E18: =INDEX(Gebruikt!$B$4:$B$48,MATCH(D18,F18:AX18,0)) -> Classical prefilter + GPU nonce search pipeline | F18: =1-SUMPRODUCT(ABS(Ongebruikt!$AH$18:$AU$18-Gebruikt!$AH$4:$AU$4))/14 -> 0.5 | G18: =1-SUMPRODUCT(ABS(Ongebruikt!$AH$18:$AU$18-Gebruikt!$AH$5:$AU$5))/14 -> 0.87142857 | H18: =1-SUMPRODUCT(ABS(Ongebruikt!$AH$18:$AU$18-Gebruikt!$AH$6:$AU$6))/14 -> 0.87142857 | I18: =1-SUMPRODUCT(ABS(Ongebruikt!$AH$18:$AU$18-Gebruikt!$AH$7:$AU$7))/14 -> 0.65714286 | J18: =1-SUMPRODUCT(ABS(Ongebruikt!$AH$18:$AU$18-Gebruikt!$AH$8:$AU$8))/14 -> 0.83571429 | K18: =1-SUMPRODUCT(ABS(Ongebruikt!$AH$18:$AU$18-Gebruikt!$AH$9:$AU$9))/14 -> 0.75714286 | L18: =1-SUMPRODUCT(ABS(Ongebruikt!$AH$18:$AU$18-Gebruikt!$AH$10:$AU$10))/14 -> 0.75714286 | M18: =1-SUMPRODUCT(ABS(Ongebruikt!$AH$18:$AU$18-Gebruikt!$AH$11:$AU$11))/14 -> 0.75714286 | N18: =1-SUMPRODUCT(ABS(Ongebruikt!$AH$18:$AU$18-Gebruikt!$AH$12:$AU$12))/14 -> 0.65 | O18: =1-SUMPRODUCT(ABS(Ongebruikt!$AH$18:$AU$18-Gebruikt!$AH$13:$AU$13))/14 -> 0.52857143 | P18: =1-SUMPRODUCT(ABS(Ongebruikt!$AH$18:$AU$18-Gebruikt!$AH$14:$AU$14))/14 -> 0.82857143 | Q18: =1-SUMPRODUCT(ABS(Ongebruikt!$AH$18:$AU$18-Gebruikt!$AH$15:$AU$15))/14 -> 0.9 | R18: =1-SUMPRODUCT(ABS(Ongebruikt!$AH$18:$AU$18-Gebruikt!$AH$16:$AU$16))/14 -> 0.9 | S18: =1-SUMPRODUCT(ABS(Ongebruikt!$AH$18:$AU$18-Gebruikt!$AH$17:$AU$17))/14 -> 0.72142857 | T18: =1-SUMPRODUCT(ABS(Ongebruikt!$AH$18:$AU$18-Gebruikt!$AH$18:$AU$18))/14 -> 0.5 | U18: =1-SUMPRODUCT(ABS(Ongebruikt!$AH$18:$AU$18-Gebruikt!$AH$19:$AU$19))/14 -> 0.58571429 | V18: =1-SUMPRODUCT(ABS(Ongebruikt!$AH$18:$AU$18-Gebruikt!$AH$20:$AU$20))/14 -> 0.75714286 | W18: =1-SUMPRODUCT(ABS(Ongebruikt!$AH$18:$AU$18-Gebruikt!$AH$21:$AU$21))/14 -> 0.87142857 | X18: =1-SUMPRODUCT(ABS(Ongebruikt!$AH$18:$AU$18-Gebruikt!$AH$22:$AU$22))/14 -> 0.59285714 | Y18: =1-SUMPRODUCT(ABS(Ongebruikt!$AH$18:$AU$18-Gebruikt!$AH$23:$AU$23))/14 -> 0.83571429 | Z18: =1-SUMPRODUCT(ABS(Ongebruikt!$AH$18:$AU$18-Gebruikt!$AH$24:$AU$24))/14 -> 0.83571429 | AA18: =1-SUMPRODUCT(ABS(Ongebruikt!$AH$18:$AU$18-Gebruikt!$AH$25:$AU$25))/14 -> 0.67142857 | AB18: =1-SUMPRODUCT(ABS(Ongebruikt!$AH$18:$AU$18-Gebruikt!$AH$26:$AU$26))/14 -> 0.52857143 | AC18: =1-SUMPRODUCT(ABS(Ongebruikt!$AH$18:$AU$18-Gebruikt!$AH$27:$AU$27))/14 -> 0.6 | AD18: =1-SUMPRODUCT(ABS(Ongebruikt!$AH$18:$AU$18-Gebruikt!$AH$28:$AU$28))/14 -> 0.52857143 | AE18: =1-SUMPRODUCT(ABS(Ongebruikt!$AH$18:$AU$18-Gebruikt!$AH$29:$AU$29))/14 -> 0.69285714 | AF18: =1-SUMPRODUCT(ABS(Ongebruikt!$AH$18:$AU$18-Gebruikt!$AH$30:$AU$30))/14 -> 0.66428571 | AG18: =1-SUMPRODUCT(ABS(Ongebruikt!$AH$18:$AU$18-Gebruikt!$AH$31:$AU$31))/14 -> 0.57142857 | AH18: =1-SUMPRODUCT(ABS(Ongebruikt!$AH$18:$AU$18-Gebruikt!$AH$32:$AU$32))/14 -> 0.5 | AI18: =1-SUMPRODUCT(ABS(Ongebruikt!$AH$18:$AU$18-Gebruikt!$AH$33:$AU$33))/14 -> 0.69285714 | AJ18: =1-SUMPRODUCT(ABS(Ongebruikt!$AH$18:$AU$18-Gebruikt!$AH$34:$AU$34))/14 -> 0.87142857 | AK18: =1-SUMPRODUCT(ABS(Ongebruikt!$AH$18:$AU$18-Gebruikt!$AH$35:$AU$35))/14 -> 0.83571429 | AL18: =1-SUMPRODUCT(ABS(Ongebruikt!$AH$18:$AU$18-Gebruikt!$AH$36:$AU$36))/14 -> 0.57142857 | AM18: =1-SUMPRODUCT(ABS(Ongebruikt!$AH$18:$AU$18-Gebruikt!$AH$37:$AU$37))/14 -> 0.42857143 | AN18: =1-SUMPRODUCT(ABS(Ongebruikt!$AH$18:$AU$18-Gebruikt!$AH$38:$AU$38))/14 -> 0.69285714 | AO18: =1-SUMPRODUCT(ABS(Ongebruikt!$AH$18:$AU$18-Gebruikt!$AH$39:$AU$39))/14 -> 0.44285714 | AP18: =1-SUMPRODUCT(ABS(Ongebruikt!$AH$18:$AU$18-Gebruikt!$AH$40:$AU$40))/14 -> 0.75714286 | AQ18: =1-SUMPRODUCT(ABS(Ongebruikt!$AH$18:$AU$18-Gebruikt!$AH$41:$AU$41))/14 -> 0.73571429 | AR18: =1-SUMPRODUCT(ABS(Ongebruikt!$AH$18:$AU$18-Gebruikt!$AH$42:$AU$42))/14 -> 0.75714286 | AS18: =1-SUMPRODUCT(ABS(Ongebruikt!$AH$18:$AU$18-Gebruikt!$AH$43:$AU$43))/14 -> 0.72142857 | AT18: =1-SUMPRODUCT(ABS(Ongebruikt!$AH$18:$AU$18-Gebruikt!$AH$44:$AU$44))/14 -> 0.86428571 | AU18: =1-SUMPRODUCT(ABS(Ongebruikt!$AH$18:$AU$18-Gebruikt!$AH$45:$AU$45))/14 -> 0.72142857 | AV18: =1-SUMPRODUCT(ABS(Ongebruikt!$AH$18:$AU$18-Gebruikt!$AH$46:$AU$46))/14 -> 0.73571429 | AW18: =1-SUMPRODUCT(ABS(Ongebruikt!$AH$18:$AU$18-Gebruikt!$AH$47:$AU$47))/14 -> 0.75714286 | AX18: =1-SUMPRODUCT(ABS(Ongebruikt!$AH$18:$AU$18-Gebruikt!$AH$48:$AU$48))/14 -> 0.72142857
